Workbook
Name LISTA: Productos!$G$2:$G$3564

Sheet Productos
D1: IMAGEN | N1: Jul21-Mar22 | O1: Abr22-Feb23 | P1: Feb23-Mar24 | Q1: Mar24-Sep24 | R1: Sep24-Feb25 | S1: Lista Feb 2025 | W1: 0.05 | Z1: 0.1 | AC1: 0.15 | AF1: 0.17 | AI1: 0.2 | AL1: FORMULA QUE DEBE IR EN LA CELDA AN3 (DE AQUI SALEN LOS ESPEJOS =FILTER(A:AM,A:A=1) | AO1: IMAGEN | AY1: Ene21-Jun21 | AZ1: Jul21-Mar22 | BA1: Abr22-Feb23 | BB1: Feb23-Mar24 | BC1: Mar24-Sep24 | BD1: Lista 2024 oct | BH1: 0.05 | BK1: 0.1 | BN1: 0.15 | BQ1: 0.17 | BT1: 0.2
A2: V | B2: T | C2: C | D2: CLAVE | E2: UD | F2: LINEA | G2: DESCRIPCIÓN LARGA | H2: DESCRIPCIÓN CORTA | I2: C | J2: MIN | K2: MAX | L2: SISTEMAS | M2: VACIO | N2: PRECIO DE LISTA (1) | O2: PRECIO DE LISTA (1) | P2: PRECIO DE LISTA (1) | Q2: PRECIO DE LISTA (1) | R2: PRECIO DE LISTA (1) | S2: PRECIO DE LISTA (1) | T2: IVA | U2: TOTAL | V2: Dif respecto al precio anterior | W2: PRECIO MAYOREO (2) | X2: IVA | Y2: TOTAL | Z2: PRECIO MECÁNICOS (3) | AA2: IVA | AB2: TOTAL | AC2: PRECIO DISTRIBUIDOR A (4) | AD2: IVA | AE2: TOTAL | AF2: PRECIO DISTRIBUIDOR B (5) | AG2: IVA | AH2: TOTAL | AI2: PRECIO SUCURSAL (6) | AJ2: IVA | AK2: TOTAL | AL2: V | AM2: T | AN2: C | AO2: CLAVE | AP2: UD | AQ2: LINEA | AR2: DESCRIPCIÓN LARGA | AS2: DESCRIPCIÓN CORTA | AT2: C | AU2: MIN | AV2: MAX | AW2: SISTEMAS | AX2: VACIO | AY2: PRECIO DE LISTA (1) | AZ2: PRECIO DE LISTA (1) | BA2: PRECIO DE LISTA (1) | BB2: PRECIO DE LISTA (1) | BC2: PRECIO DE LISTA (1) | BD2: PRECIO DE LISTA (1) | BE2: IVA | BF2: TOTAL | BG2: Dif respecto al precio anterior | BH2: PRECIO MAYOREO (4) | BI2: IVA | BJ2: TOTAL | BK2: PRECIO MECÁNICOS (5) | BL2: IVA | BM2: TOTAL | BN2: PRECIO DISTRIBUIDOR A (6) | BO2: IVA | BP2: TOTAL | BQ2: PRECIO DISTRIBUIDOR B (7) | BR2: IVA | BS2: TOTAL | BT2: PRECIO SUCURSAL (8) | BU2: IVA | BV2: TOTAL
C3: E | D3: AB01 | E3: PZA | F3: WAL | G3: ABRAZADERA ACERO INOXIDABLE 6" CLAMP | I3: =IF(D3="","",LEN(H3)) -> 0 | O3: 1074 | P3: 1220 | Q3: 1220 | R3: 1281 | S3: 1345 | T3: =S3*0.16 -> 215.2 | U3: =S3+T3 -> 1560.2 | V3: =(S3-R3)/R3 -> 0.049960968 | W3: =(IF(B3="",(S3*(1-$W$1)),(IF(B3=1,(S3*(1-$W$1)),(IF(B3=2,(S3*(1-$W$1)),(IF(B3=3,(S3*(1-$W$1)),(IF(B3=4,(S3*(1)))))))))))) -> 1277.75 | X3: =W3*0.16 -> 204.44 | Y3: =W3+X3 -> 1482.19 | Z3: =(IF(B3="",(S3*(1-$Z$1)),(IF(B3=1,(S3*(1-$Z$1)),(IF(B3=2,(S3*(1-$Z$1)),(IF(B3=3,(S3*(1-$Z$1)),(IF(B3=4,(S3*(1)))))))))))) -> 1210.5 | AA3: =Z3*0.16 -> 193.68 | AB3: =Z3+AA3 -> 1404.18 | AC3: =(IF(B3="",(S3*(1-$AC$1)),(IF(B3=1,(S3*(1-$AC$1)),(IF(B3=2,(S3*(1-0.15)),(IF(B3=3,(S3*(1-0.1)),(IF(B3=4,(S3*(1)))))))))))) -> 1143.25 | AD3: =AC3*0.16 -> 182.92 | AE3: =AC3+AD3 -> 1326.17 | AF3: =(IF(B3="",(S3*(1-$AF$1)),(IF(B3=1,(S3*(1-$AF$1)),(IF(B3=2,(S3*(1-0.15)),(IF(B3=3,(S3*(1-0.1)),(IF(B3=4,(S3*(1)))))))))))) -> 1116.35 | AG3: =AF3*0.16 -> 178.616 | AH3: =AF3+AG3 -> 1294.966 | AI3: =(IF(B3="",(S3*(1-$AI$1)),(IF(B3=1,(S3*(1-$AI$1)),(IF(B3=2,(S3*(1-0.15)),(IF(B3=3,(S3*(1-0.1)),(IF(B3=4,(S3*(1)))))))))))) -> 1076 | AJ3: =AI3*0.16 -> 172.16 | AK3: =AI3+AJ3 -> 1248.16 | AL3: =IFERROR(__xludf.DUMMYFUNCTION("FILTER(A:AK,A:A=1)"),1.0) -> 1 | AN3: =IFERROR(__xludf.DUMMYFUNCTION("""COMPUTED_VALUE""")," C") -> C | AO3: =IFERROR(__xludf.DUMMYFUNCTION("""COMPUTED_VALUE""")," AC02") -> AC02 | AP3: =IFERROR(__xludf.DUMMYFUNCTION("""COMPUTED_VALUE""")," PZA") -> PZA | AQ3: =IFERROR(__xludf.DUMMYFUNCTION("""COMPUTED_VALUE""")," REF") -> REF | AR3: =IFERROR(__xludf.DUMMYFUNCTION("""COMPUTED_VALUE""")," ACEITE SAE BARDAHL 40") -> ACEITE SAE BARDAHL 40 | AS3: =IFERROR(__xludf.DUMMYFUNCTION("""COMPUTED_VALUE""")," ACEITE SAE BARDAHL 40") -> ACEITE SAE BARDAHL 40 | AT3: =IFERROR(__xludf.DUMMYFUNCTION("""COMPUTED_VALUE"""),21.0) -> 21 | AY3: =IFERROR(__xludf.DUMMYFUNCTION("""COMPUTED_VALUE"""),100.0) -> 100 | AZ3: =IFERROR(__xludf.DUMMYFUNCTION("""COMPUTED_VALUE"""),108.0) -> 108 | BA3: =IFERROR(__xludf.DUMMYFUNCTION("""COMPUTED_VALUE"""),134.78) -> 134.78 | BB3: =IFERROR(__xludf.DUMMYFUNCTION("""COMPUTED_VALUE"""),134.78) -> 134.78 | BC3: =IFERROR(__xludf.DUMMYFUNCTION("""COMPUTED_VALUE"""),130.0) -> 130 | BD3: =IFERROR(__xludf.DUMMYFUNCTION("""COMPUTED_VALUE"""),137.0) -> 137 | BE3: =IFERROR(__xludf.DUMMYFUNCTION("""COMPUTED_VALUE"""),21.92) -> 21.92 | BF3: =IFERROR(__xludf.DUMMYFUNCTION("""COMPUTED_VALUE"""),158.92000000000002) -> 158.92 | BG3: =IFERROR(__xludf.DUMMYFUNCTION("""COMPUTED_VALUE"""),0.05384615384615385) -> 0.053846154 | BH3: =IFERROR(__xludf.DUMMYFUNCTION("""COMPUTED_VALUE"""),130.15) -> 130.15 | BI3: =IFERROR(__xludf.DUMMYFUNCTION("""COMPUTED_VALUE"""),20.824) -> 20.824 | BJ3: =IFERROR(__xludf.DUMMYFUNCTION("""COMPUTED_VALUE"""),150.97400000000002) -> 150.974 | BK3: =IFERROR(__xludf.DUMMYFUNCTION("""COMPUTED_VALUE"""),123.3) -> 123.3 | BL3: =IFERROR(__xludf.DUMMYFUNCTION("""COMPUTED_VALUE"""),19.728) -> 19.728 | BM3: =IFERROR(__xludf.DUMMYFUNCTION("""COMPUTED_VALUE"""),143.028) -> 143.028 | BN3: =IFERROR(__xludf.DUMMYFUNCTION("""COMPUTED_VALUE"""),116.45) -> 116.45 | BO3: =IFERROR(__xludf.DUMMYFUNCTION("""COMPUTED_VALUE"""),18.632) -> 18.632 | BP3: =IFERROR(__xludf.DUMMYFUNCTION("""COMPUTED_VALUE"""),135.082) -> 135.082 | BQ3: =IFERROR(__xludf.DUMMYFUNCTION("""COMPUTED_VALUE"""),113.71) -> 113.71 | BR3: =IFERROR(__xludf.DUMMYFUNCTION("""COMPUTED_VALUE"""),18.1936) -> 18.1936 | BS3: =IFERROR(__xludf.DUMMYFUNCTION("""COMPUTED_VALUE"""),131.90359999999998) -> 131.9036 | BT3: =IFERROR(__xludf.DUMMYFUNCTION("""COMPUTED_VALUE"""),109.60000000000001) -> 109.6 | BU3: =IFERROR(__xludf.DUMMYFUNCTION("""COMPUTED_VALUE"""),17.536) -> 17.536 | BV3: =IFERROR(__xludf.DUMMYFUNCTION("""COMPUTED_VALUE"""),127.13600000000001) -> 127.136
C4: C | D4: AC01 | E4: PZA | F4: REF | G4: ACEITE ROSHFRANS ESTÁNDAR 250 | H4: ACEITE ROSHFRANS ESTANDAR 250 | I4: =IF(D4="","",LEN(H4)) -> 29 | N4: 88 | O4: 126 | P4: 136.08 | Q4: 136.08 | R4: 144 | S4: 151 | T4: =S4*0.16 -> 24.16 | U4: =S4+T4 -> 175.16 | V4: =(S4-R4)/R4 -> 0.048611111 | W4: =(IF(B4="",(S4*(1-$W$1)),(IF(B4=1,(S4*(1-$W$1)),(IF(B4=2,(S4*(1-$W$1)),(IF(B4=3,(S4*(1-$W$1)),(IF(B4=4,(S4*(1)))))))))))) -> 143.45 | X4: =W4*0.16 -> 22.952 | Y4: =W4+X4 -> 166.402 | Z4: =(IF(B4="",(S4*(1-$Z$1)),(IF(B4=1,(S4*(1-$Z$1)),(IF(B4=2,(S4*(1-$Z$1)),(IF(B4=3,(S4*(1-$Z$1)),(IF(B4=4,(S4*(1)))))))))))) -> 135.9 | AA4: =Z4*0.16 -> 21.744 | AB4: =Z4+AA4 -> 157.644 | AC4: =(IF(B4="",(S4*(1-$AC$1)),(IF(B4=1,(S4*(1-$AC$1)),(IF(B4=2,(S4*(1-0.15)),(IF(B4=3,(S4*(1-0.1)),(IF(B4=4,(S4*(1)))))))))))) -> 128.35 | AD4: =AC4*0.16 -> 20.536 | AE4: =AC4+AD4 -> 148.886 | AF4: =(IF(B4="",(S4*(1-$AF$1)),(IF(B4=1,(S4*(1-$AF$1)),(IF(B4=2,(S4*(1-0.15)),(IF(B4=3,(S4*(1-0.1)),(IF(B4=4,(S4*(1)))))))))))) -> 125.33 | AG4: =AF4*0.16 -> 20.0528 | AH4: =AF4+AG4 -> 145.3828 | AI4: =(IF(B4="",(S4*(1-$AI$1)),(IF(B4=1,(S4*(1-$AI$1)),(IF(B4=2,(S4*(1-0.15)),(IF(B4=3,(S4*(1-0.1)),(IF(B4=4,(S4*(1)))))))))))) -> 120.8 | AJ4: =AI4*0.16 -> 19.328 | AK4: =AI4+AJ4 -> 140.128 | AL4: =IFERROR(__xludf.DUMMYFUNCTION("""COMPUTED_VALUE"""),1.0) -> 1 | AM4: =IFERROR(__xludf.DUMMYFUNCTION("""COMPUTED_VALUE"""),2.0) -> 2 | AN4: =IFERROR(__xludf.DUMMYFUNCTION("""COMPUTED_VALUE""")," C") -> C | AO4: =IFERROR(__xludf.DUMMYFUNCTION("""COMPUTED_VALUE""")," AE01") -> AE01 | AP4: =IFERROR(__xludf.DUMMYFUNCTION("""COMPUTED_VALUE""")," PZA") -> PZA | AQ4: =IFERROR(__xludf.DUMMYFUNCTION("""COMPUTED_VALUE""")," REF") -> REF | AR4: =IFERROR(__xludf.DUMMYFUNCTION("""COMPUTED_VALUE""")," ACEITERA DE PIPETA FLEXIBLE 300 ML. TRUPER") -> ACEITERA DE PIPETA FLEXIBLE 300 ML. TRUPER | AS4: =IFERROR(__xludf.DUMMYFUNCTION("""COMPUTED_VALUE""")," ACEITERA PIPETA FLEXIBLE 300 ML TRUPER") -> ACEITERA PIPETA FLEXIBLE 300 ML TRUPER | AT4: =IFERROR(__xludf.DUMMYFUNCTION("""COMPUTED_VALUE"""),38.0) -> 38 | AY4: =IFERROR(__xludf.DUMMYFUNCTION("""COMPUTED_VALUE"""),103.0) -> 103 | AZ4: =IFERROR(__xludf.DUMMYFUNCTION("""COMPUTED_VALUE"""),111.0) -> 111 | BA4: =IFERROR(__xludf.DUMMYFUNCTION("""COMPUTED_VALUE"""),119.88000000000001) -> 119.88 | BB4: =IFERROR(__xludf.DUMMYFUNCTION("""COMPUTED_VALUE"""),119.88000000000001) -> 119.88 | BC4: =IFERROR(__xludf.DUMMYFUNCTION("""COMPUTED_VALUE"""),135.0) -> 135 | BD4: =IFERROR(__xludf.DUMMYFUNCTION("""COMPUTED_VALUE"""),142.0) -> 142 | BE4: =IFERROR(__xludf.DUMMYFUNCTION("""COMPUTED_VALUE"""),22.72) -> 22.72 | BF4: =IFERROR(__xludf.DUMMYFUNCTION("""COMPUTED_VALUE"""),164.72) -> 164.72 | BG4: =IFERROR(__xludf.DUMMYFUNCTION("""COMPUTED_VALUE"""),0.05185185185185185) -> 0.051851852 | BH4: =IFERROR(__xludf.DUMMYFUNCTION("""COMPUTED_VALUE"""),134.9) -> 134.9 | BI4: =IFERROR(__xludf.DUMMYFUNCTION("""COMPUTED_VALUE"""),21.584) -> 21.584 | BJ4: =IFERROR(__xludf.DUMMYFUNCTION("""COMPUTED_VALUE"""),156.484) -> 156.484 | BK4: =IFERROR(__xludf.DUMMYFUNCTION("""COMPUTED_VALUE"""),127.8) -> 127.8 | BL4: =IFERROR(__xludf.DUMMYFUNCTION("""COMPUTED_VALUE"""),20.448) -> 20.448 | BM4: =IFERROR(__xludf.DUMMYFUNCTION("""COMPUTED_VALUE"""),148.248) -> 148.248 | BN4: =IFERROR(__xludf.DUMMYFUNCTION("""COMPUTED_VALUE"""),120.7) -> 120.7 | BO4: =IFERROR(__xludf.DUMMYFUNCTION("""COMPUTED_VALUE"""),19.312) -> 19.312 | BP4: =IFERROR(__xludf.DUMMYFUNCTION("""COMPUTED_VALUE"""),140.012) -> 140.012 | BQ4: =IFERROR(__xludf.DUMMYFUNCTION("""COMPUTED_VALUE"""),120.7) -> 120.7 | BR4: =IFERROR(__xludf.DUMMYFUNCTION("""COMPUTED_VALUE"""),19.312) -> 19.312 | BS4: =IFERROR(__xludf.DUMMYFUNCTION("""COMPUTED_VALUE"""),140.012) -> 140.012 | BT4: =IFERROR(__xludf.DUMMYFUNCTION("""COMPUTED_VALUE"""),120.7) -> 120.7 | BU4: =IFERROR(__xludf.DUMMYFUNCTION("""COMPUTED_VALUE"""),19.312) -> 19.312 | BV4: =IFERROR(__xludf.DUMMYFUNCTION("""COMPUTED_VALUE"""),140.012) -> 140.012
A5: 1 | C5: C | D5: AC02 | E5: PZA | F5: REF | G5: ACEITE SAE BARDAHL 40 | H5: =G5 -> ACEITE SAE BARDAHL 40 | I5: =IF(D5="","",LEN(H5)) -> 21 | N5: 100 | O5: 108 | P5: 134.78 | Q5: 134.78 | R5: 130 | S5: 137 | T5: =S5*0.16 -> 21.92 | U5: =S5+T5 -> 158.92 | V5: =(S5-R5)/R5 -> 0.053846154 | W5: =(IF(B5="",(S5*(1-$W$1)),(IF(B5=1,(S5*(1-$W$1)),(IF(B5=2,(S5*(1-$W$1)),(IF(B5=3,(S5*(1-$W$1)),(IF(B5=4,(S5*(1)))))))))))) -> 130.15 | X5: =W5*0.16 -> 20.824 | Y5: =W5+X5 -> 150.974 | Z5: =(IF(B5="",(S5*(1-$Z$1)),(IF(B5=1,(S5*(1-$Z$1)),(IF(B5=2,(S5*(1-$Z$1)),(IF(B5=3,(S5*(1-$Z$1)),(IF(B5=4,(S5*(1)))))))))))) -> 123.3 | AA5: =Z5*0.16 -> 19.728 | AB5: =Z5+AA5 -> 143.028 | AC5: =(IF(B5="",(S5*(1-$AC$1)),(IF(B5=1,(S5*(1-$AC$1)),(IF(B5=2,(S5*(1-0.15)),(IF(B5=3,(S5*(1-0.1)),(IF(B5=4,(S5*(1)))))))))))) -> 116.45 | AD5: =AC5*0.16 -> 18.632 | AE5: =AC5+AD5 -> 135.082 | AF5: =(IF(B5="",(S5*(1-$AF$1)),(IF(B5=1,(S5*(1-$AF$1)),(IF(B5=2,(S5*(1-0.15)),(IF(B5=3,(S5*(1-0.1)),(IF(B5=4,(S5*(1)))))))))))) -> 113.71 | AG5: =AF5*0.16 -> 18.1936 | AH5: =AF5+AG5 -> 131.9036 | AI5: =(IF(B5="",(S5*(1-$AI$1)),(IF(B5=1,(S5*(1-$AI$1)),(IF(B5=2,(S5*(1-0.15)),(IF(B5=3,(S5*(1-0.1)),(IF(B5=4,(S5*(1)))))))))))) -> 109.6 | AJ5: =AI5*0.16 -> 17.536 | AK5: =AI5+AJ5 -> 127.136 | AL5: =IFERROR(__xludf.DUMMYFUNCTION("""COMPUTED_VALUE"""),1.0) -> 1 | AM5: =IFERROR(__xludf.DUMMYFUNCTION("""COMPUTED_VALUE"""),2.0) -> 2 | AN5: =IFERROR(__xludf.DUMMYFUNCTION("""COMPUTED_VALUE""")," C") -> C | AO5: =IFERROR(__xludf.DUMMYFUNCTION("""COMPUTED_VALUE""")," AE02") -> AE02 | AP5: =IFERROR(__xludf.DUMMYFUNCTION("""COMPUTED_VALUE""")," PZA") -> PZA | AQ5: =IFERROR(__xludf.DUMMYFUNCTION("""COMPUTED_VALUE""")," REF") -> REF | AR5: =IFERROR(__xludf.DUMMYFUNCTION("""COMPUTED_VALUE""")," ACEITERA DE PIPETA FLEXIBLE 500 ML. TRUPER") -> ACEITERA DE PIPETA FLEXIBLE 500 ML. TRUPER | AS5: =IFERROR(__xludf.DUMMYFUNCTION("""COMPUTED_VALUE""")," ACEITERA PIPETA FLEXIBLE 500 ML TRUPER") -> ACEITERA PIPETA FLEXIBLE 500 ML TRUPER | AT5: =IFERROR(__xludf.DUMMYFUNCTION("""COMPUTED_VALUE"""),38.0) -> 38 | AY5: =IFERROR(__xludf.DUMMYFUNCTION("""COMPUTED_VALUE"""),119.0) -> 119 | AZ5: =IFERROR(__xludf.DUMMYFUNCTION("""COMPUTED_VALUE"""),128.0) -> 128 | BA5: =IFERROR(__xludf.DUMMYFUNCTION("""COMPUTED_VALUE"""),138.24) -> 138.24 | BB5: =IFERROR(__xludf.DUMMYFUNCTION("""COMPUTED_VALUE"""),138.24) -> 138.24 | BC5: =IFERROR(__xludf.DUMMYFUNCTION("""COMPUTED_VALUE"""),155.0) -> 155 | BD5: =IFERROR(__xludf.DUMMYFUNCTION("""COMPUTED_VALUE"""),163.0) -> 163 | BE5: =IFERROR(__xludf.DUMMYFUNCTION("""COMPUTED_VALUE"""),26.080000000000002) -> 26.08 | BF5: =IFERROR(__xludf.DUMMYFUNCTION("""COMPUTED_VALUE"""),189.08) -> 189.08 | BG5: =IFERROR(__xludf.DUMMYFUNCTION("""COMPUTED_VALUE"""),0.05161290322580645) -> 0.051612903 | BH5: =IFERROR(__xludf.DUMMYFUNCTION("""COMPUTED_VALUE"""),154.85) -> 154.85 | BI5: =IFERROR(__xludf.DUMMYFUNCTION("""COMPUTED_VALUE"""),24.776) -> 24.776 | BJ5: =IFERROR(__xludf.DUMMYFUNCTION("""COMPUTED_VALUE"""),179.626) -> 179.626 | BK5: =IFERROR(__xludf.DUMMYFUNCTION("""COMPUTED_VALUE"""),146.70000000000002) -> 146.7 | BL5: =IFERROR(__xludf.DUMMYFUNCTION("""COMPUTED_VALUE"""),23.472000000000005) -> 23.472 | BM5: =IFERROR(__xludf.DUMMYFUNCTION("""COMPUTED_VALUE"""),170.17200000000003) -> 170.172 | BN5: =IFERROR(__xludf.DUMMYFUNCTION("""COMPUTED_VALUE"""),138.54999999999998) -> 138.55 | BO5: =IFERROR(__xludf.DUMMYFUNCTION("""COMPUTED_VALUE"""),22.168) -> 22.168 | BP5: =IFERROR(__xludf.DUMMYFUNCTION("""COMPUTED_VALUE"""),160.718) -> 160.718 | BQ5: =IFERROR(__xludf.DUMMYFUNCTION("""COMPUTED_VALUE"""),138.54999999999998) -> 138.55 | BR5: =IFERROR(__xludf.DUMMYFUNCTION("""COMPUTED_VALUE"""),22.168) -> 22.168 | BS5: =IFERROR(__xludf.DUMMYFUNCTION("""COMPUTED_VALUE"""),160.718) -> 160.718 | BT5: =IFERROR(__xludf.DUMMYFUNCTION("""COMPUTED_VALUE"""),138.54999999999998) -> 138.55 | BU5: =IFERROR(__xludf.DUMMYFUNCTION("""COMPUTED_VALUE"""),22.168) -> 22.168 | BV5: =IFERROR(__xludf.DUMMYFUNCTION("""COMPUTED_VALUE"""),160.718) -> 160.718
A6: 1 | B6: 2 | C6: C | D6: AE01 | E6: PZA | F6: REF | G6: ACEITERA DE PIPETA FLEXIBLE 300 ML. TRUPER | H6: ACEITERA PIPETA FLEXIBLE 300 ML TRUPER | I6: =IF(D6="","",LEN(H6)) -> 38 | N6: 103 | O6: 111 | P6: 119.88 | Q6: 119.88 | R6: 135 | S6: 142 | T6: =S6*0.16 -> 22.72 | U6: =S6+T6 -> 164.72 | V6: =(S6-R6)/R6 -> 0.051851852 | W6: =(IF(B6="",(S6*(1-$W$1)),(IF(B6=1,(S6*(1-$W$1)),(IF(B6=2,(S6*(1-$W$1)),(IF(B6=3,(S6*(1-$W$1)),(IF(B6=4,(S6*(1)))))))))))) -> 134.9 | X6: =W6*0.16 -> 21.584 | Y6: =W6+X6 -> 156.484 | Z6: =(IF(B6="",(S6*(1-$Z$1)),(IF(B6=1,(S6*(1-$Z$1)),(IF(B6=2,(S6*(1-$Z$1)),(IF(B6=3,(S6*(1-$Z$1)),(IF(B6=4,(S6*(1)))))))))))) -> 127.8 | AA6: =Z6*0.16 -> 20.448 | AB6: =Z6+AA6 -> 148.248 | AC6: =(IF(B6="",(S6*(1-$AC$1)),(IF(B6=1,(S6*(1-$AC$1)),(IF(B6=2,(S6*(1-0.15)),(IF(B6=3,(S6*(1-0.1)),(IF(B6=4,(S6*(1)))))))))))) -> 120.7 | AD6: =AC6*0.16 -> 19.312 | AE6: =AC6+AD6 -> 140.012 | AF6: =(IF(B6="",(S6*(1-$AF$1)),(IF(B6=1,(S6*(1-$AF$1)),(IF(B6=2,(S6*(1-0.15)),(IF(B6=3,(S6*(1-0.1)),(IF(B6=4,(S6*(1)))))))))))) -> 120.7 | AG6: =AF6*0.16 -> 19.312 | AH6: =AF6+AG6 -> 140.012 | AI6: =(IF(B6="",(S6*(1-$AI$1)),(IF(B6=1,(S6*(1-$AI$1)),(IF(B6=2,(S6*(1-0.15)),(IF(B6=3,(S6*(1-0.1)),(IF(B6=4,(S6*(1)))))))))))) -> 120.7 | AJ6: =AI6*0.16 -> 19.312 | AK6: =AI6+AJ6 -> 140.012 | AL6: =IFERROR(__xludf.DUMMYFUNCTION("""COMPUTED_VALUE"""),1.0) -> 1 | AN6: =IFERROR(__xludf.DUMMYFUNCTION("""COMPUTED_VALUE""")," P") -> P | AO6: =IFERROR(__xludf.DUMMYFUNCTION("""COMPUTED_VALUE""")," AM10") -> AM10 | AP6: =IFERROR(__xludf.DUMMYFUNCTION("""COMPUTED_VALUE""")," PZA") -> PZA | AQ6: =IFERROR(__xludf.DUMMYFUNCTION("""COMPUTED_VALUE""")," REF") -> REF | AR6: =IFERROR(__xludf.DUMMYFUNCTION("""COMPUTED_VALUE""")," ACOMODADOR DE TORTILLAS CUADRUPLEX") -> ACOMODADOR DE TORTILLAS CUADRUPLEX | AS6: =IFERROR(__xludf.DUMMYFUNCTION("""COMPUTED_VALUE""")," ACOMODADOR DE TORTILLAS CUADRUPLEX") -> ACOMODADOR DE TORTILLAS CUADRUPLEX | AT6: =IFERROR(__xludf.DUMMYFUNCTION("""COMPUTED_VALUE"""),34.0) -> 34 | AY6: =IFERROR(__xludf.DUMMYFUNCTION("""COMPUTED_VALUE"""),4097.0) -> 4097 | AZ6: =IFERROR(__xludf.DUMMYFUNCTION("""COMPUTED_VALUE"""),4424.0) -> 4424 | BA6: =IFERROR(__xludf.DUMMYFUNCTION("""COMPUTED_VALUE"""),4777.92) -> 4777.92 | BB6: =IFERROR(__xludf.DUMMYFUNCTION("""COMPUTED_VALUE"""),4777.92) -> 4777.92 | BC6: =IFERROR(__xludf.DUMMYFUNCTION("""COMPUTED_VALUE"""),5319.0) -> 5319 | BD6: =IFERROR(__xludf.DUMMYFUNCTION("""COMPUTED_VALUE"""),5585.0) -> 5585 | BE6: =IFERROR(__xludf.DUMMYFUNCTION("""COMPUTED_VALUE"""),893.6) -> 893.6 | BF6: =IFERROR(__xludf.DUMMYFUNCTION("""COMPUTED_VALUE"""),6478.6) -> 6478.6 | BG6: =IFERROR(__xludf.DUMMYFUNCTION("""COMPUTED_VALUE"""),0.05000940026320737) -> 0.0500094 | BH6: =IFERROR(__xludf.DUMMYFUNCTION("""COMPUTED_VALUE"""),5305.75) -> 5305.75 | BI6: =IFERROR(__xludf.DUMMYFUNCTION("""COMPUTED_VALUE"""),848.9200000000001) -> 848.92 | BJ6: =IFERROR(__xludf.DUMMYFUNCTION("""COMPUTED_VALUE"""),6154.67) -> 6154.67 | BK6: =IFERROR(__xludf.DUMMYFUNCTION("""COMPUTED_VALUE"""),5026.5) -> 5026.5 | BL6: =IFERROR(__xludf.DUMMYFUNCTION("""COMPUTED_VALUE"""),804.24) -> 804.24 | BM6: =IFERROR(__xludf.DUMMYFUNCTION("""COMPUTED_VALUE"""),5830.74) -> 5830.74 | BN6: =IFERROR(__xludf.DUMMYFUNCTION("""COMPUTED_VALUE"""),4747.25) -> 4747.25 | BO6: =IFERROR(__xludf.DUMMYFUNCTION("""COMPUTED_VALUE"""),759.5600000000001) -> 759.56 | BP6: =IFERROR(__xludf.DUMMYFUNCTION("""COMPUTED_VALUE"""),5506.81) -> 5506.81 | BQ6: =IFERROR(__xludf.DUMMYFUNCTION("""COMPUTED_VALUE"""),4635.55) -> 4635.55 | BR6: =IFERROR(__xludf.DUMMYFUNCTION("""COMPUTED_VALUE"""),741.688) -> 741.688 | BS6: =IFERROR(__xludf.DUMMYFUNCTION("""COMPUTED_VALUE"""),5377.238) -> 5377.238 | BT6: =IFERROR(__xludf.DUMMYFUNCTION("""COMPUTED_VALUE"""),4468.0) -> 4468 | BU6: =IFERROR(__xludf.DUMMYFUNCTION("""COMPUTED_VALUE"""),714.88) -> 714.88 | BV6: =IFERROR(__xludf.DUMMYFUNCTION("""COMPUTED_VALUE"""),5182.88) -> 5182.88
A7: 1 | B7: 2 | C7: C | D7: AE02 | E7: PZA | F7: REF | G7: ACEITERA DE PIPETA FLEXIBLE 500 ML. TRUPER | H7: ACEITERA PIPETA FLEXIBLE 500 ML TRUPER | I7: =IF(D7="","",LEN(H7)) -> 38 | N7: 119 | O7: 128 | P7: 138.24 | Q7: 138.24 | R7: 155 | S7: 163 | T7: =S7*0.16 -> 26.08 | U7: =S7+T7 -> 189.08 | V7: =(S7-R7)/R7 -> 0.051612903 | W7: =(IF(B7="",(S7*(1-$W$1)),(IF(B7=1,(S7*(1-$W$1)),(IF(B7=2,(S7*(1-$W$1)),(IF(B7=3,(S7*(1-$W$1)),(IF(B7=4,(S7*(1)))))))))))) -> 154.85 | X7: =W7*0.16 -> 24.776 | Y7: =W7+X7 -> 179.626 | Z7: =(IF(B7="",(S7*(1-$Z$1)),(IF(B7=1,(S7*(1-$Z$1)),(IF(B7=2,(S7*(1-$Z$1)),(IF(B7=3,(S7*(1-$Z$1)),(IF(B7=4,(S7*(1)))))))))))) -> 146.7 | AA7: =Z7*0.16 -> 23.472 | AB7: =Z7+AA7 -> 170.172 | AC7: =(IF(B7="",(S7*(1-$AC$1)),(IF(B7=1,(S7*(1-$AC$1)),(IF(B7=2,(S7*(1-0.15)),(IF(B7=3,(S7*(1-0.1)),(IF(B7=4,(S7*(1)))))))))))) -> 138.55 | AD7: =AC7*0.16 -> 22.168 | AE7: =AC7+AD7 -> 160.718 | AF7: =(IF(B7="",(S7*(1-$AF$1)),(IF(B7=1,(S7*(1-$AF$1)),(IF(B7=2,(S7*(1-0.15)),(IF(B7=3,(S7*(1-0.1)),(IF(B7=4,(S7*(1)))))))))))) -> 138.55 | AG7: =AF7*0.16 -> 22.168 | AH7: =AF7+AG7 -> 160.718 | AI7: =(IF(B7="",(S7*(1-$AI$1)),(IF(B7=1,(S7*(1-$AI$1)),(IF(B7=2,(S7*(1-0.15)),(IF(B7=3,(S7*(1-0.1)),(IF(B7=4,(S7*(1)))))))))))) -> 138.55 | AJ7: =AI7*0.16 -> 22.168 | AK7: =AI7+AJ7 -> 160.718 | AL7: =IFERROR(__xludf.DUMMYFUNCTION("""COMPUTED_VALUE"""),1.0) -> 1 | AN7: =IFERROR(__xludf.DUMMYFUNCTION("""COMPUTED_VALUE""")," P") -> P | AO7: =IFERROR(__xludf.DUMMYFUNCTION("""COMPUTED_VALUE""")," AM01") -> AM01 | AP7: =IFERROR(__xludf.DUMMYFUNCTION("""COMPUTED_VALUE""")," PZA") -> PZA | AQ7: =IFERROR(__xludf.DUMMYFUNCTION("""COMPUTED_VALUE""")," REF") -> REF | AR7: =IFERROR(__xludf.DUMMYFUNCTION("""COMPUTED_VALUE""")," ACOMODADOR DE TORTILLAS ESTÁNDAR (10-17 CM.)") -> ACOMODADOR DE TORTILLAS ESTÁNDAR (10-17 CM.) | AS7: =IFERROR(__xludf.DUMMYFUNCTION("""COMPUTED_VALUE""")," ACOMODADOR DE TORTILLAS STD 10-17 CM") -> ACOMODADOR DE TORTILLAS STD 10-17 CM | AT7: =IFERROR(__xludf.DUMMYFUNCTION("""COMPUTED_VALUE"""),36.0) -> 36 | AY7: =IFERROR(__xludf.DUMMYFUNCTION("""COMPUTED_VALUE"""),780.0) -> 780 | AZ7: =IFERROR(__xludf.DUMMYFUNCTION("""COMPUTED_VALUE"""),842.0) -> 842 | BA7: =IFERROR(__xludf.DUMMYFUNCTION("""COMPUTED_VALUE"""),909.36) -> 909.36 | BB7: =IFERROR(__xludf.DUMMYFUNCTION("""COMPUTED_VALUE"""),909.36) -> 909.36 | BC7: =IFERROR(__xludf.DUMMYFUNCTION("""COMPUTED_VALUE"""),1013.0) -> 1013 | BD7: =IFERROR(__xludf.DUMMYFUNCTION("""COMPUTED_VALUE"""),1064.0) -> 1064 | BE7: =IFERROR(__xludf.DUMMYFUNCTION("""COMPUTED_VALUE"""),170.24) -> 170.24 | BF7: =IFERROR(__xludf.DUMMYFUNCTION("""COMPUTED_VALUE"""),1234.24) -> 1234.24 | BG7: =IFERROR(__xludf.DUMMYFUNCTION("""COMPUTED_VALUE"""),0.050345508390918066) -> 0.050345508 | BH7: =IFERROR(__xludf.DUMMYFUNCTION("""COMPUTED_VALUE"""),1010.8) -> 1010.8 | BI7: =IFERROR(__xludf.DUMMYFUNCTION("""COMPUTED_VALUE"""),161.728) -> 161.728 | BJ7: =IFERROR(__xludf.DUMMYFUNCTION("""COMPUTED_VALUE"""),1172.528) -> 1172.528 | BK7: =IFERROR(__xludf.DUMMYFUNCTION("""COMPUTED_VALUE"""),957.6) -> 957.6 | BL7: =IFERROR(__xludf.DUMMYFUNCTION("""COMPUTED_VALUE"""),153.216) -> 153.216 | BM7: =IFERROR(__xludf.DUMMYFUNCTION("""COMPUTED_VALUE"""),1110.816) -> 1110.816 | BN7: =IFERROR(__xludf.DUMMYFUNCTION("""COMPUTED_VALUE"""),904.4) -> 904.4 | BO7: =IFERROR(__xludf.DUMMYFUNCTION("""COMPUTED_VALUE"""),144.704) -> 144.704 | BP7: =IFERROR(__xludf.DUMMYFUNCTION("""COMPUTED_VALUE"""),1049.104) -> 1049.104 | BQ7: =IFERROR(__xludf.DUMMYFUNCTION("""COMPUTED_VALUE"""),883.12) -> 883.12 | BR7: =IFERROR(__xludf.DUMMYFUNCTION("""COMPUTED_VALUE"""),141.2992) -> 141.2992 | BS7: =IFERROR(__xludf.DUMMYFUNCTION("""COMPUTED_VALUE"""),1024.4192) -> 1024.4192 | BT7: =IFERROR(__xludf.DUMMYFUNCTION("""COMPUTED_VALUE"""),851.2) -> 851.2 | BU7: =IFERROR(__xludf.DUMMYFUNCTION("""COMPUTED_VALUE"""),136.192) -> 136.192 | BV7: =IFERROR(__xludf.DUMMYFUNCTION("""COMPUTED_VALUE"""),987.392) -> 987.392
C8: P | D8: AM16 | E8: PZA | F8: REF | G8: ACOMODADOR MÁQUINA TVRD 15CM | H8: ACOMODADOR MAQUINA TVRD 15CM | I8: =IF(D8="","",LEN(H8)) -> 29 | N8: 2100 | O8: 2268 | P8: 2449.44 | Q8: 2449.44 | R8: 2572 | S8: 2701 | T8: =S8*0.16 -> 432.16 | U8: =S8+T8 -> 3133.16 | V8: =(S8-R8)/R8 -> 0.050155521 | W8: =(IF(B8="",(S8*(1-$W$1)),(IF(B8=1,(S8*(1-$W$1)),(IF(B8=2,(S8*(1-$W$1)),(IF(B8=3,(S8*(1-$W$1)),(IF(B8=4,(S8*(1)))))))))))) -> 2565.95 | X8: =W8*0.16 -> 410.552 | Y8: =W8+X8 -> 2976.502 | Z8: =(IF(B8="",(S8*(1-$Z$1)),(IF(B8=1,(S8*(1-$Z$1)),(IF(B8=2,(S8*(1-$Z$1)),(IF(B8=3,(S8*(1-$Z$1)),(IF(B8=4,(S8*(1)))))))))))) -> 2430.9 | AA8: =Z8*0.16 -> 388.944 | AB8: =Z8+AA8 -> 2819.844 | AC8: =(IF(B8="",(S8*(1-$AC$1)),(IF(B8=1,(S8*(1-$AC$1)),(IF(B8=2,(S8*(1-0.15)),(IF(B8=3,(S8*(1-0.1)),(IF(B8=4,(S8*(1)))))))))))) -> 2295.85 | AD8: =AC8*0.16 -> 367.336 | AE8: =AC8+AD8 -> 2663.186 | AF8: =(IF(B8="",(S8*(1-$AF$1)),(IF(B8=1,(S8*(1-$AF$1)),(IF(B8=2,(S8*(1-0.15)),(IF(B8=3,(S8*(1-0.1)),(IF(B8=4,(S8*(1)))))))))))) -> 2241.83 | AG8: =AF8*0.16 -> 358.6928 | AH8: =AF8+AG8 -> 2600.5228 | AI8: =(IF(B8="",(S8*(1-$AI$1)),(IF(B8=1,(S8*(1-$AI$1)),(IF(B8=2,(S8*(1-0.15)),(IF(B8=3,(S8*(1-0.1)),(IF(B8=4,(S8*(1)))))))))))) -> 2160.8 | AJ8: =AI8*0.16 -> 345.728 | AK8: =AI8+AJ8 -> 2506.528 | AL8: =IFERROR(__xludf.DUMMYFUNCTION("""COMPUTED_VALUE"""),1.0) -> 1 | AN8: =IFERROR(__xludf.DUMMYFUNCTION("""COMPUTED_VALUE""")," P") -> P | AO8: =IFERROR(__xludf.DUMMYFUNCTION("""COMPUTED_VALUE""")," AM02") -> AM02 | AP8: =IFERROR(__xludf.DUMMYFUNCTION("""COMPUTED_VALUE""")," PZA") -> PZA | AQ8: =IFERROR(__xludf.DUMMYFUNCTION("""COMPUTED_VALUE""")," REF") -> REF | AR8: =IFERROR(__xludf.DUMMYFUNCTION("""COMPUTED_VALUE""")," ACOMODADOR DE TORTILLAS TIPO PUEBLA ") -> ACOMODADOR DE TORTILLAS TIPO PUEBLA | AS8: =IFERROR(__xludf.DUMMYFUNCTION("""COMPUTED_VALUE""")," ACOMODADOR DE TORTILLAS TIPO PUEBLA ") -> ACOMODADOR DE TORTILLAS TIPO PUEBLA | AT8: =IFERROR(__xludf.DUMMYFUNCTION("""COMPUTED_VALUE"""),36.0) -> 36 | AY8: =IFERROR(__xludf.DUMMYFUNCTION("""COMPUTED_VALUE"""),898.0) -> 898 | AZ8: =IFERROR(__xludf.DUMMYFUNCTION("""COMPUTED_VALUE"""),969.0) -> 969 | BA8: =IFERROR(__xludf.DUMMYFUNCTION("""COMPUTED_VALUE"""),1046.52) -> 1046.52 | BB8: =IFERROR(__xludf.DUMMYFUNCTION("""COMPUTED_VALUE"""),1046.52) -> 1046.52 | BC8: =IFERROR(__xludf.DUMMYFUNCTION("""COMPUTED_VALUE"""),1166.0) -> 1166 | BD8: =IFERROR(__xludf.DUMMYFUNCTION("""COMPUTED_VALUE"""),1224.0) -> 1224 | BE8: =IFERROR(__xludf.DUMMYFUNCTION("""COMPUTED_VALUE"""),195.84) -> 195.84 | BF8: =IFERROR(__xludf.DUMMYFUNCTION("""COMPUTED_VALUE"""),1419.84) -> 1419.84 | BG8: =IFERROR(__xludf.DUMMYFUNCTION("""COMPUTED_VALUE"""),0.04974271012006861) -> 0.04974271 | BH8: =IFERROR(__xludf.DUMMYFUNCTION("""COMPUTED_VALUE"""),1162.8) -> 1162.8 | BI8: =IFERROR(__xludf.DUMMYFUNCTION("""COMPUTED_VALUE"""),186.048) -> 186.048 | BJ8: =IFERROR(__xludf.DUMMYFUNCTION("""COMPUTED_VALUE"""),1348.848) -> 1348.848 | BK8: =IFERROR(__xludf.DUMMYFUNCTION("""COMPUTED_VALUE"""),1101.6000000000001) -> 1101.6 | BL8: =IFERROR(__xludf.DUMMYFUNCTION("""COMPUTED_VALUE"""),176.25600000000003) -> 176.256 | BM8: =IFERROR(__xludf.DUMMYFUNCTION("""COMPUTED_VALUE"""),1277.8560000000002) -> 1277.856 | BN8: =IFERROR(__xludf.DUMMYFUNCTION("""COMPUTED_VALUE"""),1040.3999999999999) -> 1040.4 | BO8: =IFERROR(__xludf.DUMMYFUNCTION("""COMPUTED_VALUE"""),166.46399999999997) -> 166.464 | BP8: =IFERROR(__xludf.DUMMYFUNCTION("""COMPUTED_VALUE"""),1206.8639999999998) -> 1206.864 | BQ8: =IFERROR(__xludf.DUMMYFUNCTION("""COMPUTED_VALUE"""),1015.92) -> 1015.92 | BR8: =IFERROR(__xludf.DUMMYFUNCTION("""COMPUTED_VALUE"""),162.5472) -> 162.5472 | BS8: =IFERROR(__xludf.DUMMYFUNCTION("""COMPUTED_VALUE"""),1178.4672) -> 1178.4672 | BT8: =IFERROR(__xludf.DUMMYFUNCTION("""COMPUTED_VALUE"""),979.2) -> 979.2 | BU8: =IFERROR(__xludf.DUMMYFUNCTION("""COMPUTED_VALUE"""),156.672) -> 156.672 | BV8: =IFERROR(__xludf.DUMMYFUNCTION("""COMPUTED_VALUE"""),1135.872) -> 1135.872
C9: P | D9: AM17 | E9: PZA | F9: REF | G9: ACOMODADOR MÁQUINA TVRD 16CM | H9: ACOMODADOR MAQUINA TVRD 16CM | I9: =IF(D9="","",LEN(H9)) -> 29 | N9: 2100 | O9: 2268 | P9: 2449.44 | Q9: 2449.44 | R9: 2572 | S9: 2701 | T9: =S9*0.16 -> 432.16 | U9: =S9+T9 -> 3133.16 | V9: =(S9-R9)/R9 -> 0.050155521 | W9: =(IF(B9="",(S9*(1-$W$1)),(IF(B9=1,(S9*(1-$W$1)),(IF(B9=2,(S9*(1-$W$1)),(IF(B9=3,(S9*(1-$W$1)),(IF(B9=4,(S9*(1)))))))))))) -> 2565.95 | X9: =W9*0.16 -> 410.552 | Y9: =W9+X9 -> 2976.502 | Z9: =(IF(B9="",(S9*(1-$Z$1)),(IF(B9=1,(S9*(1-$Z$1)),(IF(B9=2,(S9*(1-$Z$1)),(IF(B9=3,(S9*(1-$Z$1)),(IF(B9=4,(S9*(1)))))))))))) -> 2430.9 | AA9: =Z9*0.16 -> 388.944 | AB9: =Z9+AA9 -> 2819.844 | AC9: =(IF(B9="",(S9*(1-$AC$1)),(IF(B9=1,(S9*(1-$AC$1)),(IF(B9=2,(S9*(1-0.15)),(IF(B9=3,(S9*(1-0.1)),(IF(B9=4,(S9*(1)))))))))))) -> 2295.85 | AD9: =AC9*0.16 -> 367.336 | AE9: =AC9+AD9 -> 2663.186 | AF9: =(IF(B9="",(S9*(1-$AF$1)),(IF(B9=1,(S9*(1-$AF$1)),(IF(B9=2,(S9*(1-0.15)),(IF(B9=3,(S9*(1-0.1)),(IF(B9=4,(S9*(1)))))))))))) -> 2241.83 | AG9: =AF9*0.16 -> 358.6928 | AH9: =AF9+AG9 -> 2600.5228 | AI9: =(IF(B9="",(S9*(1-$AI$1)),(IF(B9=1,(S9*(1-$AI$1)),(IF(B9=2,(S9*(1-0.15)),(IF(B9=3,(S9*(1-0.1)),(IF(B9=4,(S9*(1)))))))))))) -> 2160.8 | AJ9: =AI9*0.16 -> 345.728 | AK9: =AI9+AJ9 -> 2506.528 | AL9: =IFERROR(__xludf.DUMMYFUNCTION("""COMPUTED_VALUE"""),1.0) -> 1 | AN9: =IFERROR(__xludf.DUMMYFUNCTION("""COMPUTED_VALUE""")," P") -> P | AO9: =IFERROR(__xludf.DUMMYFUNCTION("""COMPUTED_VALUE""")," AM18") -> AM18 | AP9: =IFERROR(__xludf.DUMMYFUNCTION("""COMPUTED_VALUE""")," JGO") -> JGO | AQ9: =IFERROR(__xludf.DUMMYFUNCTION("""COMPUTED_VALUE""")," REF") -> REF | AR9: =IFERROR(__xludf.DUMMYFUNCTION("""COMPUTED_VALUE""")," ACOMODADOR DE TORTILLAS TIPO PUEBLA CON TIRANTES (18-22 CM.)") -> ACOMODADOR DE TORTILLAS TIPO PUEBLA CON TIRANTES (18-22 CM.) | AS9: =IFERROR(__xludf.DUMMYFUNCTION("""COMPUTED_VALUE""")," ACOMODADOR TORT. T/PUE C/TIRANT 18-22 CM") -> ACOMODADOR TORT. T/PUE C/TIRANT 18-22 CM | AT9: =IFERROR(__xludf.DUMMYFUNCTION("""COMPUTED_VALUE"""),40.0) -> 40 | AY9: =IFERROR(__xludf.DUMMYFUNCTION("""COMPUTED_VALUE"""),1026.0) -> 1026 | AZ9: =IFERROR(__xludf.DUMMYFUNCTION("""COMPUTED_VALUE"""),1108.0) -> 1108 | BA9: =IFERROR(__xludf.DUMMYFUNCTION("""COMPUTED_VALUE"""),1196.64) -> 1196.64 | BB9: =IFERROR(__xludf.DUMMYFUNCTION("""COMPUTED_VALUE"""),1196.64) -> 1196.64 | BC9: =IFERROR(__xludf.DUMMYFUNCTION("""COMPUTED_VALUE"""),1257.0) -> 1257 | BD9: =IFERROR(__xludf.DUMMYFUNCTION("""COMPUTED_VALUE"""),1320.0) -> 1320 | BE9: =IFERROR(__xludf.DUMMYFUNCTION("""COMPUTED_VALUE"""),211.20000000000002) -> 211.2 | BF9: =IFERROR(__xludf.DUMMYFUNCTION("""COMPUTED_VALUE"""),1531.2) -> 1531.2 | BG9: =IFERROR(__xludf.DUMMYFUNCTION("""COMPUTED_VALUE"""),0.050119331742243436) -> 0.050119332 | BH9: =IFERROR(__xludf.DUMMYFUNCTION("""COMPUTED_VALUE"""),1254.0) -> 1254 | BI9: =IFERROR(__xludf.DUMMYFUNCTION("""COMPUTED_VALUE"""),200.64000000000001) -> 200.64 | BJ9: =IFERROR(__xludf.DUMMYFUNCTION("""COMPUTED_VALUE"""),1454.64) -> 1454.64 | BK9: =IFERROR(__xludf.DUMMYFUNCTION("""COMPUTED_VALUE"""),1188.0) -> 1188 | BL9: =IFERROR(__xludf.DUMMYFUNCTION("""COMPUTED_VALUE"""),190.08) -> 190.08 | BM9: =IFERROR(__xludf.DUMMYFUNCTION("""COMPUTED_VALUE"""),1378.08) -> 1378.08 | BN9: =IFERROR(__xludf.DUMMYFUNCTION("""COMPUTED_VALUE"""),1122.0) -> 1122 | BO9: =IFERROR(__xludf.DUMMYFUNCTION("""COMPUTED_VALUE"""),179.52) -> 179.52 | BP9: =IFERROR(__xludf.DUMMYFUNCTION("""COMPUTED_VALUE"""),1301.52) -> 1301.52 | BQ9: =IFERROR(__xludf.DUMMYFUNCTION("""COMPUTED_VALUE"""),1095.6) -> 1095.6 | BR9: =IFERROR(__xludf.DUMMYFUNCTION("""COMPUTED_VALUE"""),175.296) -> 175.296 | BS9: =IFERROR(__xludf.DUMMYFUNCTION("""COMPUTED_VALUE"""),1270.896) -> 1270.896 | BT9: =IFERROR(__xludf.DUMMYFUNCTION("""COMPUTED_VALUE"""),1056.0) -> 1056 | BU9: =IFERROR(__xludf.DUMMYFUNCTION("""COMPUTED_VALUE"""),168.96) -> 168.96 | BV9: =IFERROR(__xludf.DUMMYFUNCTION("""COMPUTED_VALUE"""),1224.96) -> 1224.96
B10: 3 | C10: E | D10: AM07 | E10: PZA | F10: TNO | G10: ACOMODADOR DE TORTILLAS AUTOMÁTICO DÚPLEX | I10: =IF(D10="","",LEN(H10)) -> 0 | O10: 17667 | P10: 19080.36 | Q10: 19080.36 | R10: 21036 | S10: 22088 | T10: =S10*0.16 -> 3534.08 | U10: =S10+T10 -> 25622.08 | V10: =(S10-R10)/R10 -> 0.050009508 | W10: =(IF(B10="",(S10*(1-$W$1)),(IF(B10=1,(S10*(1-$W$1)),(IF(B10=2,(S10*(1-$W$1)),(IF(B10=3,(S10*(1-$W$1)),(IF(B10=4,(S10*(1)))))))))))) -> 20983.6 | X10: =W10*0.16 -> 3357.376 | Y10: =W10+X10 -> 24340.976 | Z10: =(IF(B10="",(S10*(1-$Z$1)),(IF(B10=1,(S10*(1-$Z$1)),(IF(B10=2,(S10*(1-$Z$1)),(IF(B10=3,(S10*(1-$Z$1)),(IF(B10=4,(S10*(1)))))))))))) -> 19879.2 | AA10: =Z10*0.16 -> 3180.672 | AB10: =Z10+AA10 -> 23059.872 | AC10: =(IF(B10="",(S10*(1-$AC$1)),(IF(B10=1,(S10*(1-$AC$1)),(IF(B10=2,(S10*(1-0.15)),(IF(B10=3,(S10*(1-0.1)),(IF(B10=4,(S10*(1)))))))))))) -> 19879.2 | AD10: =AC10*0.16 -> 3180.672 | AE10: =AC10+AD10 -> 23059.872 | AF10: =(IF(B10="",(S10*(1-$AF$1)),(IF(B10=1,(S10*(1-$AF$1)),(IF(B10=2,(S10*(1-0.15)),(IF(B10=3,(S10*(1-0.1)),(IF(B10=4,(S10*(1)))))))))))) -> 19879.2 | AG10: =AF10*0.16 -> 3180.672 | AH10: =AF10+AG10 -> 23059.872 | AI10: =(IF(B10="",(S10*(1-$AI$1)),(IF(B10=1,(S10*(1-$AI$1)),(IF(B10=2,(S10*(1-0.15)),(IF(B10=3,(S10*(1-0.1)),(IF(B10=4,(S10*(1)))))))))))) -> 19879.2 | AJ10: =AI10*0.16 -> 3180.672 | AK10: =AI10+AJ10 -> 23059.872 | AL10: =IFERROR(__xludf.DUMMYFUNCTION("""COMPUTED_VALUE"""),1.0) -> 1 | AN10: =IFERROR(__xludf.DUMMYFUNCTION("""COMPUTED_VALUE""")," C") -> C | AO10: =IFERROR(__xludf.DUMMYFUNCTION("""COMPUTED_VALUE""")," RL15") -> RL15 | AP10: =IFERROR(__xludf.DUMMYFUNCTION("""COMPUTED_VALUE""")," PZA") -> PZA | AQ10: =IFERROR(__xludf.DUMMYFUNCTION("""COMPUTED_VALUE""")," REF") -> REF | AR10: =IFERROR(__xludf.DUMMYFUNCTION("""COMPUTED_VALUE""")," ALAMBRE DESPEGADOR 15 GR") -> ALAMBRE DESPEGADOR 15 GR | AS10: =IFERROR(__xludf.DUMMYFUNCTION("""COMPUTED_VALUE""")," ALAMBRE DESPEGADOR 15 GR") -> ALAMBRE DESPEGADOR 15 GR | AT10: =IFERROR(__xludf.DUMMYFUNCTION("""COMPUTED_VALUE"""),24.0) -> 24 | BC10: =IFERROR(__xludf.DUMMYFUNCTION("""COMPUTED_VALUE"""),42.0) -> 42 | BD10: =IFERROR(__xludf.DUMMYFUNCTION("""COMPUTED_VALUE"""),44.0) -> 44 | BE10: =IFERROR(__xludf.DUMMYFUNCTION("""COMPUTED_VALUE"""),7.04) -> 7.04 | BF10: =IFERROR(__xludf.DUMMYFUNCTION("""COMPUTED_VALUE"""),51.04) -> 51.04 | BG10: =IFERROR(__xludf.DUMMYFUNCTION("""COMPUTED_VALUE"""),0.047619047619047616) -> 0.047619048 | BH10: =IFERROR(__xludf.DUMMYFUNCTION("""COMPUTED_VALUE"""),41.8) -> 41.8 | BI10: =IFERROR(__xludf.DUMMYFUNCTION("""COMPUTED_VALUE"""),6.688) -> 6.688 | BJ10: =IFERROR(__xludf.DUMMYFUNCTION("""COMPUTED_VALUE"""),48.488) -> 48.488 | BK10: =IFERROR(__xludf.DUMMYFUNCTION("""COMPUTED_VALUE"""),39.6) -> 39.6 | BL10: =IFERROR(__xludf.DUMMYFUNCTION("""COMPUTED_VALUE"""),6.336) -> 6.336 | BM10: =IFERROR(__xludf.DUMMYFUNCTION("""COMPUTED_VALUE"""),45.936) -> 45.936 | BN10: =IFERROR(__xludf.DUMMYFUNCTION("""COMPUTED_VALUE"""),37.4) -> 37.4 | BO10: =IFERROR(__xludf.DUMMYFUNCTION("""COMPUTED_VALUE"""),5.984) -> 5.984 | BP10: =IFERROR(__xludf.DUMMYFUNCTION("""COMPUTED_VALUE"""),43.384) -> 43.384 | BQ10: =IFERROR(__xludf.DUMMYFUNCTION("""COMPUTED_VALUE"""),36.519999999999996) -> 36.52 | BR10: =IFERROR(__xludf.DUMMYFUNCTION("""COMPUTED_VALUE"""),5.8431999999999995) -> 5.8432 | BS10: =IFERROR(__xludf.DUMMYFUNCTION("""COMPUTED_VALUE"""),42.36319999999999) -> 42.3632 | BT10: =IFERROR(__xludf.DUMMYFUNCTION("""COMPUTED_VALUE"""),35.2) -> 35.2
B11: 3 | C11: E | D11: AM05 | E11: PZA | F11: TNO | G11: ACOMODADOR DE TORTILLAS AUTOMÁTICO SENCILLO (15 y 16 CM) | I11: =IF(D11="","",LEN(H11)) -> 0 | O11: 7624 | P11: 8233.92 | Q11: 8233.92 | R11: 9079 | S11: 9533 | T11: =S11*0.16 -> 1525.28 | U11: =S11+T11 -> 11058.28 | V11: =(S11-R11)/R11 -> 0.050005507 | W11: =(IF(B11="",(S11*(1-$W$1)),(IF(B11=1,(S11*(1-$W$1)),(IF(B11=2,(S11*(1-$W$1)),(IF(B11=3,(S11*(1-$W$1)),(IF(B11=4,(S11*(1)))))))))))) -> 9056.35 | X11: =W11*0.16 -> 1449.016 | Y11: =W11+X11 -> 10505.366 | Z11: =(IF(B11="",(S11*(1-$Z$1)),(IF(B11=1,(S11*(1-$Z$1)),(IF(B11=2,(S11*(1-$Z$1)),(IF(B11=3,(S11*(1-$Z$1)),(IF(B11=4,(S11*(1)))))))))))) -> 8579.7 | AA11: =Z11*0.16 -> 1372.752 | AB11: =Z11+AA11 -> 9952.452 | AC11: =(IF(B11="",(S11*(1-$AC$1)),(IF(B11=1,(S11*(1-$AC$1)),(IF(B11=2,(S11*(1-0.15)),(IF(B11=3,(S11*(1-0.1)),(IF(B11=4,(S11*(1)))))))))))) -> 8579.7 | AD11: =AC11*0.16 -> 1372.752 | AE11: =AC11+AD11 -> 9952.452 | AF11: =(IF(B11="",(S11*(1-$AF$1)),(IF(B11=1,(S11*(1-$AF$1)),(IF(B11=2,(S11*(1-0.15)),(IF(B11=3,(S11*(1-0.1)),(IF(B11=4,(S11*(1)))))))))))) -> 8579.7 | AG11: =AF11*0.16 -> 1372.752 | AH11: =AF11+AG11 -> 9952.452 | AI11: =(IF(B11="",(S11*(1-$AI$1)),(IF(B11=1,(S11*(1-$AI$1)),(IF(B11=2,(S11*(1-0.15)),(IF(B11=3,(S11*(1-0.1)),(IF(B11=4,(S11*(1)))))))))))) -> 8579.7 | AJ11: =AI11*0.16 -> 1372.752 | AK11: =AI11+AJ11 -> 9952.452 | AL11: =IFERROR(__xludf.DUMMYFUNCTION("""COMPUTED_VALUE"""),1.0) -> 1 | AN11: =IFERROR(__xludf.DUMMYFUNCTION("""COMPUTED_VALUE""")," C") -> C | AO11: =IFERROR(__xludf.DUMMYFUNCTION("""COMPUTED_VALUE""")," RL90") -> RL90 | AP11: =IFERROR(__xludf.DUMMYFUNCTION("""COMPUTED_VALUE""")," PZA") -> PZA | AQ11: =IFERROR(__xludf.DUMMYFUNCTION("""COMPUTED_VALUE""")," REF") -> REF | AR11: =IFERROR(__xludf.DUMMYFUNCTION("""COMPUTED_VALUE""")," ALAMBRE DESPEGADOR 90 GR") -> ALAMBRE DESPEGADOR 90 GR | AS11: =IFERROR(__xludf.DUMMYFUNCTION("""COMPUTED_VALUE""")," ALAMBRE DESPEGADOR 90 GR") -> ALAMBRE DESPEGADOR 90 GR | AT11: =IFERROR(__xludf.DUMMYFUNCTION("""COMPUTED_VALUE"""),24.0) -> 24 | BC11: =IFERROR(__xludf.DUMMYFUNCTION("""COMPUTED_VALUE"""),250.0) -> 250 | BD11: =IFERROR(__xludf.DUMMYFUNCTION("""COMPUTED_VALUE"""),263.0) -> 263 | BE11: =IFERROR(__xludf.DUMMYFUNCTION("""COMPUTED_VALUE"""),42.08) -> 42.08 | BF11: =IFERROR(__xludf.DUMMYFUNCTION("""COMPUTED_VALUE"""),305.08) -> 305.08 | BG11: =IFERROR(__xludf.DUMMYFUNCTION("""COMPUTED_VALUE"""),0.052) -> 0.052 | BH11: =IFERROR(__xludf.DUMMYFUNCTION("""COMPUTED_VALUE"""),249.85) -> 249.85 | BI11: =IFERROR(__xludf.DUMMYFUNCTION("""COMPUTED_VALUE"""),39.976) -> 39.976 | BJ11: =IFERROR(__xludf.DUMMYFUNCTION("""COMPUTED_VALUE"""),289.826) -> 289.826 | BK11: =IFERROR(__xludf.DUMMYFUNCTION("""COMPUTED_VALUE"""),236.70000000000002) -> 236.7 | BL11: =IFERROR(__xludf.DUMMYFUNCTION("""COMPUTED_VALUE"""),37.87200000000001) -> 37.872 | BM11: =IFERROR(__xludf.DUMMYFUNCTION("""COMPUTED_VALUE"""),274.572) -> 274.572 | BN11: =IFERROR(__xludf.DUMMYFUNCTION("""COMPUTED_VALUE"""),223.54999999999998) -> 223.55 | BO11: =IFERROR(__xludf.DUMMYFUNCTION("""COMPUTED_VALUE"""),35.768) -> 35.768 | BP11: =IFERROR(__xludf.DUMMYFUNCTION("""COMPUTED_VALUE"""),259.318) -> 259.318 | BQ11: =IFERROR(__xludf.DUMMYFUNCTION("""COMPUTED_VALUE"""),218.29) -> 218.29 | BR11: =IFERROR(__xludf.DUMMYFUNCTION("""COMPUTED_VALUE"""),34.9264) -> 34.9264 | BS11: =IFERROR(__xludf.DUMMYFUNCTION("""COMPUTED_VALUE"""),253.2164) -> 253.2164 | BT11: =IFERROR(__xludf.DUMMYFUNCTION("""COMPUTED_VALUE"""),210.4) -> 210.4
B12: 3 | C12: E | D12: AM06 | E12: PZA | F12: TNO | G12: ACOMODADOR DE TORTILLAS AUTOMÁTICO SENCILLO TIPO PUEBLA (18, 19 y 20 cm) | I12: =IF(D12="","",LEN(H12)) -> 0 | O12: 9037 | P12: 9759.96 | Q12: 9759.96 | R12: 10761 | S12: 11299 | T12: =S12*0.16 -> 1807.84 | U12: =S12+T12 -> 13106.84 | V12: =(S12-R12)/R12 -> 0.049995354 | W12: =(IF(B12="",(S12*(1-$W$1)),(IF(B12=1,(S12*(1-$W$1)),(IF(B12=2,(S12*(1-$W$1)),(IF(B12=3,(S12*(1-$W$1)),(IF(B12=4,(S12*(1)))))))))))) -> 10734.05 | X12: =W12*0.16 -> 1717.448 | Y12: =W12+X12 -> 12451.498 | Z12: =(IF(B12="",(S12*(1-$Z$1)),(IF(B12=1,(S12*(1-$Z$1)),(IF(B12=2,(S12*(1-$Z$1)),(IF(B12=3,(S12*(1-$Z$1)),(IF(B12=4,(S12*(1)))))))))))) -> 10169.1 | AA12: =Z12*0.16 -> 1627.056 | AB12: =Z12+AA12 -> 11796.156 | AC12: =(IF(B12="",(S12*(1-$AC$1)),(IF(B12=1,(S12*(1-$AC$1)),(IF(B12=2,(S12*(1-0.15)),(IF(B12=3,(S12*(1-0.1)),(IF(B12=4,(S12*(1)))))))))))) -> 10169.1 | AD12: =AC12*0.16 -> 1627.056 | AE12: =AC12+AD12 -> 11796.156 | AF12: =(IF(B12="",(S12*(1-$AF$1)),(IF(B12=1,(S12*(1-$AF$1)),(IF(B12=2,(S12*(1-0.15)),(IF(B12=3,(S12*(1-0.1)),(IF(B12=4,(S12*(1)))))))))))) -> 10169.1 | AG12: =AF12*0.16 -> 1627.056 | AH12: =AF12+AG12 -> 11796.156 | AI12: =(IF(B12="",(S12*(1-$AI$1)),(IF(B12=1,(S12*(1-$AI$1)),(IF(B12=2,(S12*(1-0.15)),(IF(B12=3,(S12*(1-0.1)),(IF(B12=4,(S12*(1)))))))))))) -> 10169.1 | AJ12: =AI12*0.16 -> 1627.056 | AK12: =AI12+AJ12 -> 11796.156 | AL12: =IFERROR(__xludf.DUMMYFUNCTION("""COMPUTED_VALUE"""),1.0) -> 1 | AN12: =IFERROR(__xludf.DUMMYFUNCTION("""COMPUTED_VALUE""")," C") -> C | AO12: =IFERROR(__xludf.DUMMYFUNCTION("""COMPUTED_VALUE""")," AN01") -> AN01 | AP12: =IFERROR(__xludf.DUMMYFUNCTION("""COMPUTED_VALUE""")," CUB") -> CUB | AQ12: =IFERROR(__xludf.DUMMYFUNCTION("""COMPUTED_VALUE""")," REF") -> REF | AR12: =IFERROR(__xludf.DUMMYFUNCTION("""COMPUTED_VALUE""")," ANTIADHERENTE ""A"" 19 LITROS") -> ANTIADHERENTE "A" 19 LITROS | AS12: =IFERROR(__xludf.DUMMYFUNCTION("""COMPUTED_VALUE""")," ANTIADHERENTE A 19 LITROS") -> ANTIADHERENTE A 19 LITROS | AT12: =IFERROR(__xludf.DUMMYFUNCTION("""COMPUTED_VALUE"""),25.0) -> 25 | AY12: =IFERROR(__xludf.DUMMYFUNCTION("""COMPUTED_VALUE"""),3537.0) -> 3537 | AZ12: =IFERROR(__xludf.DUMMYFUNCTION("""COMPUTED_VALUE"""),2554.0) -> 2554 | BA12: =IFERROR(__xludf.DUMMYFUNCTION("""COMPUTED_VALUE"""),2291.4) -> 2291.4 | BB12: =IFERROR(__xludf.DUMMYFUNCTION("""COMPUTED_VALUE"""),2291.4) -> 2291.4 | BC12: =IFERROR(__xludf.DUMMYFUNCTION("""COMPUTED_VALUE"""),2551.0) -> 2551 | BD12: =IFERROR(__xludf.DUMMYFUNCTION("""COMPUTED_VALUE"""),2679.0) -> 2679 | BE12: =IFERROR(__xludf.DUMMYFUNCTION("""COMPUTED_VALUE"""),428.64) -> 428.64 | BF12: =IFERROR(__xludf.DUMMYFUNCTION("""COMPUTED_VALUE"""),3107.64) -> 3107.64 | BG12: =IFERROR(__xludf.DUMMYFUNCTION("""COMPUTED_VALUE"""),0.05017640141121129) -> 0.050176401 | BH12: =IFERROR(__xludf.DUMMYFUNCTION("""COMPUTED_VALUE"""),2545.0499999999997) -> 2545.05 | BI12: =IFERROR(__xludf.DUMMYFUNCTION("""COMPUTED_VALUE"""),407.20799999999997) -> 407.208 | BJ12: =IFERROR(__xludf.DUMMYFUNCTION("""COMPUTED_VALUE"""),2952.258) -> 2952.258 | BK12: =IFERROR(__xludf.DUMMYFUNCTION("""COMPUTED_VALUE"""),2411.1) -> 2411.1 | BL12: =IFERROR(__xludf.DUMMYFUNCTION("""COMPUTED_VALUE"""),385.776) -> 385.776 | BM12: =IFERROR(__xludf.DUMMYFUNCTION("""COMPUTED_VALUE"""),2796.8759999999997) -> 2796.876 | BN12: =IFERROR(__xludf.DUMMYFUNCTION("""COMPUTED_VALUE"""),2277.15) -> 2277.15 | BO12: =IFERROR(__xludf.DUMMYFUNCTION("""COMPUTED_VALUE"""),364.344) -> 364.344 | BP12: =IFERROR(__xludf.DUMMYFUNCTION("""COMPUTED_VALUE"""),2641.494) -> 2641.494 | BQ12: =IFERROR(__xludf.DUMMYFUNCTION("""COMPUTED_VALUE"""),2223.5699999999997) -> 2223.57 | BR12: =IFERROR(__xludf.DUMMYFUNCTION("""COMPUTED_VALUE"""),355.77119999999996) -> 355.7712 | BS12: =IFERROR(__xludf.DUMMYFUNCTION("""COMPUTED_VALUE"""),2579.3412) -> 2579.3412 | BT12: =IFERROR(__xludf.DUMMYFUNCTION("""COMPUTED_VALUE"""),2143.2000000000003) -> 2143.2 | BU12: =IFERROR(__xludf.DUMMYFUNCTION("""COMPUTED_VALUE"""),342.91200000000003) -> 342.912 | BV12: =IFERROR(__xludf.DUMMYFUNCTION("""COMPUTED_VALUE"""),2486.112) -> 2486.112
C13: E | D13: AM03 | E13: PZA | F13: WAL | G13: ACOMODADOR DE TORTILLAS CON SOLERAS WALMART | I13: =IF(D13="","",LEN(H13)) -> 0 | O13: 1559.04 | P13: 1683.7632 | Q13: 1683.7632 | R13: 1769 | S13: 1857 | T13: =S13*0.16 -> 297.12 | U13: =S13+T13 -> 2154.12 | V13: =(S13-R13)/R13 -> 0.049745619 | W13: =(IF(B13="",(S13*(1-$W$1)),(IF(B13=1,(S13*(1-$W$1)),(IF(B13=2,(S13*(1-$W$1)),(IF(B13=3,(S13*(1-$W$1)),(IF(B13=4,(S13*(1)))))))))))) -> 1764.15 | X13: =W13*0.16 -> 282.264 | Y13: =W13+X13 -> 2046.414 | Z13: =(IF(B13="",(S13*(1-$Z$1)),(IF(B13=1,(S13*(1-$Z$1)),(IF(B13=2,(S13*(1-$Z$1)),(IF(B13=3,(S13*(1-$Z$1)),(IF(B13=4,(S13*(1)))))))))))) -> 1671.3 | AA13: =Z13*0.16 -> 267.408 | AB13: =Z13+AA13 -> 1938.708 | AC13: =(IF(B13="",(S13*(1-$AC$1)),(IF(B13=1,(S13*(1-$AC$1)),(IF(B13=2,(S13*(1-0.15)),(IF(B13=3,(S13*(1-0.1)),(IF(B13=4,(S13*(1)))))))))))) -> 1578.45 | AD13: =AC13*0.16 -> 252.552 | AE13: =AC13+AD13 -> 1831.002 | AF13: =(IF(B13="",(S13*(1-$AF$1)),(IF(B13=1,(S13*(1-$AF$1)),(IF(B13=2,(S13*(1-0.15)),(IF(B13=3,(S13*(1-0.1)),(IF(B13=4,(S13*(1)))))))))))) -> 1541.31 | AG13: =AF13*0.16 -> 246.6096 | AH13: =AF13+AG13 -> 1787.9196 | AI13: =(IF(B13="",(S13*(1-$AI$1)),(IF(B13=1,(S13*(1-$AI$1)),(IF(B13=2,(S13*(1-0.15)),(IF(B13=3,(S13*(1-0.1)),(IF(B13=4,(S13*(1)))))))))))) -> 1485.6 | AJ13: =AI13*0.16 -> 237.696 | AK13: =AI13+AJ13 -> 1723.296 | AL13: =IFERROR(__xludf.DUMMYFUNCTION("""COMPUTED_VALUE"""),1.0) -> 1 | AN13: =IFERROR(__xludf.DUMMYFUNCTION("""COMPUTED_VALUE""")," C") -> C | AO13: =IFERROR(__xludf.DUMMYFUNCTION("""COMPUTED_VALUE""")," AN02") -> AN02 | AP13: =IFERROR(__xludf.DUMMYFUNCTION("""COMPUTED_VALUE""")," GAL") -> GAL | AQ13: =IFERROR(__xludf.DUMMYFUNCTION("""COMPUTED_VALUE""")," REF") -> REF | AR13: =IFERROR(__xludf.DUMMYFUNCTION("""COMPUTED_VALUE""")," ANTIADHERENTE ""A"" GALÓN") -> ANTIADHERENTE "A" GALÓN | AS13: =IFERROR(__xludf.DUMMYFUNCTION("""COMPUTED_VALUE""")," ANTIADHERENTE A GALON") -> ANTIADHERENTE A GALON | AT13: =IFERROR(__xludf.DUMMYFUNCTION("""COMPUTED_VALUE"""),21.0) -> 21 | AY13: =IFERROR(__xludf.DUMMYFUNCTION("""COMPUTED_VALUE"""),744.0) -> 744 | AZ13: =IFERROR(__xludf.DUMMYFUNCTION("""COMPUTED_VALUE"""),538.0) -> 538 | BA13: =IFERROR(__xludf.DUMMYFUNCTION("""COMPUTED_VALUE"""),482.4) -> 482.4 | BB13: =IFERROR(__xludf.DUMMYFUNCTION("""COMPUTED_VALUE"""),482.4) -> 482.4 | BC13: =IFERROR(__xludf.DUMMYFUNCTION("""COMPUTED_VALUE"""),538.0) -> 538 | BD13: =IFERROR(__xludf.DUMMYFUNCTION("""COMPUTED_VALUE"""),565.0) -> 565 | BE13: =IFERROR(__xludf.DUMMYFUNCTION("""COMPUTED_VALUE"""),90.4) -> 90.4 | BF13: =IFERROR(__xludf.DUMMYFUNCTION("""COMPUTED_VALUE"""),655.4) -> 655.4 | BG13: =IFERROR(__xludf.DUMMYFUNCTION("""COMPUTED_VALUE"""),0.05018587360594796) -> 0.050185874 | BH13: =IFERROR(__xludf.DUMMYFUNCTION("""COMPUTED_VALUE"""),536.75) -> 536.75 | BI13: =IFERROR(__xludf.DUMMYFUNCTION("""COMPUTED_VALUE"""),85.88) -> 85.88 | BJ13: =IFERROR(__xludf.DUMMYFUNCTION("""COMPUTED_VALUE"""),622.63) -> 622.63 | BK13: =IFERROR(__xludf.DUMMYFUNCTION("""COMPUTED_VALUE"""),508.5) -> 508.5 | BL13: =IFERROR(__xludf.DUMMYFUNCTION("""COMPUTED_VALUE"""),81.36) -> 81.36 | BM13: =IFERROR(__xludf.DUMMYFUNCTION("""COMPUTED_VALUE"""),589.86) -> 589.86 | BN13: =IFERROR(__xludf.DUMMYFUNCTION("""COMPUTED_VALUE"""),480.25) -> 480.25 | BO13: =IFERROR(__xludf.DUMMYFUNCTION("""COMPUTED_VALUE"""),76.84) -> 76.84 | BP13: =IFERROR(__xludf.DUMMYFUNCTION("""COMPUTED_VALUE"""),557.09) -> 557.09 | BQ13: =IFERROR(__xludf.DUMMYFUNCTION("""COMPUTED_VALUE"""),468.95) -> 468.95 | BR13: =IFERROR(__xludf.DUMMYFUNCTION("""COMPUTED_VALUE"""),75.032) -> 75.032 | BS13: =IFERROR(__xludf.DUMMYFUNCTION("""COMPUTED_VALUE"""),543.982) -> 543.982 | BT13: =IFERROR(__xludf.DUMMYFUNCTION("""COMPUTED_VALUE"""),452.0) -> 452 | BU13: =IFERROR(__xludf.DUMMYFUNCTION("""COMPUTED_VALUE"""),72.32000000000001) -> 72.32 | BV13: =IFERROR(__xludf.DUMMYFUNCTION("""COMPUTED_VALUE"""),524.32) -> 524.32
A14: 1 | C14: P | D14: AM10 | E14: PZA | F14: REF | G14: ACOMODADOR DE TORTILLAS CUADRUPLEX | H14: ACOMODADOR DE TORTILLAS CUADRUPLEX | I14: =IF(D14="","",LEN(H14)) -> 34 | N14: 4097 | O14: 4424 | P14: 4777.92 | Q14: 4777.92 | R14: 5319 | S14: 5585 | T14: =S14*0.16 -> 893.6 | U14: =S14+T14 -> 6478.6 | V14: =(S14-R14)/R14 -> 0.0500094 | W14: =(IF(B14="",(S14*(1-$W$1)),(IF(B14=1,(S14*(1-$W$1)),(IF(B14=2,(S14*(1-$W$1)),(IF(B14=3,(S14*(1-$W$1)),(IF(B14=4,(S14*(1)))))))))))) -> 5305.75 | X14: =W14*0.16 -> 848.92 | Y14: =W14+X14 -> 6154.67 | Z14: =(IF(B14="",(S14*(1-$Z$1)),(IF(B14=1,(S14*(1-$Z$1)),(IF(B14=2,(S14*(1-$Z$1)),(IF(B14=3,(S14*(1-$Z$1)),(IF(B14=4,(S14*(1)))))))))))) -> 5026.5 | AA14: =Z14*0.16 -> 804.24 | AB14: =Z14+AA14 -> 5830.74 | AC14: =(IF(B14="",(S14*(1-$AC$1)),(IF(B14=1,(S14*(1-$AC$1)),(IF(B14=2,(S14*(1-0.15)),(IF(B14=3,(S14*(1-0.1)),(IF(B14=4,(S14*(1)))))))))))) -> 4747.25 | AD14: =AC14*0.16 -> 759.56 | AE14: =AC14+AD14 -> 5506.81 | AF14: =(IF(B14="",(S14*(1-$AF$1)),(IF(B14=1,(S14*(1-$AF$1)),(IF(B14=2,(S14*(1-0.15)),(IF(B14=3,(S14*(1-0.1)),(IF(B14=4,(S14*(1)))))))))))) -> 4635.55 | AG14: =AF14*0.16 -> 741.688 | AH14: =AF14+AG14 -> 5377.238 | AI14: =(IF(B14="",(S14*(1-$AI$1)),(IF(B14=1,(S14*(1-$AI$1)),(IF(B14=2,(S14*(1-0.15)),(IF(B14=3,(S14*(1-0.1)),(IF(B14=4,(S14*(1)))))))))))) -> 4468 | AJ14: =AI14*0.16 -> 714.88 | AK14: =AI14+AJ14 -> 5182.88 | AL14: =IFERROR(__xludf.DUMMYFUNCTION("""COMPUTED_VALUE"""),1.0) -> 1 | AN14: =IFERROR(__xludf.DUMMYFUNCTION("""COMPUTED_VALUE""")," C") -> C | AO14: =IFERROR(__xludf.DUMMYFUNCTION("""COMPUTED_VALUE""")," AN03") -> AN03 | AP14: =IFERROR(__xludf.DUMMYFUNCTION("""COMPUTED_VALUE""")," LTR") -> LTR | AQ14: =IFERROR(__xludf.DUMMYFUNCTION("""COMPUTED_VALUE""")," REF") -> REF | AR14: =IFERROR(__xludf.DUMMYFUNCTION("""COMPUTED_VALUE""")," ANTIADHERENTE ""A"" LITRO") -> ANTIADHERENTE "A" LITRO | AS14: =IFERROR(__xludf.DUMMYFUNCTION("""COMPUTED_VALUE""")," ANTIADHERENTE A LITRO") -> ANTIADHERENTE A LITRO | AT14: =IFERROR(__xludf.DUMMYFUNCTION("""COMPUTED_VALUE"""),21.0) -> 21 | AY14: =IFERROR(__xludf.DUMMYFUNCTION("""COMPUTED_VALUE"""),182.0) -> 182 | AZ14: =IFERROR(__xludf.DUMMYFUNCTION("""COMPUTED_VALUE"""),134.0) -> 134 | BA14: =IFERROR(__xludf.DUMMYFUNCTION("""COMPUTED_VALUE"""),120.6) -> 120.6 | BB14: =IFERROR(__xludf.DUMMYFUNCTION("""COMPUTED_VALUE"""),120.6) -> 120.6 | BC14: =IFERROR(__xludf.DUMMYFUNCTION("""COMPUTED_VALUE"""),134.0) -> 134 | BD14: =IFERROR(__xludf.DUMMYFUNCTION("""COMPUTED_VALUE"""),141.0) -> 141 | BE14: =IFERROR(__xludf.DUMMYFUNCTION("""COMPUTED_VALUE"""),22.56) -> 22.56 | BF14: =IFERROR(__xludf.DUMMYFUNCTION("""COMPUTED_VALUE"""),163.56) -> 163.56 | BG14: =IFERROR(__xludf.DUMMYFUNCTION("""COMPUTED_VALUE"""),0.05223880597014925) -> 0.052238806 | BH14: =IFERROR(__xludf.DUMMYFUNCTION("""COMPUTED_VALUE"""),133.95) -> 133.95 | BI14: =IFERROR(__xludf.DUMMYFUNCTION("""COMPUTED_VALUE"""),21.432) -> 21.432 | BJ14: =IFERROR(__xludf.DUMMYFUNCTION("""COMPUTED_VALUE"""),155.38199999999998) -> 155.382 | BK14: =IFERROR(__xludf.DUMMYFUNCTION("""COMPUTED_VALUE"""),126.9) -> 126.9 | BL14: =IFERROR(__xludf.DUMMYFUNCTION("""COMPUTED_VALUE"""),20.304000000000002) -> 20.304 | BM14: =IFERROR(__xludf.DUMMYFUNCTION("""COMPUTED_VALUE"""),147.204) -> 147.204 | BN14: =IFERROR(__xludf.DUMMYFUNCTION("""COMPUTED_VALUE"""),119.85) -> 119.85 | BO14: =IFERROR(__xludf.DUMMYFUNCTION("""COMPUTED_VALUE"""),19.176) -> 19.176 | BP14: =IFERROR(__xludf.DUMMYFUNCTION("""COMPUTED_VALUE"""),139.02599999999998) -> 139.026 | BQ14: =IFERROR(__xludf.DUMMYFUNCTION("""COMPUTED_VALUE"""),117.03) -> 117.03 | BR14: =IFERROR(__xludf.DUMMYFUNCTION("""COMPUTED_VALUE"""),18.724800000000002) -> 18.7248 | BS14: =IFERROR(__xludf.DUMMYFUNCTION("""COMPUTED_VALUE"""),135.7548) -> 135.7548 | BT14: =IFERROR(__xludf.DUMMYFUNCTION("""COMPUTED_VALUE"""),112.80000000000001) -> 112.8 | BU14: =IFERROR(__xludf.DUMMYFUNCTION("""COMPUTED_VALUE"""),18.048000000000002) -> 18.048 | BV14: =IFERROR(__xludf.DUMMYFUNCTION("""COMPUTED_VALUE"""),130.848) -> 130.848
A15: 1 | C15: P | D15: AM01 | E15: PZA | F15: REF | G15: ACOMODADOR DE TORTILLAS ESTÁNDAR (10-17 CM.) | H15: ACOMODADOR DE TORTILLAS STD 10-17 CM | I15: =IF(D15="","",LEN(H15)) -> 36 | N15: 780 | O15: 842 | P15: 909.36 | Q15: 909.36 | R15: 1013 | S15: 1064 | T15: =S15*0.16 -> 170.24 | U15: =S15+T15 -> 1234.24 | V15: =(S15-R15)/R15 -> 0.050345508 | W15: =(IF(B15="",(S15*(1-$W$1)),(IF(B15=1,(S15*(1-$W$1)),(IF(B15=2,(S15*(1-$W$1)),(IF(B15=3,(S15*(1-$W$1)),(IF(B15=4,(S15*(1)))))))))))) -> 1010.8 | X15: =W15*0.16 -> 161.728 | Y15: =W15+X15 -> 1172.528 | Z15: =(IF(B15="",(S15*(1-$Z$1)),(IF(B15=1,(S15*(1-$Z$1)),(IF(B15=2,(S15*(1-$Z$1)),(IF(B15=3,(S15*(1-$Z$1)),(IF(B15=4,(S15*(1)))))))))))) -> 957.6 | AA15: =Z15*0.16 -> 153.216 | AB15: =Z15+AA15 -> 1110.816 | AC15: =(IF(B15="",(S15*(1-$AC$1)),(IF(B15=1,(S15*(1-$AC$1)),(IF(B15=2,(S15*(1-0.15)),(IF(B15=3,(S15*(1-0.1)),(IF(B15=4,(S15*(1)))))))))))) -> 904.4 | AD15: =AC15*0.16 -> 144.704 | AE15: =AC15+AD15 -> 1049.104 | AF15: =(IF(B15="",(S15*(1-$AF$1)),(IF(B15=1,(S15*(1-$AF$1)),(IF(B15=2,(S15*(1-0.15)),(IF(B15=3,(S15*(1-0.1)),(IF(B15=4,(S15*(1)))))))))))) -> 883.12 | AG15: =AF15*0.16 -> 141.2992 | AH15: =AF15+AG15 -> 1024.4192 | AI15: =(IF(B15="",(S15*(1-$AI$1)),(IF(B15=1,(S15*(1-$AI$1)),(IF(B15=2,(S15*(1-0.15)),(IF(B15=3,(S15*(1-0.1)),(IF(B15=4,(S15*(1)))))))))))) -> 851.2 | AJ15: =AI15*0.16 -> 136.192 | AK15: =AI15+AJ15 -> 987.392 | AL15: =IFERROR(__xludf.DUMMYFUNCTION("""COMPUTED_VALUE"""),1.0) -> 1 | AN15: =IFERROR(__xludf.DUMMYFUNCTION("""COMPUTED_VALUE""")," C") -> C | AO15: =IFERROR(__xludf.DUMMYFUNCTION("""COMPUTED_VALUE""")," AN04") -> AN04 | AP15: =IFERROR(__xludf.DUMMYFUNCTION("""COMPUTED_VALUE""")," CUB") -> CUB | AQ15: =IFERROR(__xludf.DUMMYFUNCTION("""COMPUTED_VALUE""")," REF") -> REF | AR15: =IFERROR(__xludf.DUMMYFUNCTION("""COMPUTED_VALUE""")," ANTIADHERENTE ""B"" 19 LITROS") -> ANTIADHERENTE "B" 19 LITROS | AS15: =IFERROR(__xludf.DUMMYFUNCTION("""COMPUTED_VALUE""")," ANTIADHERENTE B 19 LITROS") -> ANTIADHERENTE B 19 LITROS | AT15: =IFERROR(__xludf.DUMMYFUNCTION("""COMPUTED_VALUE"""),25.0) -> 25 | AY15: =IFERROR(__xludf.DUMMYFUNCTION("""COMPUTED_VALUE"""),2567.0) -> 2567 | AZ15: =IFERROR(__xludf.DUMMYFUNCTION("""COMPUTED_VALUE"""),1763.0) -> 1763 | BA15: =IFERROR(__xludf.DUMMYFUNCTION("""COMPUTED_VALUE"""),1675.8) -> 1675.8 | BB15: =IFERROR(__xludf.DUMMYFUNCTION("""COMPUTED_VALUE"""),1675.8) -> 1675.8 | BC15: =IFERROR(__xludf.DUMMYFUNCTION("""COMPUTED_VALUE"""),1866.0) -> 1866 | BD15: =IFERROR(__xludf.DUMMYFUNCTION("""COMPUTED_VALUE"""),1959.0) -> 1959 | BE15: =IFERROR(__xludf.DUMMYFUNCTION("""COMPUTED_VALUE"""),313.44) -> 313.44 | BF15: =IFERROR(__xludf.DUMMYFUNCTION("""COMPUTED_VALUE"""),2272.44) -> 2272.44 | BG15: =IFERROR(__xludf.DUMMYFUNCTION("""COMPUTED_VALUE"""),0.04983922829581994) -> 0.049839228 | BH15: =IFERROR(__xludf.DUMMYFUNCTION("""COMPUTED_VALUE"""),1861.05) -> 1861.05 | BI15: =IFERROR(__xludf.DUMMYFUNCTION("""COMPUTED_VALUE"""),297.768) -> 297.768 | BJ15: =IFERROR(__xludf.DUMMYFUNCTION("""COMPUTED_VALUE"""),2158.8179999999998) -> 2158.818 | BK15: =IFERROR(__xludf.DUMMYFUNCTION("""COMPUTED_VALUE"""),1763.1000000000001) -> 1763.1 | BL15: =IFERROR(__xludf.DUMMYFUNCTION("""COMPUTED_VALUE"""),282.096) -> 282.096 | BM15: =IFERROR(__xludf.DUMMYFUNCTION("""COMPUTED_VALUE"""),2045.1960000000001) -> 2045.196 | BN15: =IFERROR(__xludf.DUMMYFUNCTION("""COMPUTED_VALUE"""),1665.1499999999999) -> 1665.15 | BO15: =IFERROR(__xludf.DUMMYFUNCTION("""COMPUTED_VALUE"""),266.424) -> 266.424 | BP15: =IFERROR(__xludf.DUMMYFUNCTION("""COMPUTED_VALUE"""),1931.5739999999998) -> 1931.574 | BQ15: =IFERROR(__xludf.DUMMYFUNCTION("""COMPUTED_VALUE"""),1625.97) -> 1625.97 | BR15: =IFERROR(__xludf.DUMMYFUNCTION("""COMPUTED_VALUE"""),260.15520000000004) -> 260.1552 | BS15: =IFERROR(__xludf.DUMMYFUNCTION("""COMPUTED_VALUE"""),1886.1252) -> 1886.1252 | BT15: =IFERROR(__xludf.DUMMYFUNCTION("""COMPUTED_VALUE"""),1567.2) -> 1567.2 | BU15: =IFERROR(__xludf.DUMMYFUNCTION("""COMPUTED_VALUE"""),250.752) -> 250.752 | BV15: =IFERROR(__xludf.DUMMYFUNCTION("""COMPUTED_VALUE"""),1817.952) -> 1817.952
A16: 1 | C16: P | D16: AM02 | E16: PZA | F16: REF | G16: ACOMODADOR DE TORTILLAS TIPO PUEBLA | H16: ACOMODADOR DE TORTILLAS TIPO PUEBLA | I16: =IF(D16="","",LEN(H16)) -> 36 | N16: 898 | O16: 969 | P16: 1046.52 | Q16: 1046.52 | R16: 1166 | S16: 1224 | T16: =S16*0.16 -> 195.84 | U16: =S16+T16 -> 1419.84 | V16: =(S16-R16)/R16 -> 0.04974271 | W16: =(IF(B16="",(S16*(1-$W$1)),(IF(B16=1,(S16*(1-$W$1)),(IF(B16=2,(S16*(1-$W$1)),(IF(B16=3,(S16*(1-$W$1)),(IF(B16=4,(S16*(1)))))))))))) -> 1162.8 | X16: =W16*0.16 -> 186.048 | Y16: =W16+X16 -> 1348.848 | Z16: =(IF(B16="",(S16*(1-$Z$1)),(IF(B16=1,(S16*(1-$Z$1)),(IF(B16=2,(S16*(1-$Z$1)),(IF(B16=3,(S16*(1-$Z$1)),(IF(B16=4,(S16*(1)))))))))))) -> 1101.6 | AA16: =Z16*0.16 -> 176.256 | AB16: =Z16+AA16 -> 1277.856 | AC16: =(IF(B16="",(S16*(1-$AC$1)),(IF(B16=1,(S16*(1-$AC$1)),(IF(B16=2,(S16*(1-0.15)),(IF(B16=3,(S16*(1-0.1)),(IF(B16=4,(S16*(1)))))))))))) -> 1040.4 | AD16: =AC16*0.16 -> 166.464 | AE16: =AC16+AD16 -> 1206.864 | AF16: =(IF(B16="",(S16*(1-$AF$1)),(IF(B16=1,(S16*(1-$AF$1)),(IF(B16=2,(S16*(1-0.15)),(IF(B16=3,(S16*(1-0.1)),(IF(B16=4,(S16*(1)))))))))))) -> 1015.92 | AG16: =AF16*0.16 -> 162.5472 | AH16: =AF16+AG16 -> 1178.4672 | AI16: =(IF(B16="",(S16*(1-$AI$1)),(IF(B16=1,(S16*(1-$AI$1)),(IF(B16=2,(S16*(1-0.15)),(IF(B16=3,(S16*(1-0.1)),(IF(B16=4,(S16*(1)))))))))))) -> 979.2 | AJ16: =AI16*0.16 -> 156.672 | AK16: =AI16+AJ16 -> 1135.872 | AL16: =IFERROR(__xludf.DUMMYFUNCTION("""COMPUTED_VALUE"""),1.0) -> 1 | AN16: =IFERROR(__xludf.DUMMYFUNCTION("""COMPUTED_VALUE""")," C") -> C | AO16: =IFERROR(__xludf.DUMMYFUNCTION("""COMPUTED_VALUE""")," AN05") -> AN05 | AP16: =IFERROR(__xludf.DUMMYFUNCTION("""COMPUTED_VALUE""")," GAL") -> GAL | AQ16: =IFERROR(__xludf.DUMMYFUNCTION("""COMPUTED_VALUE""")," REF") -> REF | AR16: =IFERROR(__xludf.DUMMYFUNCTION("""COMPUTED_VALUE""")," ANTIADHERENTE ""B"" GALÓN") -> ANTIADHERENTE "B" GALÓN | AS16: =IFERROR(__xludf.DUMMYFUNCTION("""COMPUTED_VALUE""")," ANTIADHERENTE B GALON") -> ANTIADHERENTE B GALON | AT16: =IFERROR(__xludf.DUMMYFUNCTION("""COMPUTED_VALUE"""),21.0) -> 21 | AY16: =IFERROR(__xludf.DUMMYFUNCTION("""COMPUTED_VALUE"""),540.0) -> 540 | AZ16: =IFERROR(__xludf.DUMMYFUNCTION("""COMPUTED_VALUE"""),371.0) -> 371 | BA16: =IFERROR(__xludf.DUMMYFUNCTION("""COMPUTED_VALUE"""),352.8) -> 352.8 | BB16: =IFERROR(__xludf.DUMMYFUNCTION("""COMPUTED_VALUE"""),352.8) -> 352.8 | BC16: =IFERROR(__xludf.DUMMYFUNCTION("""COMPUTED_VALUE"""),393.0) -> 393 | BD16: =IFERROR(__xludf.DUMMYFUNCTION("""COMPUTED_VALUE"""),413.0) -> 413 | BE16: =IFERROR(__xludf.DUMMYFUNCTION("""COMPUTED_VALUE"""),66.08) -> 66.08 | BF16: =IFERROR(__xludf.DUMMYFUNCTION("""COMPUTED_VALUE"""),479.08) -> 479.08 | BG16: =IFERROR(__xludf.DUMMYFUNCTION("""COMPUTED_VALUE"""),0.05089058524173028) -> 0.050890585 | BH16: =IFERROR(__xludf.DUMMYFUNCTION("""COMPUTED_VALUE"""),392.34999999999997) -> 392.35 | BI16: =IFERROR(__xludf.DUMMYFUNCTION("""COMPUTED_VALUE"""),62.775999999999996) -> 62.776 | BJ16: =IFERROR(__xludf.DUMMYFUNCTION("""COMPUTED_VALUE"""),455.126) -> 455.126 | BK16: =IFERROR(__xludf.DUMMYFUNCTION("""COMPUTED_VALUE"""),371.7) -> 371.7 | BL16: =IFERROR(__xludf.DUMMYFUNCTION("""COMPUTED_VALUE"""),59.472) -> 59.472 | BM16: =IFERROR(__xludf.DUMMYFUNCTION("""COMPUTED_VALUE"""),431.17199999999997) -> 431.172 | BN16: =IFERROR(__xludf.DUMMYFUNCTION("""COMPUTED_VALUE"""),351.05) -> 351.05 | BO16: =IFERROR(__xludf.DUMMYFUNCTION("""COMPUTED_VALUE"""),56.168000000000006) -> 56.168 | BP16: =IFERROR(__xludf.DUMMYFUNCTION("""COMPUTED_VALUE"""),407.218) -> 407.218 | BQ16: =IFERROR(__xludf.DUMMYFUNCTION("""COMPUTED_VALUE"""),342.78999999999996) -> 342.79 | BR16: =IFERROR(__xludf.DUMMYFUNCTION("""COMPUTED_VALUE"""),54.846399999999996) -> 54.8464 | BS16: =IFERROR(__xludf.DUMMYFUNCTION("""COMPUTED_VALUE"""),397.6364) -> 397.6364 | BT16: =IFERROR(__xludf.DUMMYFUNCTION("""COMPUTED_VALUE"""),330.40000000000003) -> 330.4 | BU16: =IFERROR(__xludf.DUMMYFUNCTION("""COMPUTED_VALUE"""),52.864000000000004) -> 52.864 | BV16: =IFERROR(__xludf.DUMMYFUNCTION("""COMPUTED_VALUE"""),383.264) -> 383.264
A17: 1 | C17: P | D17: AM18 | E17: JGO | F17: REF | G17: ACOMODADOR DE TORTILLAS TIPO PUEBLA CON TIRANTES (18-22 CM.) | H17: ACOMODADOR TORT. T/PUE C/TIRANT 18-22 CM | I17: =IF(D17="","",LEN(H17)) -> 40 | N17: 1026 | O17: 1108 | P17: 1196.64 | Q17: 1196.64 | R17: 1257 | S17: 1320 | T17: =S17*0.16 -> 211.2 | U17: =S17+T17 -> 1531.2 | V17: =(S17-R17)/R17 -> 0.050119332 | W17: =(IF(B17="",(S17*(1-$W$1)),(IF(B17=1,(S17*(1-$W$1)),(IF(B17=2,(S17*(1-$W$1)),(IF(B17=3,(S17*(1-$W$1)),(IF(B17=4,(S17*(1)))))))))))) -> 1254 | X17: =W17*0.16 -> 200.64 | Y17: =W17+X17 -> 1454.64 | Z17: =(IF(B17="",(S17*(1-$Z$1)),(IF(B17=1,(S17*(1-$Z$1)),(IF(B17=2,(S17*(1-$Z$1)),(IF(B17=3,(S17*(1-$Z$1)),(IF(B17=4,(S17*(1)))))))))))) -> 1188 | AA17: =Z17*0.16 -> 190.08 | AB17: =Z17+AA17 -> 1378.08 | AC17: =(IF(B17="",(S17*(1-$AC$1)),(IF(B17=1,(S17*(1-$AC$1)),(IF(B17=2,(S17*(1-0.15)),(IF(B17=3,(S17*(1-0.1)),(IF(B17=4,(S17*(1)))))))))))) -> 1122 | AD17: =AC17*0.16 -> 179.52 | AE17: =AC17+AD17 -> 1301.52 | AF17: =(IF(B17="",(S17*(1-$AF$1)),(IF(B17=1,(S17*(1-$AF$1)),(IF(B17=2,(S17*(1-0.15)),(IF(B17=3,(S17*(1-0.1)),(IF(B17=4,(S17*(1)))))))))))) -> 1095.6 | AG17: =AF17*0.16 -> 175.296 | AH17: =AF17+AG17 -> 1270.896 | AI17: =(IF(B17="",(S17*(1-$AI$1)),(IF(B17=1,(S17*(1-$AI$1)),(IF(B17=2,(S17*(1-0.15)),(IF(B17=3,(S17*(1-0.1)),(IF(B17=4,(S17*(1)))))))))))) -> 1056 | AJ17: =AI17*0.16 -> 168.96 | AK17: =AI17+AJ17 -> 1224.96 | AL17: =IFERROR(__xludf.DUMMYFUNCTION("""COMPUTED_VALUE"""),1.0) -> 1 | AN17: =IFERROR(__xludf.DUMMYFUNCTION("""COMPUTED_VALUE""")," C") -> C | AO17: =IFERROR(__xludf.DUMMYFUNCTION("""COMPUTED_VALUE""")," AN06") -> AN06 | AP17: =IFERROR(__xludf.DUMMYFUNCTION("""COMPUTED_VALUE""")," LTR") -> LTR | AQ17: =IFERROR(__xludf.DUMMYFUNCTION("""COMPUTED_VALUE""")," REF") -> REF | AR17: =IFERROR(__xludf.DUMMYFUNCTION("""COMPUTED_VALUE""")," ANTIADHERENTE ""B"" LITRO") -> ANTIADHERENTE "B" LITRO | AS17: =IFERROR(__xludf.DUMMYFUNCTION("""COMPUTED_VALUE""")," ANTIADHERENTE B LITRO") -> ANTIADHERENTE B LITRO | AT17: =IFERROR(__xludf.DUMMYFUNCTION("""COMPUTED_VALUE"""),21.0) -> 21 | AY17: =IFERROR(__xludf.DUMMYFUNCTION("""COMPUTED_VALUE"""),144.0) -> 144 | AZ17: =IFERROR(__xludf.DUMMYFUNCTION("""COMPUTED_VALUE"""),93.0) -> 93 | BA17: =IFERROR(__xludf.DUMMYFUNCTION("""COMPUTED_VALUE"""),88.2) -> 88.2 | BB17: =IFERROR(__xludf.DUMMYFUNCTION("""COMPUTED_VALUE"""),88.2) -> 88.2 | BC17: =IFERROR(__xludf.DUMMYFUNCTION("""COMPUTED_VALUE"""),99.0) -> 99 | BD17: =IFERROR(__xludf.DUMMYFUNCTION("""COMPUTED_VALUE"""),104.0) -> 104 | BE17: =IFERROR(__xludf.DUMMYFUNCTION("""COMPUTED_VALUE"""),16.64) -> 16.64 | BF17: =IFERROR(__xludf.DUMMYFUNCTION("""COMPUTED_VALUE"""),120.64) -> 120.64 | BG17: =IFERROR(__xludf.DUMMYFUNCTION("""COMPUTED_VALUE"""),0.050505050505050504) -> 0.050505051 | BH17: =IFERROR(__xludf.DUMMYFUNCTION("""COMPUTED_VALUE"""),98.8) -> 98.8 | BI17: =IFERROR(__xludf.DUMMYFUNCTION("""COMPUTED_VALUE"""),15.808) -> 15.808 | BJ17: =IFERROR(__xludf.DUMMYFUNCTION("""COMPUTED_VALUE"""),114.608) -> 114.608 | BK17: =IFERROR(__xludf.DUMMYFUNCTION("""COMPUTED_VALUE"""),93.60000000000001) -> 93.6 | BL17: =IFERROR(__xludf.DUMMYFUNCTION("""COMPUTED_VALUE"""),14.976) -> 14.976 | BM17: =IFERROR(__xludf.DUMMYFUNCTION("""COMPUTED_VALUE"""),108.57600000000001) -> 108.576 | BN17: =IFERROR(__xludf.DUMMYFUNCTION("""COMPUTED_VALUE"""),88.39999999999999) -> 88.4 | BO17: =IFERROR(__xludf.DUMMYFUNCTION("""COMPUTED_VALUE"""),14.143999999999998) -> 14.144 | BP17: =IFERROR(__xludf.DUMMYFUNCTION("""COMPUTED_VALUE"""),102.54399999999998) -> 102.544 | BQ17: =IFERROR(__xludf.DUMMYFUNCTION("""COMPUTED_VALUE"""),86.32) -> 86.32 | BR17: =IFERROR(__xludf.DUMMYFUNCTION("""COMPUTED_VALUE"""),13.8112) -> 13.8112 | BS17: =IFERROR(__xludf.DUMMYFUNCTION("""COMPUTED_VALUE"""),100.13119999999999) -> 100.1312 | BT17: =IFERROR(__xludf.DUMMYFUNCTION("""COMPUTED_VALUE"""),83.2) -> 83.2 | BU17: =IFERROR(__xludf.DUMMYFUNCTION("""COMPUTED_VALUE"""),13.312000000000001) -> 13.312 | BV17: =IFERROR(__xludf.DUMMYFUNCTION("""COMPUTED_VALUE"""),96.512) -> 96.512
D18: AM08 | E18: PZA | G18: ACOMODADOR TORTILLAS AUTOM SENCILLO 10CM | I18: =IF(D18="","",LEN(H18)) -> 0 | P18: 7624 | Q18: 7624 | R18: 8406 | S18: 8826 | T18: =S18*0.16 -> 1412.16 | U18: =S18+T18 -> 10238.16 | V18: =(S18-R18)/R18 -> 0.049964311 | W18: =(IF(B18="",(S18*(1-$W$1)),(IF(B18=1,(S18*(1-$W$1)),(IF(B18=2,(S18*(1-$W$1)),(IF(B18=3,(S18*(1-$W$1)),(IF(B18=4,(S18*(1)))))))))))) -> 8384.7 | X18: =W18*0.16 -> 1341.552 | Y18: =W18+X18 -> 9726.252 | Z18: =(IF(B18="",(S18*(1-$Z$1)),(IF(B18=1,(S18*(1-$Z$1)),(IF(B18=2,(S18*(1-$Z$1)),(IF(B18=3,(S18*(1-$Z$1)),(IF(B18=4,(S18*(1)))))))))))) -> 7943.4 | AA18: =Z18*0.16 -> 1270.944 | AB18: =Z18+AA18 -> 9214.344 | AC18: =(IF(B18="",(S18*(1-$AC$1)),(IF(B18=1,(S18*(1-$AC$1)),(IF(B18=2,(S18*(1-0.15)),(IF(B18=3,(S18*(1-0.1)),(IF(B18=4,(S18*(1)))))))))))) -> 7502.1 | AD18: =AC18*0.16 -> 1200.336 | AE18: =AC18+AD18 -> 8702.436 | AF18: =(IF(B18="",(S18*(1-$AF$1)),(IF(B18=1,(S18*(1-$AF$1)),(IF(B18=2,(S18*(1-0.15)),(IF(B18=3,(S18*(1-0.1)),(IF(B18=4,(S18*(1)))))))))))) -> 7325.58 | AG18: =AF18*0.16 -> 1172.0928 | AH18: =AF18+AG18 -> 8497.6728 | AI18: =(IF(B18="",(S18*(1-$AI$1)),(IF(B18=1,(S18*(1-$AI$1)),(IF(B18=2,(S18*(1-0.15)),(IF(B18=3,(S18*(1-0.1)),(IF(B18=4,(S18*(1)))))))))))) -> 7060.8 | AJ18: =AI18*0.16 -> 1129.728 | AK18: =AI18+AJ18 -> 8190.528 | AL18: =IFERROR(__xludf.DUMMYFUNCTION("""COMPUTED_VALUE"""),1.0) -> 1 | AN18: =IFERROR(__xludf.DUMMYFUNCTION("""COMPUTED_VALUE""")," C") -> C | AO18: =IFERROR(__xludf.DUMMYFUNCTION("""COMPUTED_VALUE""")," AN07") -> AN07 | AP18: =IFERROR(__xludf.DUMMYFUNCTION("""COMPUTED_VALUE""")," CUB") -> CUB | AQ18: =IFERROR(__xludf.DUMMYFUNCTION("""COMPUTED_VALUE""")," REF") -> REF | AR18: =IFERROR(__xludf.DUMMYFUNCTION("""COMPUTED_VALUE""")," ANTIADHERENTE ""TRANSPARENTE"" 19 LITROS") -> ANTIADHERENTE "TRANSPARENTE" 19 LITROS | AS18: =IFERROR(__xludf.DUMMYFUNCTION("""COMPUTED_VALUE""")," ANTIADHERENTE TRANSPARENTE 19 LITROS") -> ANTIADHERENTE TRANSPARENTE 19 LITROS | AT18: =IFERROR(__xludf.DUMMYFUNCTION("""COMPUTED_VALUE"""),36.0) -> 36 | AY18: =IFERROR(__xludf.DUMMYFUNCTION("""COMPUTED_VALUE"""),4820.0) -> 4820 | AZ18: =IFERROR(__xludf.DUMMYFUNCTION("""COMPUTED_VALUE"""),3739.0) -> 3739 | BA18: =IFERROR(__xludf.DUMMYFUNCTION("""COMPUTED_VALUE"""),2907.0) -> 2907 | BB18: =IFERROR(__xludf.DUMMYFUNCTION("""COMPUTED_VALUE"""),2907.0) -> 2907 | BC18: =IFERROR(__xludf.DUMMYFUNCTION("""COMPUTED_VALUE"""),3237.0) -> 3237 | BD18: =IFERROR(__xludf.DUMMYFUNCTION("""COMPUTED_VALUE"""),3399.0) -> 3399 | BE18: =IFERROR(__xludf.DUMMYFUNCTION("""COMPUTED_VALUE"""),543.84) -> 543.84 | BF18: =IFERROR(__xludf.DUMMYFUNCTION("""COMPUTED_VALUE"""),3942.84) -> 3942.84 | BG18: =IFERROR(__xludf.DUMMYFUNCTION("""COMPUTED_VALUE"""),0.05004633920296571) -> 0.050046339 | BH18: =IFERROR(__xludf.DUMMYFUNCTION("""COMPUTED_VALUE"""),3229.0499999999997) -> 3229.05 | BI18: =IFERROR(__xludf.DUMMYFUNCTION("""COMPUTED_VALUE"""),516.6479999999999) -> 516.648 | BJ18: =IFERROR(__xludf.DUMMYFUNCTION("""COMPUTED_VALUE"""),3745.6979999999994) -> 3745.698 | BK18: =IFERROR(__xludf.DUMMYFUNCTION("""COMPUTED_VALUE"""),3059.1) -> 3059.1 | BL18: =IFERROR(__xludf.DUMMYFUNCTION("""COMPUTED_VALUE"""),489.456) -> 489.456 | BM18: =IFERROR(__xludf.DUMMYFUNCTION("""COMPUTED_VALUE"""),3548.556) -> 3548.556 | BN18: =IFERROR(__xludf.DUMMYFUNCTION("""COMPUTED_VALUE"""),2889.15) -> 2889.15 | BO18: =IFERROR(__xludf.DUMMYFUNCTION("""COMPUTED_VALUE"""),462.264) -> 462.264 | BP18: =IFERROR(__xludf.DUMMYFUNCTION("""COMPUTED_VALUE"""),3351.414) -> 3351.414 | BQ18: =IFERROR(__xludf.DUMMYFUNCTION("""COMPUTED_VALUE"""),2821.17) -> 2821.17 | BR18: =IFERROR(__xludf.DUMMYFUNCTION("""COMPUTED_VALUE"""),451.3872) -> 451.3872 | BS18: =IFERROR(__xludf.DUMMYFUNCTION("""COMPUTED_VALUE"""),3272.5572) -> 3272.5572 | BT18: =IFERROR(__xludf.DUMMYFUNCTION("""COMPUTED_VALUE"""),2719.2000000000003) -> 2719.2 | BU18: =IFERROR(__xludf.DUMMYFUNCTION("""COMPUTED_VALUE"""),435.07200000000006) -> 435.072 | BV18: =IFERROR(__xludf.DUMMYFUNCTION("""COMPUTED_VALUE"""),3154.2720000000004) -> 3154.272
D19: AM09 | E19: PZA | G19: ACOMODADOR TORTILLAS AUTOM SENCILLO 17CM | I19: =IF(D19="","",LEN(H19)) -> 0 | P19: 8331 | Q19: 8331 | R19: 9186 | S19: 9645 | T19: =S19*0.16 -> 1543.2 | U19: =S19+T19 -> 11188.2 | V19: =(S19-R19)/R19 -> 0.049967342 | W19: =(IF(B19="",(S19*(1-$W$1)),(IF(B19=1,(S19*(1-$W$1)),(IF(B19=2,(S19*(1-$W$1)),(IF(B19=3,(S19*(1-$W$1)),(IF(B19=4,(S19*(1)))))))))))) -> 9162.75 | X19: =W19*0.16 -> 1466.04 | Y19: =W19+X19 -> 10628.79 | Z19: =(IF(B19="",(S19*(1-$Z$1)),(IF(B19=1,(S19*(1-$Z$1)),(IF(B19=2,(S19*(1-$Z$1)),(IF(B19=3,(S19*(1-$Z$1)),(IF(B19=4,(S19*(1)))))))))))) -> 8680.5 | AA19: =Z19*0.16 -> 1388.88 | AB19: =Z19+AA19 -> 10069.38 | AC19: =(IF(B19="",(S19*(1-$AC$1)),(IF(B19=1,(S19*(1-$AC$1)),(IF(B19=2,(S19*(1-0.15)),(IF(B19=3,(S19*(1-0.1)),(IF(B19=4,(S19*(1)))))))))))) -> 8198.25 | AD19: =AC19*0.16 -> 1311.72 | AE19: =AC19+AD19 -> 9509.97 | AF19: =(IF(B19="",(S19*(1-$AF$1)),(IF(B19=1,(S19*(1-$AF$1)),(IF(B19=2,(S19*(1-0.15)),(IF(B19=3,(S19*(1-0.1)),(IF(B19=4,(S19*(1)))))))))))) -> 8005.35 | AG19: =AF19*0.16 -> 1280.856 | AH19: =AF19+AG19 -> 9286.206 | AI19: =(IF(B19="",(S19*(1-$AI$1)),(IF(B19=1,(S19*(1-$AI$1)),(IF(B19=2,(S19*(1-0.15)),(IF(B19=3,(S19*(1-0.1)),(IF(B19=4,(S19*(1)))))))))))) -> 7716 | AJ19: =AI19*0.16 -> 1234.56 | AK19: =AI19+AJ19 -> 8950.56 | AL19: =IFERROR(__xludf.DUMMYFUNCTION("""COMPUTED_VALUE"""),1.0) -> 1 | AN19: =IFERROR(__xludf.DUMMYFUNCTION("""COMPUTED_VALUE""")," C") -> C | AO19: =IFERROR(__xludf.DUMMYFUNCTION("""COMPUTED_VALUE""")," AN08") -> AN08 | AP19: =IFERROR(__xludf.DUMMYFUNCTION("""COMPUTED_VALUE""")," GAL") -> GAL | AQ19: =IFERROR(__xludf.DUMMYFUNCTION("""COMPUTED_VALUE""")," REF") -> REF | AR19: =IFERROR(__xludf.DUMMYFUNCTION("""COMPUTED_VALUE""")," ANTIADHERENTE ""TRANSPARENTE"" GALÓN") -> ANTIADHERENTE "TRANSPARENTE" GALÓN | AS19: =IFERROR(__xludf.DUMMYFUNCTION("""COMPUTED_VALUE""")," ANTIADHERENTE TRANSPARENTE GALON") -> ANTIADHERENTE TRANSPARENTE GALON | AT19: =IFERROR(__xludf.DUMMYFUNCTION("""COMPUTED_VALUE"""),32.0) -> 32 | AY19: =IFERROR(__xludf.DUMMYFUNCTION("""COMPUTED_VALUE"""),1055.0) -> 1055 | AZ19: =IFERROR(__xludf.DUMMYFUNCTION("""COMPUTED_VALUE"""),787.0) -> 787 | BA19: =IFERROR(__xludf.DUMMYFUNCTION("""COMPUTED_VALUE"""),612.0) -> 612 | BB19: =IFERROR(__xludf.DUMMYFUNCTION("""COMPUTED_VALUE"""),612.0) -> 612 | BC19: =IFERROR(__xludf.DUMMYFUNCTION("""COMPUTED_VALUE"""),682.0) -> 682 | BD19: =IFERROR(__xludf.DUMMYFUNCTION("""COMPUTED_VALUE"""),716.0) -> 716 | BE19: =IFERROR(__xludf.DUMMYFUNCTION("""COMPUTED_VALUE"""),114.56) -> 114.56 | BF19: =IFERROR(__xludf.DUMMYFUNCTION("""COMPUTED_VALUE"""),830.56) -> 830.56 | BG19: =IFERROR(__xludf.DUMMYFUNCTION("""COMPUTED_VALUE"""),0.04985337243401759) -> 0.049853372 | BH19: =IFERROR(__xludf.DUMMYFUNCTION("""COMPUTED_VALUE"""),680.1999999999999) -> 680.2 | BI19: =IFERROR(__xludf.DUMMYFUNCTION("""COMPUTED_VALUE"""),108.832) -> 108.832 | BJ19: =IFERROR(__xludf.DUMMYFUNCTION("""COMPUTED_VALUE"""),789.0319999999999) -> 789.032 | BK19: =IFERROR(__xludf.DUMMYFUNCTION("""COMPUTED_VALUE"""),644.4) -> 644.4 | BL19: =IFERROR(__xludf.DUMMYFUNCTION("""COMPUTED_VALUE"""),103.104) -> 103.104 | BM19: =IFERROR(__xludf.DUMMYFUNCTION("""COMPUTED_VALUE"""),747.504) -> 747.504 | BN19: =IFERROR(__xludf.DUMMYFUNCTION("""COMPUTED_VALUE"""),608.6) -> 608.6 | BO19: =IFERROR(__xludf.DUMMYFUNCTION("""COMPUTED_VALUE"""),97.376) -> 97.376 | BP19: =IFERROR(__xludf.DUMMYFUNCTION("""COMPUTED_VALUE"""),705.976) -> 705.976 | BQ19: =IFERROR(__xludf.DUMMYFUNCTION("""COMPUTED_VALUE"""),594.28) -> 594.28 | BR19: =IFERROR(__xludf.DUMMYFUNCTION("""COMPUTED_VALUE"""),95.0848) -> 95.0848 | BS19: =IFERROR(__xludf.DUMMYFUNCTION("""COMPUTED_VALUE"""),689.3648) -> 689.3648 | BT19: =IFERROR(__xludf.DUMMYFUNCTION("""COMPUTED_VALUE"""),572.8000000000001) -> 572.8 | BU19: =IFERROR(__xludf.DUMMYFUNCTION("""COMPUTED_VALUE"""),91.64800000000001) -> 91.648 | BV19: =IFERROR(__xludf.DUMMYFUNCTION("""COMPUTED_VALUE"""),664.4480000000001) -> 664.448
C20: E | D20: RL03 | E20: RLL | F20: WAL | G20: ALAMBRE DESPEGADOR 120 GR | H20: ALAMBRE DESPEGADOR 120 GR | I20: =IF(D20="","",LEN(H20)) -> 25 | O20: 462.72 | P20: 499.7376 | Q20: 499.7376 | R20: 525 | S20: 551 | T20: =S20*0.16 -> 88.16 | U20: =S20+T20 -> 639.16 | V20: =(S20-R20)/R20 -> 0.04952381 | W20: =(IF(B20="",(S20*(1-$W$1)),(IF(B20=1,(S20*(1-$W$1)),(IF(B20=2,(S20*(1-$W$1)),(IF(B20=3,(S20*(1-$W$1)),(IF(B20=4,(S20*(1)))))))))))) -> 523.45 | X20: =W20*0.16 -> 83.752 | Y20: =W20+X20 -> 607.202 | Z20: =(IF(B20="",(S20*(1-$Z$1)),(IF(B20=1,(S20*(1-$Z$1)),(IF(B20=2,(S20*(1-$Z$1)),(IF(B20=3,(S20*(1-$Z$1)),(IF(B20=4,(S20*(1)))))))))))) -> 495.9 | AA20: =Z20*0.16 -> 79.344 | AB20: =Z20+AA20 -> 575.244 | AC20: =(IF(B20="",(S20*(1-$AC$1)),(IF(B20=1,(S20*(1-$AC$1)),(IF(B20=2,(S20*(1-0.15)),(IF(B20=3,(S20*(1-0.1)),(IF(B20=4,(S20*(1)))))))))))) -> 468.35 | AD20: =AC20*0.16 -> 74.936 | AE20: =AC20+AD20 -> 543.286 | AF20: =(IF(B20="",(S20*(1-$AF$1)),(IF(B20=1,(S20*(1-$AF$1)),(IF(B20=2,(S20*(1-0.15)),(IF(B20=3,(S20*(1-0.1)),(IF(B20=4,(S20*(1)))))))))))) -> 457.33 | AG20: =AF20*0.16 -> 73.1728 | AH20: =AF20+AG20 -> 530.5028 | AI20: =(IF(B20="",(S20*(1-$AI$1)),(IF(B20=1,(S20*(1-$AI$1)),(IF(B20=2,(S20*(1-0.15)),(IF(B20=3,(S20*(1-0.1)),(IF(B20=4,(S20*(1)))))))))))) -> 440.8 | AJ20: =AI20*0.16 -> 70.528 | AK20: =AI20+AJ20 -> 511.328 | AL20: =IFERROR(__xludf.DUMMYFUNCTION("""COMPUTED_VALUE"""),1.0) -> 1 | AN20: =IFERROR(__xludf.DUMMYFUNCTION("""COMPUTED_VALUE""")," C") -> C | AO20: =IFERROR(__xludf.DUMMYFUNCTION("""COMPUTED_VALUE""")," AN09") -> AN09 | AP20: =IFERROR(__xludf.DUMMYFUNCTION("""COMPUTED_VALUE""")," LTR") -> LTR | AQ20: =IFERROR(__xludf.DUMMYFUNCTION("""COMPUTED_VALUE""")," REF") -> REF | AR20: =IFERROR(__xludf.DUMMYFUNCTION("""COMPUTED_VALUE""")," ANTIADHERENTE ""TRANSPARENTE"" LITRO") -> ANTIADHERENTE "TRANSPARENTE" LITRO | AS20: =IFERROR(__xludf.DUMMYFUNCTION("""COMPUTED_VALUE""")," ANTIADHERENTE TRANSPARENTE LITRO") -> ANTIADHERENTE TRANSPARENTE LITRO | AT20: =IFERROR(__xludf.DUMMYFUNCTION("""COMPUTED_VALUE"""),32.0) -> 32 | AY20: =IFERROR(__xludf.DUMMYFUNCTION("""COMPUTED_VALUE"""),254.0) -> 254 | AZ20: =IFERROR(__xludf.DUMMYFUNCTION("""COMPUTED_VALUE"""),197.0) -> 197 | BA20: =IFERROR(__xludf.DUMMYFUNCTION("""COMPUTED_VALUE"""),153.0) -> 153 | BB20: =IFERROR(__xludf.DUMMYFUNCTION("""COMPUTED_VALUE"""),153.0) -> 153 | BC20: =IFERROR(__xludf.DUMMYFUNCTION("""COMPUTED_VALUE"""),172.0) -> 172 | BD20: =IFERROR(__xludf.DUMMYFUNCTION("""COMPUTED_VALUE"""),181.0) -> 181 | BE20: =IFERROR(__xludf.DUMMYFUNCTION("""COMPUTED_VALUE"""),28.96) -> 28.96 | BF20: =IFERROR(__xludf.DUMMYFUNCTION("""COMPUTED_VALUE"""),209.96) -> 209.96 | BG20: =IFERROR(__xludf.DUMMYFUNCTION("""COMPUTED_VALUE"""),0.05232558139534884) -> 0.052325581 | BH20: =IFERROR(__xludf.DUMMYFUNCTION("""COMPUTED_VALUE"""),171.95) -> 171.95 | BI20: =IFERROR(__xludf.DUMMYFUNCTION("""COMPUTED_VALUE"""),27.512) -> 27.512 | BJ20: =IFERROR(__xludf.DUMMYFUNCTION("""COMPUTED_VALUE"""),199.462) -> 199.462 | BK20: =IFERROR(__xludf.DUMMYFUNCTION("""COMPUTED_VALUE"""),162.9) -> 162.9 | BL20: =IFERROR(__xludf.DUMMYFUNCTION("""COMPUTED_VALUE"""),26.064) -> 26.064 | BM20: =IFERROR(__xludf.DUMMYFUNCTION("""COMPUTED_VALUE"""),188.964) -> 188.964 | BN20: =IFERROR(__xludf.DUMMYFUNCTION("""COMPUTED_VALUE"""),153.85) -> 153.85 | BO20: =IFERROR(__xludf.DUMMYFUNCTION("""COMPUTED_VALUE"""),24.616) -> 24.616 | BP20: =IFERROR(__xludf.DUMMYFUNCTION("""COMPUTED_VALUE"""),178.466) -> 178.466 | BQ20: =IFERROR(__xludf.DUMMYFUNCTION("""COMPUTED_VALUE"""),150.23) -> 150.23 | BR20: =IFERROR(__xludf.DUMMYFUNCTION("""COMPUTED_VALUE"""),24.0368) -> 24.0368 | BS20: =IFERROR(__xludf.DUMMYFUNCTION("""COMPUTED_VALUE"""),174.2668) -> 174.2668 | BT20: =IFERROR(__xludf.DUMMYFUNCTION("""COMPUTED_VALUE"""),144.8) -> 144.8 | BU20: =IFERROR(__xludf.DUMMYFUNCTION("""COMPUTED_VALUE"""),23.168000000000003) -> 23.168 | BV20: =IFERROR(__xludf.DUMMYFUNCTION("""COMPUTED_VALUE"""),167.96800000000002) -> 167.968
A21: 1 | C21: C | D21: RL15 | E21: PZA | F21: REF | G21: ALAMBRE DESPEGADOR 15 GR | H21: ALAMBRE DESPEGADOR 15 GR | I21: =IF(D21="","",LEN(H21)) -> 24 | R21: 42 | S21: 44 | T21: =S21*0.16 -> 7.04 | U21: =S21+T21 -> 51.04 | V21: =(S21-R21)/R21 -> 0.047619048 | W21: =(IF(B21="",(S21*(1-$W$1)),(IF(B21=1,(S21*(1-$W$1)),(IF(B21=2,(S21*(1-$W$1)),(IF(B21=3,(S21*(1-$W$1)),(IF(B21=4,(S21*(1)))))))))))) -> 41.8 | X21: =W21*0.16 -> 6.688 | Y21: =W21+X21 -> 48.488 | Z21: =(IF(B21="",(S21*(1-$Z$1)),(IF(B21=1,(S21*(1-$Z$1)),(IF(B21=2,(S21*(1-$Z$1)),(IF(B21=3,(S21*(1-$Z$1)),(IF(B21=4,(S21*(1)))))))))))) -> 39.6 | AA21: =Z21*0.16 -> 6.336 | AB21: =Z21+AA21 -> 45.936 | AC21: =(IF(B21="",(S21*(1-$AC$1)),(IF(B21=1,(S21*(1-$AC$1)),(IF(B21=2,(S21*(1-0.15)),(IF(B21=3,(S21*(1-0.1)),(IF(B21=4,(S21*(1)))))))))))) -> 37.4 | AD21: =AC21*0.16 -> 5.984 | AE21: =AC21+AD21 -> 43.384 | AF21: =(IF(B21="",(S21*(1-$AF$1)),(IF(B21=1,(S21*(1-$AF$1)),(IF(B21=2,(S21*(1-0.15)),(IF(B21=3,(S21*(1-0.1)),(IF(B21=4,(S21*(1)))))))))))) -> 36.52 | AG21: =AF21*0.16 -> 5.8432 | AH21: =AF21+AG21 -> 42.3632 | AI21: =(IF(B21="",(S21*(1-$AI$1)),(IF(B21=1,(S21*(1-$AI$1)),(IF(B21=2,(S21*(1-0.15)),(IF(B21=3,(S21*(1-0.1)),(IF(B21=4,(S21*(1)))))))))))) -> 35.2 | AL21: =IFERROR(__xludf.DUMMYFUNCTION("""COMPUTED_VALUE"""),1.0) -> 1 | AN21: =IFERROR(__xludf.DUMMYFUNCTION("""COMPUTED_VALUE""")," C") -> C | AO21: =IFERROR(__xludf.DUMMYFUNCTION("""COMPUTED_VALUE""")," AN99") -> AN99 | AP21: =IFERROR(__xludf.DUMMYFUNCTION("""COMPUTED_VALUE""")," LTR") -> LTR | AQ21: =IFERROR(__xludf.DUMMYFUNCTION("""COMPUTED_VALUE""")," REF") -> REF | AR21: =IFERROR(__xludf.DUMMYFUNCTION("""COMPUTED_VALUE""")," ANTIADHERENTE ""TRANSPARENTE"" PLUS LITRO") -> ANTIADHERENTE "TRANSPARENTE" PLUS LITRO | AS21: =IFERROR(__xludf.DUMMYFUNCTION("""COMPUTED_VALUE""")," ANTIADHERENTE TRANSPARENTE PLUS LITRO") -> ANTIADHERENTE TRANSPARENTE PLUS LITRO | AT21: =IFERROR(__xludf.DUMMYFUNCTION("""COMPUTED_VALUE"""),37.0) -> 37 | AY21: =IFERROR(__xludf.DUMMYFUNCTION("""COMPUTED_VALUE"""),297.0) -> 297 | AZ21: =IFERROR(__xludf.DUMMYFUNCTION("""COMPUTED_VALUE"""),200.0) -> 200 | BA21: =IFERROR(__xludf.DUMMYFUNCTION("""COMPUTED_VALUE"""),149.4) -> 149.4 | BB21: =IFERROR(__xludf.DUMMYFUNCTION("""COMPUTED_VALUE"""),149.4) -> 149.4 | BC21: =IFERROR(__xludf.DUMMYFUNCTION("""COMPUTED_VALUE"""),167.0) -> 167 | BD21: =IFERROR(__xludf.DUMMYFUNCTION("""COMPUTED_VALUE"""),175.0) -> 175 | BE21: =IFERROR(__xludf.DUMMYFUNCTION("""COMPUTED_VALUE"""),28.0) -> 28 | BF21: =IFERROR(__xludf.DUMMYFUNCTION("""COMPUTED_VALUE"""),203.0) -> 203 | BG21: =IFERROR(__xludf.DUMMYFUNCTION("""COMPUTED_VALUE"""),0.04790419161676647) -> 0.047904192 | BH21: =IFERROR(__xludf.DUMMYFUNCTION("""COMPUTED_VALUE"""),166.25) -> 166.25 | BI21: =IFERROR(__xludf.DUMMYFUNCTION("""COMPUTED_VALUE"""),26.6) -> 26.6 | BJ21: =IFERROR(__xludf.DUMMYFUNCTION("""COMPUTED_VALUE"""),192.85) -> 192.85 | BK21: =IFERROR(__xludf.DUMMYFUNCTION("""COMPUTED_VALUE"""),157.5) -> 157.5 | BL21: =IFERROR(__xludf.DUMMYFUNCTION("""COMPUTED_VALUE"""),25.2) -> 25.2 | BM21: =IFERROR(__xludf.DUMMYFUNCTION("""COMPUTED_VALUE"""),182.7) -> 182.7 | BN21: =IFERROR(__xludf.DUMMYFUNCTION("""COMPUTED_VALUE"""),148.75) -> 148.75 | BO21: =IFERROR(__xludf.DUMMYFUNCTION("""COMPUTED_VALUE"""),23.8) -> 23.8 | BP21: =IFERROR(__xludf.DUMMYFUNCTION("""COMPUTED_VALUE"""),172.55) -> 172.55 | BQ21: =IFERROR(__xludf.DUMMYFUNCTION("""COMPUTED_VALUE"""),145.25) -> 145.25 | BR21: =IFERROR(__xludf.DUMMYFUNCTION("""COMPUTED_VALUE"""),23.240000000000002) -> 23.24 | BS21: =IFERROR(__xludf.DUMMYFUNCTION("""COMPUTED_VALUE"""),168.49) -> 168.49 | BT21: =IFERROR(__xludf.DUMMYFUNCTION("""COMPUTED_VALUE"""),140.0) -> 140 | BU21: =IFERROR(__xludf.DUMMYFUNCTION("""COMPUTED_VALUE"""),22.400000000000002) -> 22.4 | BV21: =IFERROR(__xludf.DUMMYFUNCTION("""COMPUTED_VALUE"""),162.4) -> 162.4
A22: 1 | C22: C | D22: RL90 | E22: PZA | F22: REF | G22: ALAMBRE DESPEGADOR 90 GR | H22: ALAMBRE DESPEGADOR 90 GR | I22: =IF(D22="","",LEN(H22)) -> 24 | R22: 250 | S22: 263 | T22: =S22*0.16 -> 42.08 | U22: =S22+T22 -> 305.08 | V22: =(S22-R22)/R22 -> 0.052 | W22: =(IF(B22="",(S22*(1-$W$1)),(IF(B22=1,(S22*(1-$W$1)),(IF(B22=2,(S22*(1-$W$1)),(IF(B22=3,(S22*(1-$W$1)),(IF(B22=4,(S22*(1)))))))))))) -> 249.85 | X22: =W22*0.16 -> 39.976 | Y22: =W22+X22 -> 289.826 | Z22: =(IF(B22="",(S22*(1-$Z$1)),(IF(B22=1,(S22*(1-$Z$1)),(IF(B22=2,(S22*(1-$Z$1)),(IF(B22=3,(S22*(1-$Z$1)),(IF(B22=4,(S22*(1)))))))))))) -> 236.7 | AA22: =Z22*0.16 -> 37.872 | AB22: =Z22+AA22 -> 274.572 | AC22: =(IF(B22="",(S22*(1-$AC$1)),(IF(B22=1,(S22*(1-$AC$1)),(IF(B22=2,(S22*(1-0.15)),(IF(B22=3,(S22*(1-0.1)),(IF(B22=4,(S22*(1)))))))))))) -> 223.55 | AD22: =AC22*0.16 -> 35.768 | AE22: =AC22+AD22 -> 259.318 | AF22: =(IF(B22="",(S22*(1-$AF$1)),(IF(B22=1,(S22*(1-$AF$1)),(IF(B22=2,(S22*(1-0.15)),(IF(B22=3,(S22*(1-0.1)),(IF(B22=4,(S22*(1)))))))))))) -> 218.29 | AG22: =AF22*0.16 -> 34.9264 | AH22: =AF22+AG22 -> 253.2164 | AI22: =(IF(B22="",(S22*(1-$AI$1)),(IF(B22=1,(S22*(1-$AI$1)),(IF(B22=2,(S22*(1-0.15)),(IF(B22=3,(S22*(1-0.1)),(IF(B22=4,(S22*(1)))))))))))) -> 210.4 | AL22: =IFERROR(__xludf.DUMMYFUNCTION("""COMPUTED_VALUE"""),1.0) -> 1 | AN22: =IFERROR(__xludf.DUMMYFUNCTION("""COMPUTED_VALUE""")," C") -> C | AO22: =IFERROR(__xludf.DUMMYFUNCTION("""COMPUTED_VALUE""")," AR13") -> AR13 | AP22: =IFERROR(__xludf.DUMMYFUNCTION("""COMPUTED_VALUE""")," PZA") -> PZA | AQ22: =IFERROR(__xludf.DUMMYFUNCTION("""COMPUTED_VALUE""")," REF") -> REF | AR22: =IFERROR(__xludf.DUMMYFUNCTION("""COMPUTED_VALUE""")," ARRANCADOR PARA MOTOR DE 10 HP MONOFÁSICO 220V CODIGO 10046372 32~50 AMP") -> ARRANCADOR PARA MOTOR DE 10 HP MONOFÁSICO 220V CODIGO 10046372 32~50 AMP | AS22: =IFERROR(__xludf.DUMMYFUNCTION("""COMPUTED_VALUE""")," ARRANCADOR 10HP MON 220V 10046372 32-50A") -> ARRANCADOR 10HP MON 220V 10046372 32-50A | AT22: =IFERROR(__xludf.DUMMYFUNCTION("""COMPUTED_VALUE"""),40.0) -> 40 | AY22: =IFERROR(__xludf.DUMMYFUNCTION("""COMPUTED_VALUE"""),6858.0) -> 6858 | AZ22: =IFERROR(__xludf.DUMMYFUNCTION("""COMPUTED_VALUE"""),7406.0) -> 7406 | BA22: =IFERROR(__xludf.DUMMYFUNCTION("""COMPUTED_VALUE"""),7998.4800000000005) -> 7998.48 | BB22: =IFERROR(__xludf.DUMMYFUNCTION("""COMPUTED_VALUE"""),7998.4800000000005) -> 7998.48 | BC22: =IFERROR(__xludf.DUMMYFUNCTION("""COMPUTED_VALUE"""),8903.0) -> 8903 | BD22: =IFERROR(__xludf.DUMMYFUNCTION("""COMPUTED_VALUE"""),5251.0) -> 5251 | BE22: =IFERROR(__xludf.DUMMYFUNCTION("""COMPUTED_VALUE"""),840.16) -> 840.16 | BF22: =IFERROR(__xludf.DUMMYFUNCTION("""COMPUTED_VALUE"""),6091.16) -> 6091.16 | BG22: =IFERROR(__xludf.DUMMYFUNCTION("""COMPUTED_VALUE"""),-0.41019880939009323) -> -0.41019881 | BH22: =IFERROR(__xludf.DUMMYFUNCTION("""COMPUTED_VALUE"""),4988.45) -> 4988.45 | BI22: =IFERROR(__xludf.DUMMYFUNCTION("""COMPUTED_VALUE"""),798.152) -> 798.152 | BJ22: =IFERROR(__xludf.DUMMYFUNCTION("""COMPUTED_VALUE"""),5786.602) -> 5786.602 | BK22: =IFERROR(__xludf.DUMMYFUNCTION("""COMPUTED_VALUE"""),4725.900000000001) -> 4725.9 | BL22: =IFERROR(__xludf.DUMMYFUNCTION("""COMPUTED_VALUE"""),756.1440000000001) -> 756.144 | BM22: =IFERROR(__xludf.DUMMYFUNCTION("""COMPUTED_VALUE"""),5482.044000000001) -> 5482.044 | BN22: =IFERROR(__xludf.DUMMYFUNCTION("""COMPUTED_VALUE"""),4463.349999999999) -> 4463.35 | BO22: =IFERROR(__xludf.DUMMYFUNCTION("""COMPUTED_VALUE"""),714.136) -> 714.136 | BP22: =IFERROR(__xludf.DUMMYFUNCTION("""COMPUTED_VALUE"""),5177.485999999999) -> 5177.486 | BQ22: =IFERROR(__xludf.DUMMYFUNCTION("""COMPUTED_VALUE"""),4358.33) -> 4358.33 | BR22: =IFERROR(__xludf.DUMMYFUNCTION("""COMPUTED_VALUE"""),697.3328) -> 697.3328 | BS22: =IFERROR(__xludf.DUMMYFUNCTION("""COMPUTED_VALUE"""),5055.6628) -> 5055.6628 | BT22: =IFERROR(__xludf.DUMMYFUNCTION("""COMPUTED_VALUE"""),4200.8) -> 4200.8 | BU22: =IFERROR(__xludf.DUMMYFUNCTION("""COMPUTED_VALUE"""),672.128) -> 672.128 | BV22: =IFERROR(__xludf.DUMMYFUNCTION("""COMPUTED_VALUE"""),4872.928) -> 4872.928
B23: 0 | C23: C | D23: RL04 | E23: KG | F23: REF | G23: ALAMBRE PARA CABEZAL RESTAURANTERO DE RODILLOS DE 4" | H23: ALAMBRE P/CABEZAL REST RODILLOS 4 | I23: =IF(D23="","",LEN(H23)) -> 33 | N23: 1080 | O23: 1166 | P23: 1259.28 | Q23: 1259.28 | R23: 1322 | S23: 1388 | T23: =S23*0.16 -> 222.08 | U23: =S23+T23 -> 1610.08 | V23: =(S23-R23)/R23 -> 0.049924357 | W23: =(IF(B23="",(S23*(1-$W$1)),(IF(B23=1,(S23*(1-$W$1)),(IF(B23=2,(S23*(1-$W$1)),(IF(B23=3,(S23*(1-$W$1)),(IF(B23=4,(S23*(1)))))))))))) -> FALSE | X23: =W23*0.16 -> 0 | Y23: =W23+X23 -> 0 | Z23: =(IF(B23="",(S23*(1-$Z$1)),(IF(B23=1,(S23*(1-$Z$1)),(IF(B23=2,(S23*(1-$Z$1)),(IF(B23=3,(S23*(1-$Z$1)),(IF(B23=4,(S23*(1)))))))))))) -> FALSE | AA23: =Z23*0.16 -> 0 | AB23: =Z23+AA23 -> 0 | AC23: =(IF(B23="",(S23*(1-$AC$1)),(IF(B23=1,(S23*(1-$AC$1)),(IF(B23=2,(S23*(1-0.15)),(IF(B23=3,(S23*(1-0.1)),(IF(B23=4,(S23*(1)))))))))))) -> FALSE | AD23: =AC23*0.16 -> 0 | AE23: =AC23+AD23 -> 0 | AF23: =(IF(B23="",(S23*(1-$AF$1)),(IF(B23=1,(S23*(1-$AF$1)),(IF(B23=2,(S23*(1-0.15)),(IF(B23=3,(S23*(1-0.1)),(IF(B23=4,(S23*(1)))))))))))) -> FALSE | AG23: =AF23*0.16 -> 0 | AH23: =AF23+AG23 -> 0 | AI23: =(IF(B23="",(S23*(1-$AI$1)),(IF(B23=1,(S23*(1-$AI$1)),(IF(B23=2,(S23*(1-0.15)),(IF(B23=3,(S23*(1-0.1)),(IF(B23=4,(S23*(1)))))))))))) -> FALSE | AJ23: =AI23*0.16 -> 0 | AK23: =AI23+AJ23 -> 0 | AL23: =IFERROR(__xludf.DUMMYFUNCTION("""COMPUTED_VALUE"""),1.0) -> 1 | AN23: =IFERROR(__xludf.DUMMYFUNCTION("""COMPUTED_VALUE""")," C") -> C | AO23: =IFERROR(__xludf.DUMMYFUNCTION("""COMPUTED_VALUE""")," AR05") -> AR05 | AP23: =IFERROR(__xludf.DUMMYFUNCTION("""COMPUTED_VALUE""")," PZA") -> PZA | AQ23: =IFERROR(__xludf.DUMMYFUNCTION("""COMPUTED_VALUE""")," REF") -> REF | AR23: =IFERROR(__xludf.DUMMYFUNCTION("""COMPUTED_VALUE""")," ARRANCADOR PARA MOTOR DE 10 HP TRIFÁSICO 220V CODIGO 10072610 22~32 AMP") -> ARRANCADOR PARA MOTOR DE 10 HP TRIFÁSICO 220V CODIGO 10072610 22~32 AMP | AS23: =IFERROR(__xludf.DUMMYFUNCTION("""COMPUTED_VALUE""")," ARRANCADOR 10HP TRI 220V 10072610 22-32A") -> ARRANCADOR 10HP TRI 220V 10072610 22-32A | AT23: =IFERROR(__xludf.DUMMYFUNCTION("""COMPUTED_VALUE"""),40.0) -> 40 | AY23: =IFERROR(__xludf.DUMMYFUNCTION("""COMPUTED_VALUE"""),5184.0) -> 5184 | AZ23: =IFERROR(__xludf.DUMMYFUNCTION("""COMPUTED_VALUE"""),2686.0) -> 2686 | BA23: =IFERROR(__xludf.DUMMYFUNCTION("""COMPUTED_VALUE"""),2900.88) -> 2900.88 | BB23: =IFERROR(__xludf.DUMMYFUNCTION("""COMPUTED_VALUE"""),2900.88) -> 2900.88 | BC23: =IFERROR(__xludf.DUMMYFUNCTION("""COMPUTED_VALUE"""),3229.0) -> 3229 | BD23: =IFERROR(__xludf.DUMMYFUNCTION("""COMPUTED_VALUE"""),3390.0) -> 3390 | BE23: =IFERROR(__xludf.DUMMYFUNCTION("""COMPUTED_VALUE"""),542.4) -> 542.4 | BF23: =IFERROR(__xludf.DUMMYFUNCTION("""COMPUTED_VALUE"""),3932.4) -> 3932.4 | BG23: =IFERROR(__xludf.DUMMYFUNCTION("""COMPUTED_VALUE"""),0.049860637968411274) -> 0.049860638 | BH23: =IFERROR(__xludf.DUMMYFUNCTION("""COMPUTED_VALUE"""),3220.5) -> 3220.5 | BI23: =IFERROR(__xludf.DUMMYFUNCTION("""COMPUTED_VALUE"""),515.28) -> 515.28 | BJ23: =IFERROR(__xludf.DUMMYFUNCTION("""COMPUTED_VALUE"""),3735.7799999999997) -> 3735.78 | BK23: =IFERROR(__xludf.DUMMYFUNCTION("""COMPUTED_VALUE"""),3051.0) -> 3051 | BL23: =IFERROR(__xludf.DUMMYFUNCTION("""COMPUTED_VALUE"""),488.16) -> 488.16 | BM23: =IFERROR(__xludf.DUMMYFUNCTION("""COMPUTED_VALUE"""),3539.16) -> 3539.16 | BN23: =IFERROR(__xludf.DUMMYFUNCTION("""COMPUTED_VALUE"""),2881.5) -> 2881.5 | BO23: =IFERROR(__xludf.DUMMYFUNCTION("""COMPUTED_VALUE"""),461.04) -> 461.04 | BP23: =IFERROR(__xludf.DUMMYFUNCTION("""COMPUTED_VALUE"""),3342.54) -> 3342.54 | BQ23: =IFERROR(__xludf.DUMMYFUNCTION("""COMPUTED_VALUE"""),2813.7) -> 2813.7 | BR23: =IFERROR(__xludf.DUMMYFUNCTION("""COMPUTED_VALUE"""),450.192) -> 450.192 | BS23: =IFERROR(__xludf.DUMMYFUNCTION("""COMPUTED_VALUE"""),3263.892) -> 3263.892 | BT23: =IFERROR(__xludf.DUMMYFUNCTION("""COMPUTED_VALUE"""),2712.0) -> 2712 | BU23: =IFERROR(__xludf.DUMMYFUNCTION("""COMPUTED_VALUE"""),433.92) -> 433.92 | BV23: =IFERROR(__xludf.DUMMYFUNCTION("""COMPUTED_VALUE"""),3145.92) -> 3145.92
B24: 3 | C24: E | D24: MG72 | E24: PZA | F24: TGA | G24: ALIMENTADOR PARA MÁQUINA CUADRUPLE DE RODILLOS CON MOTOR DE 2 HP Y VARIADOR DE VELOCIDAD, 2 PALETAS Y 1 SINFIN EN INOX 304-L | I24: =IF(D24="","",LEN(H24)) -> 0 | O24: 118305 | P24: 127769.4 | Q24: 127769.4 | R24: 140865 | S24: 147908 | T24: =S24*0.16 -> 23665.28 | U24: =S24+T24 -> 171573.28 | V24: =(S24-R24)/R24 -> 0.049998225 | W24: =(IF(B24="",(S24*(1-$W$1)),(IF(B24=1,(S24*(1-$W$1)),(IF(B24=2,(S24*(1-$W$1)),(IF(B24=3,(S24*(1-$W$1)),(IF(B24=4,(S24*(1)))))))))))) -> 140512.6 | X24: =W24*0.16 -> 22482.016 | Y24: =W24+X24 -> 162994.62 | Z24: =(IF(B24="",(S24*(1-$Z$1)),(IF(B24=1,(S24*(1-$Z$1)),(IF(B24=2,(S24*(1-$Z$1)),(IF(B24=3,(S24*(1-$Z$1)),(IF(B24=4,(S24*(1)))))))))))) -> 133117.2 | AA24: =Z24*0.16 -> 21298.752 | AB24: =Z24+AA24 -> 154415.95 | AC24: =(IF(B24="",(S24*(1-$AC$1)),(IF(B24=1,(S24*(1-$AC$1)),(IF(B24=2,(S24*(1-0.15)),(IF(B24=3,(S24*(1-0.1)),(IF(B24=4,(S24*(1)))))))))))) -> 133117.2 | AD24: =AC24*0.16 -> 21298.752 | AE24: =AC24+AD24 -> 154415.95 | AF24: =(IF(B24="",(S24*(1-$AF$1)),(IF(B24=1,(S24*(1-$AF$1)),(IF(B24=2,(S24*(1-0.15)),(IF(B24=3,(S24*(1-0.1)),(IF(B24=4,(S24*(1)))))))))))) -> 133117.2 | AG24: =AF24*0.16 -> 21298.752 | AH24: =AF24+AG24 -> 154415.95 | AI24: =(IF(B24="",(S24*(1-$AI$1)),(IF(B24=1,(S24*(1-$AI$1)),(IF(B24=2,(S24*(1-0.15)),(IF(B24=3,(S24*(1-0.1)),(IF(B24=4,(S24*(1)))))))))))) -> 133117.2 | AJ24: =AI24*0.16 -> 21298.752 | AK24: =AI24+AJ24 -> 154415.95 | AL24: =IFERROR(__xludf.DUMMYFUNCTION("""COMPUTED_VALUE"""),1.0) -> 1 | AN24: =IFERROR(__xludf.DUMMYFUNCTION("""COMPUTED_VALUE""")," C") -> C | AO24: =IFERROR(__xludf.DUMMYFUNCTION("""COMPUTED_VALUE""")," AR06") -> AR06 | AP24: =IFERROR(__xludf.DUMMYFUNCTION("""COMPUTED_VALUE""")," PZA") -> PZA | AQ24: =IFERROR(__xludf.DUMMYFUNCTION("""COMPUTED_VALUE""")," REF") -> REF | AR24: =IFERROR(__xludf.DUMMYFUNCTION("""COMPUTED_VALUE""")," ARRANCADOR PARA MOTOR DE 15 HP TRIFÁSICO 220V CODIGO 10046372 32~50 AMP") -> ARRANCADOR PARA MOTOR DE 15 HP TRIFÁSICO 220V CODIGO 10046372 32~50 AMP | AS24: =IFERROR(__xludf.DUMMYFUNCTION("""COMPUTED_VALUE""")," ARRANCADOR 15HP TRI 220V 10046372 32-50A") -> ARRANCADOR 15HP TRI 220V 10046372 32-50A | AT24: =IFERROR(__xludf.DUMMYFUNCTION("""COMPUTED_VALUE"""),40.0) -> 40 | AY24: =IFERROR(__xludf.DUMMYFUNCTION("""COMPUTED_VALUE"""),6858.0) -> 6858 | AZ24: =IFERROR(__xludf.DUMMYFUNCTION("""COMPUTED_VALUE"""),3553.0) -> 3553 | BA24: =IFERROR(__xludf.DUMMYFUNCTION("""COMPUTED_VALUE"""),3837.2400000000002) -> 3837.24 | BB24: =IFERROR(__xludf.DUMMYFUNCTION("""COMPUTED_VALUE"""),3837.2400000000002) -> 3837.24 | BC24: =IFERROR(__xludf.DUMMYFUNCTION("""COMPUTED_VALUE"""),4272.0) -> 4272 | BD24: =IFERROR(__xludf.DUMMYFUNCTION("""COMPUTED_VALUE"""),4486.0) -> 4486 | BE24: =IFERROR(__xludf.DUMMYFUNCTION("""COMPUTED_VALUE"""),717.76) -> 717.76 | BF24: =IFERROR(__xludf.DUMMYFUNCTION("""COMPUTED_VALUE"""),5203.76) -> 5203.76 | BG24: =IFERROR(__xludf.DUMMYFUNCTION("""COMPUTED_VALUE"""),0.050093632958801496) -> 0.050093633 | BH24: =IFERROR(__xludf.DUMMYFUNCTION("""COMPUTED_VALUE"""),4261.7) -> 4261.7 | BI24: =IFERROR(__xludf.DUMMYFUNCTION("""COMPUTED_VALUE"""),681.872) -> 681.872 | BJ24: =IFERROR(__xludf.DUMMYFUNCTION("""COMPUTED_VALUE"""),4943.572) -> 4943.572 | BK24: =IFERROR(__xludf.DUMMYFUNCTION("""COMPUTED_VALUE"""),4037.4) -> 4037.4 | BL24: =IFERROR(__xludf.DUMMYFUNCTION("""COMPUTED_VALUE"""),645.984) -> 645.984 | BM24: =IFERROR(__xludf.DUMMYFUNCTION("""COMPUTED_VALUE"""),4683.384) -> 4683.384 | BN24: =IFERROR(__xludf.DUMMYFUNCTION("""COMPUTED_VALUE"""),3813.1) -> 3813.1 | BO24: =IFERROR(__xludf.DUMMYFUNCTION("""COMPUTED_VALUE"""),610.096) -> 610.096 | BP24: =IFERROR(__xludf.DUMMYFUNCTION("""COMPUTED_VALUE"""),4423.196) -> 4423.196 | BQ24: =IFERROR(__xludf.DUMMYFUNCTION("""COMPUTED_VALUE"""),3723.3799999999997) -> 3723.38 | BR24: =IFERROR(__xludf.DUMMYFUNCTION("""COMPUTED_VALUE"""),595.7407999999999) -> 595.7408 | BS24: =IFERROR(__xludf.DUMMYFUNCTION("""COMPUTED_VALUE"""),4319.1208) -> 4319.1208 | BT24: =IFERROR(__xludf.DUMMYFUNCTION("""COMPUTED_VALUE"""),3588.8) -> 3588.8 | BU24: =IFERROR(__xludf.DUMMYFUNCTION("""COMPUTED_VALUE"""),574.2080000000001) -> 574.208 | BV24: =IFERROR(__xludf.DUMMYFUNCTION("""COMPUTED_VALUE"""),4163.008) -> 4163.008
B25: 3 | C25: E | D25: MG29 | E25: PZA | F25: TGA | G25: ALIMENTADOR PARA MÁQUINA TVR TVRM TVRD VW DE RODILLOS CON MOTOR DE 1 HP Y VARIADOR DE VELOCIDAD, 2 PALETAS Y 1 SINFIN EN INOX 304-L | H25: ALIMENTADOR P/MAQ ROD SEN/DUP 1HP VARIAD | I25: =IF(D25="","",LEN(H25)) -> 40 | O25: 48290 | P25: 52153.2 | Q25: 52153.2 | R25: 57500 | S25: 60375 | T25: =S25*0.16 -> 9660 | U25: =S25+T25 -> 70035 | V25: =(S25-R25)/R25 -> 0.05 | W25: =(IF(B25="",(S25*(1-$W$1)),(IF(B25=1,(S25*(1-$W$1)),(IF(B25=2,(S25*(1-$W$1)),(IF(B25=3,(S25*(1-$W$1)),(IF(B25=4,(S25*(1)))))))))))) -> 57356.25 | X25: =W25*0.16 -> 9177 | Y25: =W25+X25 -> 66533.25 | Z25: =(IF(B25="",(S25*(1-$Z$1)),(IF(B25=1,(S25*(1-$Z$1)),(IF(B25=2,(S25*(1-$Z$1)),(IF(B25=3,(S25*(1-$Z$1)),(IF(B25=4,(S25*(1)))))))))))) -> 54337.5 | AA25: =Z25*0.16 -> 8694 | AB25: =Z25+AA25 -> 63031.5 | AC25: =(IF(B25="",(S25*(1-$AC$1)),(IF(B25=1,(S25*(1-$AC$1)),(IF(B25=2,(S25*(1-0.15)),(IF(B25=3,(S25*(1-0.1)),(IF(B25=4,(S25*(1)))))))))))) -> 54337.5 | AD25: =AC25*0.16 -> 8694 | AE25: =AC25+AD25 -> 63031.5 | AF25: =(IF(B25="",(S25*(1-$AF$1)),(IF(B25=1,(S25*(1-$AF$1)),(IF(B25=2,(S25*(1-0.15)),(IF(B25=3,(S25*(1-0.1)),(IF(B25=4,(S25*(1)))))))))))) -> 54337.5 | AG25: =AF25*0.16 -> 8694 | AH25: =AF25+AG25 -> 63031.5 | AI25: =(IF(B25="",(S25*(1-$AI$1)),(IF(B25=1,(S25*(1-$AI$1)),(IF(B25=2,(S25*(1-0.15)),(IF(B25=3,(S25*(1-0.1)),(IF(B25=4,(S25*(1)))))))))))) -> 54337.5 | AJ25: =AI25*0.16 -> 8694 | AK25: =AI25+AJ25 -> 63031.5 | AL25: =IFERROR(__xludf.DUMMYFUNCTION("""COMPUTED_VALUE"""),1.0) -> 1 | AN25: =IFERROR(__xludf.DUMMYFUNCTION("""COMPUTED_VALUE""")," C") -> C | AO25: =IFERROR(__xludf.DUMMYFUNCTION("""COMPUTED_VALUE""")," AR14") -> AR14 | AP25: =IFERROR(__xludf.DUMMYFUNCTION("""COMPUTED_VALUE""")," PZA") -> PZA | AQ25: =IFERROR(__xludf.DUMMYFUNCTION("""COMPUTED_VALUE""")," REF") -> REF | AR25: =IFERROR(__xludf.DUMMYFUNCTION("""COMPUTED_VALUE""")," ARRANCADOR PARA MOTOR DE 2 HP MONOFÁSICO 127V CODIGO 10410257 8~12.5 AMP") -> ARRANCADOR PARA MOTOR DE 2 HP MONOFÁSICO 127V CODIGO 10410257 8~12.5 AMP | AS25: =IFERROR(__xludf.DUMMYFUNCTION("""COMPUTED_VALUE""")," ARRANCADOR 2HP MON 127V 10410257 8-12.5A") -> ARRANCADOR 2HP MON 127V 10410257 8-12.5A | AT25: =IFERROR(__xludf.DUMMYFUNCTION("""COMPUTED_VALUE"""),40.0) -> 40 | AY25: =IFERROR(__xludf.DUMMYFUNCTION("""COMPUTED_VALUE"""),3341.0) -> 3341 | AZ25: =IFERROR(__xludf.DUMMYFUNCTION("""COMPUTED_VALUE"""),3608.0) -> 3608 | BA25: =IFERROR(__xludf.DUMMYFUNCTION("""COMPUTED_VALUE"""),3896.6400000000003) -> 3896.64 | BB25: =IFERROR(__xludf.DUMMYFUNCTION("""COMPUTED_VALUE"""),3896.6400000000003) -> 3896.64 | BC25: =IFERROR(__xludf.DUMMYFUNCTION("""COMPUTED_VALUE"""),4092.0) -> 4092 | BD25: =IFERROR(__xludf.DUMMYFUNCTION("""COMPUTED_VALUE"""),2443.0) -> 2443 | BE25: =IFERROR(__xludf.DUMMYFUNCTION("""COMPUTED_VALUE"""),390.88) -> 390.88 | BF25: =IFERROR(__xludf.DUMMYFUNCTION("""COMPUTED_VALUE"""),2833.88) -> 2833.88 | BG25: =IFERROR(__xludf.DUMMYFUNCTION("""COMPUTED_VALUE"""),-0.40298142717497554) -> -0.40298143 | BH25: =IFERROR(__xludf.DUMMYFUNCTION("""COMPUTED_VALUE"""),2320.85) -> 2320.85 | BI25: =IFERROR(__xludf.DUMMYFUNCTION("""COMPUTED_VALUE"""),371.336) -> 371.336 | BJ25: =IFERROR(__xludf.DUMMYFUNCTION("""COMPUTED_VALUE"""),2692.1859999999997) -> 2692.186 | BK25: =IFERROR(__xludf.DUMMYFUNCTION("""COMPUTED_VALUE"""),2198.7000000000003) -> 2198.7 | BL25: =IFERROR(__xludf.DUMMYFUNCTION("""COMPUTED_VALUE"""),351.79200000000003) -> 351.792 | BM25: =IFERROR(__xludf.DUMMYFUNCTION("""COMPUTED_VALUE"""),2550.492) -> 2550.492 | BN25: =IFERROR(__xludf.DUMMYFUNCTION("""COMPUTED_VALUE"""),2076.5499999999997) -> 2076.55 | BO25: =IFERROR(__xludf.DUMMYFUNCTION("""COMPUTED_VALUE"""),332.248) -> 332.248 | BP25: =IFERROR(__xludf.DUMMYFUNCTION("""COMPUTED_VALUE"""),2408.798) -> 2408.798 | BQ25: =IFERROR(__xludf.DUMMYFUNCTION("""COMPUTED_VALUE"""),2027.6899999999998) -> 2027.69 | BR25: =IFERROR(__xludf.DUMMYFUNCTION("""COMPUTED_VALUE"""),324.43039999999996) -> 324.4304 | BS25: =IFERROR(__xludf.DUMMYFUNCTION("""COMPUTED_VALUE"""),2352.1204) -> 2352.1204 | BT25: =IFERROR(__xludf.DUMMYFUNCTION("""COMPUTED_VALUE"""),1954.4) -> 1954.4 | BU25: =IFERROR(__xludf.DUMMYFUNCTION("""COMPUTED_VALUE"""),312.704) -> 312.704 | BV25: =IFERROR(__xludf.DUMMYFUNCTION("""COMPUTED_VALUE"""),2267.1040000000003) -> 2267.104
B26: 3 | C26: E | D26: MG31 | E26: PZA | F26: TGA | G26: ALIMENTADOR PARA MÁQUINA TVRT Y VW-150 DE RODILLOS CON MOTOR DE 2 HP Y VARIADOR DE VELOCIDAD, 2 PALETAS Y 1 SINFIN EN INOX 304-L | H26: ALIMENTADOR P/MAQ ROD TRIPLES 1HP VARIAD | I26: =IF(D26="","",LEN(H26)) -> 40 | O26: 63452 | P26: 68528.16 | Q26: 68528.16 | R26: 75552 | S26: 79330 | T26: =S26*0.16 -> 12692.8 | U26: =S26+T26 -> 92022.8 | V26: =(S26-R26)/R26 -> 0.050005294 | W26: =(IF(B26="",(S26*(1-$W$1)),(IF(B26=1,(S26*(1-$W$1)),(IF(B26=2,(S26*(1-$W$1)),(IF(B26=3,(S26*(1-$W$1)),(IF(B26=4,(S26*(1)))))))))))) -> 75363.5 | X26: =W26*0.16 -> 12058.16 | Y26: =W26+X26 -> 87421.66 | Z26: =(IF(B26="",(S26*(1-$Z$1)),(IF(B26=1,(S26*(1-$Z$1)),(IF(B26=2,(S26*(1-$Z$1)),(IF(B26=3,(S26*(1-$Z$1)),(IF(B26=4,(S26*(1)))))))))))) -> 71397 | AA26: =Z26*0.16 -> 11423.52 | AB26: =Z26+AA26 -> 82820.52 | AC26: =(IF(B26="",(S26*(1-$AC$1)),(IF(B26=1,(S26*(1-$AC$1)),(IF(B26=2,(S26*(1-0.15)),(IF(B26=3,(S26*(1-0.1)),(IF(B26=4,(S26*(1)))))))))))) -> 71397 | AD26: =AC26*0.16 -> 11423.52 | AE26: =AC26+AD26 -> 82820.52 | AF26: =(IF(B26="",(S26*(1-$AF$1)),(IF(B26=1,(S26*(1-$AF$1)),(IF(B26=2,(S26*(1-0.15)),(IF(B26=3,(S26*(1-0.1)),(IF(B26=4,(S26*(1)))))))))))) -> 71397 | AG26: =AF26*0.16 -> 11423.52 | AH26: =AF26+AG26 -> 82820.52 | AI26: =(IF(B26="",(S26*(1-$AI$1)),(IF(B26=1,(S26*(1-$AI$1)),(IF(B26=2,(S26*(1-0.15)),(IF(B26=3,(S26*(1-0.1)),(IF(B26=4,(S26*(1)))))))))))) -> 71397 | AJ26: =AI26*0.16 -> 11423.52 | AK26: =AI26+AJ26 -> 82820.52 | AL26: =IFERROR(__xludf.DUMMYFUNCTION("""COMPUTED_VALUE"""),1.0) -> 1 | AN26: =IFERROR(__xludf.DUMMYFUNCTION("""COMPUTED_VALUE""")," C") -> C | AO26: =IFERROR(__xludf.DUMMYFUNCTION("""COMPUTED_VALUE""")," AR09") -> AR09 | AP26: =IFERROR(__xludf.DUMMYFUNCTION("""COMPUTED_VALUE""")," PZA") -> PZA | AQ26: =IFERROR(__xludf.DUMMYFUNCTION("""COMPUTED_VALUE""")," REF") -> REF | AR26: =IFERROR(__xludf.DUMMYFUNCTION("""COMPUTED_VALUE""")," ARRANCADOR PARA MOTOR DE 2 HP MONOFÁSICO 220V CODIGO 10410257 8~12.5 AMP") -> ARRANCADOR PARA MOTOR DE 2 HP MONOFÁSICO 220V CODIGO 10410257 8~12.5 AMP | AS26: =IFERROR(__xludf.DUMMYFUNCTION("""COMPUTED_VALUE""")," ARRANCADOR 2HP MON 220V 10410257 8-12.5A") -> ARRANCADOR 2HP MON 220V 10410257 8-12.5A | AT26: =IFERROR(__xludf.DUMMYFUNCTION("""COMPUTED_VALUE"""),40.0) -> 40 | AY26: =IFERROR(__xludf.DUMMYFUNCTION("""COMPUTED_VALUE"""),3341.0) -> 3341 | AZ26: =IFERROR(__xludf.DUMMYFUNCTION("""COMPUTED_VALUE"""),3608.0) -> 3608 | BA26: =IFERROR(__xludf.DUMMYFUNCTION("""COMPUTED_VALUE"""),3896.6400000000003) -> 3896.64 | BB26: =IFERROR(__xludf.DUMMYFUNCTION("""COMPUTED_VALUE"""),3896.6400000000003) -> 3896.64 | BC26: =IFERROR(__xludf.DUMMYFUNCTION("""COMPUTED_VALUE"""),4338.0) -> 4338 | BD26: =IFERROR(__xludf.DUMMYFUNCTION("""COMPUTED_VALUE"""),2443.0) -> 2443 | BE26: =IFERROR(__xludf.DUMMYFUNCTION("""COMPUTED_VALUE"""),390.88) -> 390.88 | BF26: =IFERROR(__xludf.DUMMYFUNCTION("""COMPUTED_VALUE"""),2833.88) -> 2833.88 | BG26: =IFERROR(__xludf.DUMMYFUNCTION("""COMPUTED_VALUE"""),-0.4368372521899493) -> -0.43683725 | BH26: =IFERROR(__xludf.DUMMYFUNCTION("""COMPUTED_VALUE"""),2320.85) -> 2320.85 | BI26: =IFERROR(__xludf.DUMMYFUNCTION("""COMPUTED_VALUE"""),371.336) -> 371.336 | BJ26: =IFERROR(__xludf.DUMMYFUNCTION("""COMPUTED_VALUE"""),2692.1859999999997) -> 2692.186 | BK26: =IFERROR(__xludf.DUMMYFUNCTION("""COMPUTED_VALUE"""),2198.7000000000003) -> 2198.7 | BL26: =IFERROR(__xludf.DUMMYFUNCTION("""COMPUTED_VALUE"""),351.79200000000003) -> 351.792 | BM26: =IFERROR(__xludf.DUMMYFUNCTION("""COMPUTED_VALUE"""),2550.492) -> 2550.492 | BN26: =IFERROR(__xludf.DUMMYFUNCTION("""COMPUTED_VALUE"""),2076.5499999999997) -> 2076.55 | BO26: =IFERROR(__xludf.DUMMYFUNCTION("""COMPUTED_VALUE"""),332.248) -> 332.248 | BP26: =IFERROR(__xludf.DUMMYFUNCTION("""COMPUTED_VALUE"""),2408.798) -> 2408.798 | BQ26: =IFERROR(__xludf.DUMMYFUNCTION("""COMPUTED_VALUE"""),2027.6899999999998) -> 2027.69 | BR26: =IFERROR(__xludf.DUMMYFUNCTION("""COMPUTED_VALUE"""),324.43039999999996) -> 324.4304 | BS26: =IFERROR(__xludf.DUMMYFUNCTION("""COMPUTED_VALUE"""),2352.1204) -> 2352.1204 | BT26: =IFERROR(__xludf.DUMMYFUNCTION("""COMPUTED_VALUE"""),1954.4) -> 1954.4 | BU26: =IFERROR(__xludf.DUMMYFUNCTION("""COMPUTED_VALUE"""),312.704) -> 312.704 | BV26: =IFERROR(__xludf.DUMMYFUNCTION("""COMPUTED_VALUE"""),2267.1040000000003) -> 2267.104
D27: MG94 | E27: PZA | G27: ALIMENTADOR PARA MAQUINA VW | I27: =IF(D27="","",LEN(H27)) -> 0 | P27: 43134 | Q27: 43134 | R27: 47556 | S27: 49934 | T27: =S27*0.16 -> 7989.44 | U27: =S27+T27 -> 57923.44 | V27: =(S27-R27)/R27 -> 0.050004206 | W27: =(IF(B27="",(S27*(1-$W$1)),(IF(B27=1,(S27*(1-$W$1)),(IF(B27=2,(S27*(1-$W$1)),(IF(B27=3,(S27*(1-$W$1)),(IF(B27=4,(S27*(1)))))))))))) -> 47437.3 | X27: =W27*0.16 -> 7589.968 | Y27: =W27+X27 -> 55027.268 | Z27: =(IF(B27="",(S27*(1-$Z$1)),(IF(B27=1,(S27*(1-$Z$1)),(IF(B27=2,(S27*(1-$Z$1)),(IF(B27=3,(S27*(1-$Z$1)),(IF(B27=4,(S27*(1)))))))))))) -> 44940.6 | AA27: =Z27*0.16 -> 7190.496 | AB27: =Z27+AA27 -> 52131.096 | AC27: =(IF(B27="",(S27*(1-$AC$1)),(IF(B27=1,(S27*(1-$AC$1)),(IF(B27=2,(S27*(1-0.15)),(IF(B27=3,(S27*(1-0.1)),(IF(B27=4,(S27*(1)))))))))))) -> 42443.9 | AD27: =AC27*0.16 -> 6791.024 | AE27: =AC27+AD27 -> 49234.924 | AF27: =(IF(B27="",(S27*(1-$AF$1)),(IF(B27=1,(S27*(1-$AF$1)),(IF(B27=2,(S27*(1-0.15)),(IF(B27=3,(S27*(1-0.1)),(IF(B27=4,(S27*(1)))))))))))) -> 41445.22 | AG27: =AF27*0.16 -> 6631.2352 | AH27: =AF27+AG27 -> 48076.455 | AI27: =(IF(B27="",(S27*(1-$AI$1)),(IF(B27=1,(S27*(1-$AI$1)),(IF(B27=2,(S27*(1-0.15)),(IF(B27=3,(S27*(1-0.1)),(IF(B27=4,(S27*(1)))))))))))) -> 39947.2 | AJ27: =AI27*0.16 -> 6391.552 | AK27: =AI27+AJ27 -> 46338.752 | AL27: =IFERROR(__xludf.DUMMYFUNCTION("""COMPUTED_VALUE"""),1.0) -> 1 | AN27: =IFERROR(__xludf.DUMMYFUNCTION("""COMPUTED_VALUE""")," C") -> C | AO27: =IFERROR(__xludf.DUMMYFUNCTION("""COMPUTED_VALUE""")," AR01") -> AR01 | AP27: =IFERROR(__xludf.DUMMYFUNCTION("""COMPUTED_VALUE""")," PZA") -> PZA | AQ27: =IFERROR(__xludf.DUMMYFUNCTION("""COMPUTED_VALUE""")," REF") -> REF | AR27: =IFERROR(__xludf.DUMMYFUNCTION("""COMPUTED_VALUE""")," ARRANCADOR PARA MOTOR DE 2 HP TRIFÁSICO 220V CODIGO 10046368 5~8 AMP") -> ARRANCADOR PARA MOTOR DE 2 HP TRIFÁSICO 220V CODIGO 10046368 5~8 AMP | AS27: =IFERROR(__xludf.DUMMYFUNCTION("""COMPUTED_VALUE""")," ARRANCADOR 2HP TRI 220V 10046368 5-8A") -> ARRANCADOR 2HP TRI 220V 10046368 5-8A | AT27: =IFERROR(__xludf.DUMMYFUNCTION("""COMPUTED_VALUE"""),37.0) -> 37 | AY27: =IFERROR(__xludf.DUMMYFUNCTION("""COMPUTED_VALUE"""),2400.0) -> 2400 | AZ27: =IFERROR(__xludf.DUMMYFUNCTION("""COMPUTED_VALUE"""),1243.0) -> 1243 | BA27: =IFERROR(__xludf.DUMMYFUNCTION("""COMPUTED_VALUE"""),1342.44) -> 1342.44 | BB27: =IFERROR(__xludf.DUMMYFUNCTION("""COMPUTED_VALUE"""),1342.44) -> 1342.44 | BC27: =IFERROR(__xludf.DUMMYFUNCTION("""COMPUTED_VALUE"""),1411.0) -> 1411 | BD27: =IFERROR(__xludf.DUMMYFUNCTION("""COMPUTED_VALUE"""),1482.0) -> 1482 | BE27: =IFERROR(__xludf.DUMMYFUNCTION("""COMPUTED_VALUE"""),237.12) -> 237.12 | BF27: =IFERROR(__xludf.DUMMYFUNCTION("""COMPUTED_VALUE"""),1719.12) -> 1719.12 | BG27: =IFERROR(__xludf.DUMMYFUNCTION("""COMPUTED_VALUE"""),0.050318922749822824) -> 0.050318923 | BH27: =IFERROR(__xludf.DUMMYFUNCTION("""COMPUTED_VALUE"""),1407.8999999999999) -> 1407.9 | BI27: =IFERROR(__xludf.DUMMYFUNCTION("""COMPUTED_VALUE"""),225.26399999999998) -> 225.264 | BJ27: =IFERROR(__xludf.DUMMYFUNCTION("""COMPUTED_VALUE"""),1633.1639999999998) -> 1633.164 | BK27: =IFERROR(__xludf.DUMMYFUNCTION("""COMPUTED_VALUE"""),1333.8) -> 1333.8 | BL27: =IFERROR(__xludf.DUMMYFUNCTION("""COMPUTED_VALUE"""),213.408) -> 213.408 | BM27: =IFERROR(__xludf.DUMMYFUNCTION("""COMPUTED_VALUE"""),1547.2079999999999) -> 1547.208 | BN27: =IFERROR(__xludf.DUMMYFUNCTION("""COMPUTED_VALUE"""),1259.7) -> 1259.7 | BO27: =IFERROR(__xludf.DUMMYFUNCTION("""COMPUTED_VALUE"""),201.55200000000002) -> 201.552 | BP27: =IFERROR(__xludf.DUMMYFUNCTION("""COMPUTED_VALUE"""),1461.252) -> 1461.252 | BQ27: =IFERROR(__xludf.DUMMYFUNCTION("""COMPUTED_VALUE"""),1230.06) -> 1230.06 | BR27: =IFERROR(__xludf.DUMMYFUNCTION("""COMPUTED_VALUE"""),196.8096) -> 196.8096 | BS27: =IFERROR(__xludf.DUMMYFUNCTION("""COMPUTED_VALUE"""),1426.8696) -> 1426.8696 | BT27: =IFERROR(__xludf.DUMMYFUNCTION("""COMPUTED_VALUE"""),1185.6000000000001) -> 1185.6 | BU27: =IFERROR(__xludf.DUMMYFUNCTION("""COMPUTED_VALUE"""),189.69600000000003) -> 189.696 | BV27: =IFERROR(__xludf.DUMMYFUNCTION("""COMPUTED_VALUE"""),1375.2960000000003) -> 1375.296
D28: MM65 | E28: PZA | G28: AMASADOR Y CUELLO DE GANZO | I28: =IF(D28="","",LEN(H28)) -> 0 | P28: 280426 | Q28: 280426 | R28: 309170 | S28: 324629 | T28: =S28*0.16 -> 51940.64 | U28: =S28+T28 -> 376569.64 | V28: =(S28-R28)/R28 -> 0.050001617 | W28: =(IF(B28="",(S28*(1-$W$1)),(IF(B28=1,(S28*(1-$W$1)),(IF(B28=2,(S28*(1-$W$1)),(IF(B28=3,(S28*(1-$W$1)),(IF(B28=4,(S28*(1)))))))))))) -> 308397.55 | X28: =W28*0.16 -> 49343.608 | Y28: =W28+X28 -> 357741.16 | Z28: =(IF(B28="",(S28*(1-$Z$1)),(IF(B28=1,(S28*(1-$Z$1)),(IF(B28=2,(S28*(1-$Z$1)),(IF(B28=3,(S28*(1-$Z$1)),(IF(B28=4,(S28*(1)))))))))))) -> 292166.1 | AA28: =Z28*0.16 -> 46746.576 | AB28: =Z28+AA28 -> 338912.68 | AC28: =(IF(B28="",(S28*(1-$AC$1)),(IF(B28=1,(S28*(1-$AC$1)),(IF(B28=2,(S28*(1-0.15)),(IF(B28=3,(S28*(1-0.1)),(IF(B28=4,(S28*(1)))))))))))) -> 275934.65 | AD28: =AC28*0.16 -> 44149.544 | AE28: =AC28+AD28 -> 320084.19 | AF28: =(IF(B28="",(S28*(1-$AF$1)),(IF(B28=1,(S28*(1-$AF$1)),(IF(B28=2,(S28*(1-0.15)),(IF(B28=3,(S28*(1-0.1)),(IF(B28=4,(S28*(1)))))))))))) -> 269442.07 | AG28: =AF28*0.16 -> 43110.731 | AH28: =AF28+AG28 -> 312552.8 | AI28: =(IF(B28="",(S28*(1-$AI$1)),(IF(B28=1,(S28*(1-$AI$1)),(IF(B28=2,(S28*(1-0.15)),(IF(B28=3,(S28*(1-0.1)),(IF(B28=4,(S28*(1)))))))))))) -> 259703.2 | AJ28: =AI28*0.16 -> 41552.512 | AK28: =AI28+AJ28 -> 301255.71 | AL28: =IFERROR(__xludf.DUMMYFUNCTION("""COMPUTED_VALUE"""),1.0) -> 1 | AN28: =IFERROR(__xludf.DUMMYFUNCTION("""COMPUTED_VALUE""")," C") -> C | AO28: =IFERROR(__xludf.DUMMYFUNCTION("""COMPUTED_VALUE""")," AR07") -> AR07 | AP28: =IFERROR(__xludf.DUMMYFUNCTION("""COMPUTED_VALUE""")," PZA") -> PZA | AQ28: =IFERROR(__xludf.DUMMYFUNCTION("""COMPUTED_VALUE""")," REF") -> REF | AR28: =IFERROR(__xludf.DUMMYFUNCTION("""COMPUTED_VALUE""")," ARRANCADOR PARA MOTOR DE 20 HP TRIFÁSICO 220V CODIGO 11001941 50~63 AMP") -> ARRANCADOR PARA MOTOR DE 20 HP TRIFÁSICO 220V CODIGO 11001941 50~63 AMP | AS28: =IFERROR(__xludf.DUMMYFUNCTION("""COMPUTED_VALUE""")," ARRANCADOR 20HP TRI 220V 11001941 50-63A") -> ARRANCADOR 20HP TRI 220V 11001941 50-63A | AT28: =IFERROR(__xludf.DUMMYFUNCTION("""COMPUTED_VALUE"""),40.0) -> 40 | AY28: =IFERROR(__xludf.DUMMYFUNCTION("""COMPUTED_VALUE"""),7733.0) -> 7733 | AZ28: =IFERROR(__xludf.DUMMYFUNCTION("""COMPUTED_VALUE"""),4159.0) -> 4159 | BA28: =IFERROR(__xludf.DUMMYFUNCTION("""COMPUTED_VALUE"""),4491.72) -> 4491.72 | BB28: =IFERROR(__xludf.DUMMYFUNCTION("""COMPUTED_VALUE"""),4491.72) -> 4491.72 | BC28: =IFERROR(__xludf.DUMMYFUNCTION("""COMPUTED_VALUE"""),5001.0) -> 5001 | BD28: =IFERROR(__xludf.DUMMYFUNCTION("""COMPUTED_VALUE"""),5251.0) -> 5251 | BE28: =IFERROR(__xludf.DUMMYFUNCTION("""COMPUTED_VALUE"""),840.16) -> 840.16 | BF28: =IFERROR(__xludf.DUMMYFUNCTION("""COMPUTED_VALUE"""),6091.16) -> 6091.16 | BG28: =IFERROR(__xludf.DUMMYFUNCTION("""COMPUTED_VALUE"""),0.04999000199960008) -> 0.049990002 | BH28: =IFERROR(__xludf.DUMMYFUNCTION("""COMPUTED_VALUE"""),4988.45) -> 4988.45 | BI28: =IFERROR(__xludf.DUMMYFUNCTION("""COMPUTED_VALUE"""),798.152) -> 798.152 | BJ28: =IFERROR(__xludf.DUMMYFUNCTION("""COMPUTED_VALUE"""),5786.602) -> 5786.602 | BK28: =IFERROR(__xludf.DUMMYFUNCTION("""COMPUTED_VALUE"""),4725.900000000001) -> 4725.9 | BL28: =IFERROR(__xludf.DUMMYFUNCTION("""COMPUTED_VALUE"""),756.1440000000001) -> 756.144 | BM28: =IFERROR(__xludf.DUMMYFUNCTION("""COMPUTED_VALUE"""),5482.044000000001) -> 5482.044 | BN28: =IFERROR(__xludf.DUMMYFUNCTION("""COMPUTED_VALUE"""),4463.349999999999) -> 4463.35 | BO28: =IFERROR(__xludf.DUMMYFUNCTION("""COMPUTED_VALUE"""),714.136) -> 714.136 | BP28: =IFERROR(__xludf.DUMMYFUNCTION("""COMPUTED_VALUE"""),5177.485999999999) -> 5177.486 | BQ28: =IFERROR(__xludf.DUMMYFUNCTION("""COMPUTED_VALUE"""),4358.33) -> 4358.33 | BR28: =IFERROR(__xludf.DUMMYFUNCTION("""COMPUTED_VALUE"""),697.3328) -> 697.3328 | BS28: =IFERROR(__xludf.DUMMYFUNCTION("""COMPUTED_VALUE"""),5055.6628) -> 5055.6628 | BT28: =IFERROR(__xludf.DUMMYFUNCTION("""COMPUTED_VALUE"""),4200.8) -> 4200.8 | BU28: =IFERROR(__xludf.DUMMYFUNCTION("""COMPUTED_VALUE"""),672.128) -> 672.128 | BV28: =IFERROR(__xludf.DUMMYFUNCTION("""COMPUTED_VALUE"""),4872.928) -> 4872.928
D29: MG23 | E29: PZA | G29: AMASADORA 100KG 304GA CAL16 ESPECIAL | I29: =IF(D29="","",LEN(H29)) -> 0 | P29: 22113 | Q29: 22113 | R29: 24380 | S29: 25599 | T29: =S29*0.16 -> 4095.84 | U29: =S29+T29 -> 29694.84 | V29: =(S29-R29)/R29 -> 0.05 | W29: =(IF(B29="",(S29*(1-$W$1)),(IF(B29=1,(S29*(1-$W$1)),(IF(B29=2,(S29*(1-$W$1)),(IF(B29=3,(S29*(1-$W$1)),(IF(B29=4,(S29*(1)))))))))))) -> 24319.05 | X29: =W29*0.16 -> 3891.048 | Y29: =W29+X29 -> 28210.098 | Z29: =(IF(B29="",(S29*(1-$Z$1)),(IF(B29=1,(S29*(1-$Z$1)),(IF(B29=2,(S29*(1-$Z$1)),(IF(B29=3,(S29*(1-$Z$1)),(IF(B29=4,(S29*(1)))))))))))) -> 23039.1 | AA29: =Z29*0.16 -> 3686.256 | AB29: =Z29+AA29 -> 26725.356 | AC29: =(IF(B29="",(S29*(1-$AC$1)),(IF(B29=1,(S29*(1-$AC$1)),(IF(B29=2,(S29*(1-0.15)),(IF(B29=3,(S29*(1-0.1)),(IF(B29=4,(S29*(1)))))))))))) -> 21759.15 | AD29: =AC29*0.16 -> 3481.464 | AE29: =AC29+AD29 -> 25240.614 | AF29: =(IF(B29="",(S29*(1-$AF$1)),(IF(B29=1,(S29*(1-$AF$1)),(IF(B29=2,(S29*(1-0.15)),(IF(B29=3,(S29*(1-0.1)),(IF(B29=4,(S29*(1)))))))))))) -> 21247.17 | AG29: =AF29*0.16 -> 3399.5472 | AH29: =AF29+AG29 -> 24646.717 | AI29: =(IF(B29="",(S29*(1-$AI$1)),(IF(B29=1,(S29*(1-$AI$1)),(IF(B29=2,(S29*(1-0.15)),(IF(B29=3,(S29*(1-0.1)),(IF(B29=4,(S29*(1)))))))))))) -> 20479.2 | AJ29: =AI29*0.16 -> 3276.672 | AK29: =AI29+AJ29 -> 23755.872 | AL29: =IFERROR(__xludf.DUMMYFUNCTION("""COMPUTED_VALUE"""),1.0) -> 1 | AN29: =IFERROR(__xludf.DUMMYFUNCTION("""COMPUTED_VALUE""")," C") -> C | AO29: =IFERROR(__xludf.DUMMYFUNCTION("""COMPUTED_VALUE""")," AR08") -> AR08 | AP29: =IFERROR(__xludf.DUMMYFUNCTION("""COMPUTED_VALUE""")," PZA") -> PZA | AQ29: =IFERROR(__xludf.DUMMYFUNCTION("""COMPUTED_VALUE""")," REF") -> REF | AR29: =IFERROR(__xludf.DUMMYFUNCTION("""COMPUTED_VALUE""")," ARRANCADOR PARA MOTOR DE 25 HP TRIFÁSICO 220V CODIGO 11001942 57~76 AMP") -> ARRANCADOR PARA MOTOR DE 25 HP TRIFÁSICO 220V CODIGO 11001942 57~76 AMP | AS29: =IFERROR(__xludf.DUMMYFUNCTION("""COMPUTED_VALUE""")," ARRANCADOR 25HP TRI 220V 11001942 57-76A") -> ARRANCADOR 25HP TRI 220V 11001942 57-76A | AT29: =IFERROR(__xludf.DUMMYFUNCTION("""COMPUTED_VALUE"""),40.0) -> 40 | AY29: =IFERROR(__xludf.DUMMYFUNCTION("""COMPUTED_VALUE"""),10642.0) -> 10642 | AZ29: =IFERROR(__xludf.DUMMYFUNCTION("""COMPUTED_VALUE"""),6209.0) -> 6209 | BA29: =IFERROR(__xludf.DUMMYFUNCTION("""COMPUTED_VALUE"""),6705.72) -> 6705.72 | BB29: =IFERROR(__xludf.DUMMYFUNCTION("""COMPUTED_VALUE"""),6705.72) -> 6705.72 | BC29: =IFERROR(__xludf.DUMMYFUNCTION("""COMPUTED_VALUE"""),7465.0) -> 7465 | BD29: =IFERROR(__xludf.DUMMYFUNCTION("""COMPUTED_VALUE"""),7838.0) -> 7838 | BE29: =IFERROR(__xludf.DUMMYFUNCTION("""COMPUTED_VALUE"""),1254.08) -> 1254.08 | BF29: =IFERROR(__xludf.DUMMYFUNCTION("""COMPUTED_VALUE"""),9092.08) -> 9092.08 | BG29: =IFERROR(__xludf.DUMMYFUNCTION("""COMPUTED_VALUE"""),0.04996651038178165) -> 0.04996651 | BH29: =IFERROR(__xludf.DUMMYFUNCTION("""COMPUTED_VALUE"""),7446.099999999999) -> 7446.1 | BI29: =IFERROR(__xludf.DUMMYFUNCTION("""COMPUTED_VALUE"""),1191.376) -> 1191.376 | BJ29: =IFERROR(__xludf.DUMMYFUNCTION("""COMPUTED_VALUE"""),8637.475999999999) -> 8637.476 | BK29: =IFERROR(__xludf.DUMMYFUNCTION("""COMPUTED_VALUE"""),7054.2) -> 7054.2 | BL29: =IFERROR(__xludf.DUMMYFUNCTION("""COMPUTED_VALUE"""),1128.672) -> 1128.672 | BM29: =IFERROR(__xludf.DUMMYFUNCTION("""COMPUTED_VALUE"""),8182.871999999999) -> 8182.872 | BN29: =IFERROR(__xludf.DUMMYFUNCTION("""COMPUTED_VALUE"""),6662.3) -> 6662.3 | BO29: =IFERROR(__xludf.DUMMYFUNCTION("""COMPUTED_VALUE"""),1065.968) -> 1065.968 | BP29: =IFERROR(__xludf.DUMMYFUNCTION("""COMPUTED_VALUE"""),7728.268) -> 7728.268 | BQ29: =IFERROR(__xludf.DUMMYFUNCTION("""COMPUTED_VALUE"""),6505.54) -> 6505.54 | BR29: =IFERROR(__xludf.DUMMYFUNCTION("""COMPUTED_VALUE"""),1040.8864) -> 1040.8864 | BS29: =IFERROR(__xludf.DUMMYFUNCTION("""COMPUTED_VALUE"""),7546.4264) -> 7546.4264 | BT29: =IFERROR(__xludf.DUMMYFUNCTION("""COMPUTED_VALUE"""),6270.400000000001) -> 6270.4 | BU29: =IFERROR(__xludf.DUMMYFUNCTION("""COMPUTED_VALUE"""),1003.2640000000001) -> 1003.264 | BV29: =IFERROR(__xludf.DUMMYFUNCTION("""COMPUTED_VALUE"""),7273.664000000001) -> 7273.664
D30: MG83 | E30: PZA | G30: AMASADORA 100KG AI 304 GA S/ESQUINAS ESP | I30: =IF(D30="","",LEN(H30)) -> 0 | P30: 62257 | Q30: 62257 | R30: 68639 | S30: 72071 | T30: =S30*0.16 -> 11531.36 | U30: =S30+T30 -> 83602.36 | V30: =(S30-R30)/R30 -> 0.050000728 | W30: =(IF(B30="",(S30*(1-$W$1)),(IF(B30=1,(S30*(1-$W$1)),(IF(B30=2,(S30*(1-$W$1)),(IF(B30=3,(S30*(1-$W$1)),(IF(B30=4,(S30*(1)))))))))))) -> 68467.45 | X30: =W30*0.16 -> 10954.792 | Y30: =W30+X30 -> 79422.242 | Z30: =(IF(B30="",(S30*(1-$Z$1)),(IF(B30=1,(S30*(1-$Z$1)),(IF(B30=2,(S30*(1-$Z$1)),(IF(B30=3,(S30*(1-$Z$1)),(IF(B30=4,(S30*(1)))))))))))) -> 64863.9 | AA30: =Z30*0.16 -> 10378.224 | AB30: =Z30+AA30 -> 75242.124 | AC30: =(IF(B30="",(S30*(1-$AC$1)),(IF(B30=1,(S30*(1-$AC$1)),(IF(B30=2,(S30*(1-0.15)),(IF(B30=3,(S30*(1-0.1)),(IF(B30=4,(S30*(1)))))))))))) -> 61260.35 | AD30: =AC30*0.16 -> 9801.656 | AE30: =AC30+AD30 -> 71062.006 | AF30: =(IF(B30="",(S30*(1-$AF$1)),(IF(B30=1,(S30*(1-$AF$1)),(IF(B30=2,(S30*(1-0.15)),(IF(B30=3,(S30*(1-0.1)),(IF(B30=4,(S30*(1)))))))))))) -> 59818.93 | AG30: =AF30*0.16 -> 9571.0288 | AH30: =AF30+AG30 -> 69389.959 | AI30: =(IF(B30="",(S30*(1-$AI$1)),(IF(B30=1,(S30*(1-$AI$1)),(IF(B30=2,(S30*(1-0.15)),(IF(B30=3,(S30*(1-0.1)),(IF(B30=4,(S30*(1)))))))))))) -> 57656.8 | AJ30: =AI30*0.16 -> 9225.088 | AK30: =AI30+AJ30 -> 66881.888 | AL30: =IFERROR(__xludf.DUMMYFUNCTION("""COMPUTED_VALUE"""),1.0) -> 1 | AN30: =IFERROR(__xludf.DUMMYFUNCTION("""COMPUTED_VALUE""")," C") -> C | AO30: =IFERROR(__xludf.DUMMYFUNCTION("""COMPUTED_VALUE""")," AR15") -> AR15 | AP30: =IFERROR(__xludf.DUMMYFUNCTION("""COMPUTED_VALUE""")," PZA") -> PZA | AQ30: =IFERROR(__xludf.DUMMYFUNCTION("""COMPUTED_VALUE""")," REF") -> REF | AR30: =IFERROR(__xludf.DUMMYFUNCTION("""COMPUTED_VALUE""")," ARRANCADOR PARA MOTOR DE 3 HP MONOFÁSICO 127V CODIGO 10046370 11~17 AMP") -> ARRANCADOR PARA MOTOR DE 3 HP MONOFÁSICO 127V CODIGO 10046370 11~17 AMP | AS30: =IFERROR(__xludf.DUMMYFUNCTION("""COMPUTED_VALUE""")," ARRANCADOR 3HP MON 127V 10046370 11-17A") -> ARRANCADOR 3HP MON 127V 10046370 11-17A | AT30: =IFERROR(__xludf.DUMMYFUNCTION("""COMPUTED_VALUE"""),39.0) -> 39 | AY30: =IFERROR(__xludf.DUMMYFUNCTION("""COMPUTED_VALUE"""),3512.0) -> 3512 | AZ30: =IFERROR(__xludf.DUMMYFUNCTION("""COMPUTED_VALUE"""),3792.0) -> 3792 | BA30: =IFERROR(__xludf.DUMMYFUNCTION("""COMPUTED_VALUE"""),4095.36) -> 4095.36 | BB30: =IFERROR(__xludf.DUMMYFUNCTION("""COMPUTED_VALUE"""),4095.36) -> 4095.36 | BC30: =IFERROR(__xludf.DUMMYFUNCTION("""COMPUTED_VALUE"""),4560.0) -> 4560 | BD30: =IFERROR(__xludf.DUMMYFUNCTION("""COMPUTED_VALUE"""),4788.0) -> 4788 | BE30: =IFERROR(__xludf.DUMMYFUNCTION("""COMPUTED_VALUE"""),766.08) -> 766.08 | BF30: =IFERROR(__xludf.DUMMYFUNCTION("""COMPUTED_VALUE"""),5554.08) -> 5554.08 | BG30: =IFERROR(__xludf.DUMMYFUNCTION("""COMPUTED_VALUE"""),0.05) -> 0.05 | BH30: =IFERROR(__xludf.DUMMYFUNCTION("""COMPUTED_VALUE"""),4548.599999999999) -> 4548.6 | BI30: =IFERROR(__xludf.DUMMYFUNCTION("""COMPUTED_VALUE"""),727.776) -> 727.776 | BJ30: =IFERROR(__xludf.DUMMYFUNCTION("""COMPUTED_VALUE"""),5276.375999999999) -> 5276.376 | BK30: =IFERROR(__xludf.DUMMYFUNCTION("""COMPUTED_VALUE"""),4309.2) -> 4309.2 | BL30: =IFERROR(__xludf.DUMMYFUNCTION("""COMPUTED_VALUE"""),689.472) -> 689.472 | BM30: =IFERROR(__xludf.DUMMYFUNCTION("""COMPUTED_VALUE"""),4998.672) -> 4998.672 | BN30: =IFERROR(__xludf.DUMMYFUNCTION("""COMPUTED_VALUE"""),4069.7999999999997) -> 4069.8 | BO30: =IFERROR(__xludf.DUMMYFUNCTION("""COMPUTED_VALUE"""),651.168) -> 651.168 | BP30: =IFERROR(__xludf.DUMMYFUNCTION("""COMPUTED_VALUE"""),4720.968) -> 4720.968 | BQ30: =IFERROR(__xludf.DUMMYFUNCTION("""COMPUTED_VALUE"""),3974.04) -> 3974.04 | BR30: =IFERROR(__xludf.DUMMYFUNCTION("""COMPUTED_VALUE"""),635.8464) -> 635.8464 | BS30: =IFERROR(__xludf.DUMMYFUNCTION("""COMPUTED_VALUE"""),4609.8864) -> 4609.8864 | BT30: =IFERROR(__xludf.DUMMYFUNCTION("""COMPUTED_VALUE"""),3830.4) -> 3830.4 | BU30: =IFERROR(__xludf.DUMMYFUNCTION("""COMPUTED_VALUE"""),612.864) -> 612.864 | BV30: =IFERROR(__xludf.DUMMYFUNCTION("""COMPUTED_VALUE"""),4443.264) -> 4443.264
D31: MG81 | E31: PZA | G31: AMASADORA 25KG C/PAL Y FLECH ACINOX TAPA | I31: =IF(D31="","",LEN(H31)) -> 0 | P31: 21867 | Q31: 21867 | R31: 24108 | S31: 25313 | T31: =S31*0.16 -> 4050.08 | U31: =S31+T31 -> 29363.08 | V31: =(S31-R31)/R31 -> 0.049983408 | W31: =(IF(B31="",(S31*(1-$W$1)),(IF(B31=1,(S31*(1-$W$1)),(IF(B31=2,(S31*(1-$W$1)),(IF(B31=3,(S31*(1-$W$1)),(IF(B31=4,(S31*(1)))))))))))) -> 24047.35 | X31: =W31*0.16 -> 3847.576 | Y31: =W31+X31 -> 27894.926 | Z31: =(IF(B31="",(S31*(1-$Z$1)),(IF(B31=1,(S31*(1-$Z$1)),(IF(B31=2,(S31*(1-$Z$1)),(IF(B31=3,(S31*(1-$Z$1)),(IF(B31=4,(S31*(1)))))))))))) -> 22781.7 | AA31: =Z31*0.16 -> 3645.072 | AB31: =Z31+AA31 -> 26426.772 | AC31: =(IF(B31="",(S31*(1-$AC$1)),(IF(B31=1,(S31*(1-$AC$1)),(IF(B31=2,(S31*(1-0.15)),(IF(B31=3,(S31*(1-0.1)),(IF(B31=4,(S31*(1)))))))))))) -> 21516.05 | AD31: =AC31*0.16 -> 3442.568 | AE31: =AC31+AD31 -> 24958.618 | AF31: =(IF(B31="",(S31*(1-$AF$1)),(IF(B31=1,(S31*(1-$AF$1)),(IF(B31=2,(S31*(1-0.15)),(IF(B31=3,(S31*(1-0.1)),(IF(B31=4,(S31*(1)))))))))))) -> 21009.79 | AG31: =AF31*0.16 -> 3361.5664 | AH31: =AF31+AG31 -> 24371.356 | AI31: =(IF(B31="",(S31*(1-$AI$1)),(IF(B31=1,(S31*(1-$AI$1)),(IF(B31=2,(S31*(1-0.15)),(IF(B31=3,(S31*(1-0.1)),(IF(B31=4,(S31*(1)))))))))))) -> 20250.4 | AJ31: =AI31*0.16 -> 3240.064 | AK31: =AI31+AJ31 -> 23490.464 | AL31: =IFERROR(__xludf.DUMMYFUNCTION("""COMPUTED_VALUE"""),1.0) -> 1 | AN31: =IFERROR(__xludf.DUMMYFUNCTION("""COMPUTED_VALUE""")," C") -> C | AO31: =IFERROR(__xludf.DUMMYFUNCTION("""COMPUTED_VALUE""")," AR10") -> AR10 | AP31: =IFERROR(__xludf.DUMMYFUNCTION("""COMPUTED_VALUE""")," PZA") -> PZA | AQ31: =IFERROR(__xludf.DUMMYFUNCTION("""COMPUTED_VALUE""")," REF") -> REF | AR31: =IFERROR(__xludf.DUMMYFUNCTION("""COMPUTED_VALUE""")," ARRANCADOR PARA MOTOR DE 3 HP MONOFÁSICO 220V CODIGO 10046370 11~17 AMP") -> ARRANCADOR PARA MOTOR DE 3 HP MONOFÁSICO 220V CODIGO 10046370 11~17 AMP | AS31: =IFERROR(__xludf.DUMMYFUNCTION("""COMPUTED_VALUE""")," ARRANCADOR 3HP MON 220V 10046370 11-17A") -> ARRANCADOR 3HP MON 220V 10046370 11-17A | AT31: =IFERROR(__xludf.DUMMYFUNCTION("""COMPUTED_VALUE"""),39.0) -> 39 | AY31: =IFERROR(__xludf.DUMMYFUNCTION("""COMPUTED_VALUE"""),3512.0) -> 3512 | AZ31: =IFERROR(__xludf.DUMMYFUNCTION("""COMPUTED_VALUE"""),3792.0) -> 3792 | BA31: =IFERROR(__xludf.DUMMYFUNCTION("""COMPUTED_VALUE"""),4095.36) -> 4095.36 | BB31: =IFERROR(__xludf.DUMMYFUNCTION("""COMPUTED_VALUE"""),4095.36) -> 4095.36 | BC31: =IFERROR(__xludf.DUMMYFUNCTION("""COMPUTED_VALUE"""),4560.0) -> 4560 | BD31: =IFERROR(__xludf.DUMMYFUNCTION("""COMPUTED_VALUE"""),2443.0) -> 2443 | BE31: =IFERROR(__xludf.DUMMYFUNCTION("""COMPUTED_VALUE"""),390.88) -> 390.88 | BF31: =IFERROR(__xludf.DUMMYFUNCTION("""COMPUTED_VALUE"""),2833.88) -> 2833.88 | BG31: =IFERROR(__xludf.DUMMYFUNCTION("""COMPUTED_VALUE"""),-0.4642543859649123) -> -0.46425439 | BH31: =IFERROR(__xludf.DUMMYFUNCTION("""COMPUTED_VALUE"""),2320.85) -> 2320.85 | BI31: =IFERROR(__xludf.DUMMYFUNCTION("""COMPUTED_VALUE"""),371.336) -> 371.336 | BJ31: =IFERROR(__xludf.DUMMYFUNCTION("""COMPUTED_VALUE"""),2692.1859999999997) -> 2692.186 | BK31: =IFERROR(__xludf.DUMMYFUNCTION("""COMPUTED_VALUE"""),2198.7000000000003) -> 2198.7 | BL31: =IFERROR(__xludf.DUMMYFUNCTION("""COMPUTED_VALUE"""),351.79200000000003) -> 351.792 | BM31: =IFERROR(__xludf.DUMMYFUNCTION("""COMPUTED_VALUE"""),2550.492) -> 2550.492 | BN31: =IFERROR(__xludf.DUMMYFUNCTION("""COMPUTED_VALUE"""),2076.5499999999997) -> 2076.55 | BO31: =IFERROR(__xludf.DUMMYFUNCTION("""COMPUTED_VALUE"""),332.248) -> 332.248 | BP31: =IFERROR(__xludf.DUMMYFUNCTION("""COMPUTED_VALUE"""),2408.798) -> 2408.798 | BQ31: =IFERROR(__xludf.DUMMYFUNCTION("""COMPUTED_VALUE"""),2027.6899999999998) -> 2027.69 | BR31: =IFERROR(__xludf.DUMMYFUNCTION("""COMPUTED_VALUE"""),324.43039999999996) -> 324.4304 | BS31: =IFERROR(__xludf.DUMMYFUNCTION("""COMPUTED_VALUE"""),2352.1204) -> 2352.1204 | BT31: =IFERROR(__xludf.DUMMYFUNCTION("""COMPUTED_VALUE"""),1954.4) -> 1954.4 | BU31: =IFERROR(__xludf.DUMMYFUNCTION("""COMPUTED_VALUE"""),312.704) -> 312.704 | BV31: =IFERROR(__xludf.DUMMYFUNCTION("""COMPUTED_VALUE"""),2267.1040000000003) -> 2267.104
D32: MM11 | E32: PZA | G32: AMASADORA 50 KG ACERO INOX. T-430 TRIFAS | I32: =IF(D32="","",LEN(H32)) -> 0 | P32: 17619 | Q32: 17619 | R32: 19425 | S32: 20396 | T32: =S32*0.16 -> 3263.36 | U32: =S32+T32 -> 23659.36 | V32: =(S32-R32)/R32 -> 0.04998713 | W32: =(IF(B32="",(S32*(1-$W$1)),(IF(B32=1,(S32*(1-$W$1)),(IF(B32=2,(S32*(1-$W$1)),(IF(B32=3,(S32*(1-$W$1)),(IF(B32=4,(S32*(1)))))))))))) -> 19376.2 | X32: =W32*0.16 -> 3100.192 | Y32: =W32+X32 -> 22476.392 | Z32: =(IF(B32="",(S32*(1-$Z$1)),(IF(B32=1,(S32*(1-$Z$1)),(IF(B32=2,(S32*(1-$Z$1)),(IF(B32=3,(S32*(1-$Z$1)),(IF(B32=4,(S32*(1)))))))))))) -> 18356.4 | AA32: =Z32*0.16 -> 2937.024 | AB32: =Z32+AA32 -> 21293.424 | AC32: =(IF(B32="",(S32*(1-$AC$1)),(IF(B32=1,(S32*(1-$AC$1)),(IF(B32=2,(S32*(1-0.15)),(IF(B32=3,(S32*(1-0.1)),(IF(B32=4,(S32*(1)))))))))))) -> 17336.6 | AD32: =AC32*0.16 -> 2773.856 | AE32: =AC32+AD32 -> 20110.456 | AF32: =(IF(B32="",(S32*(1-$AF$1)),(IF(B32=1,(S32*(1-$AF$1)),(IF(B32=2,(S32*(1-0.15)),(IF(B32=3,(S32*(1-0.1)),(IF(B32=4,(S32*(1)))))))))))) -> 16928.68 | AG32: =AF32*0.16 -> 2708.5888 | AH32: =AF32+AG32 -> 19637.269 | AI32: =(IF(B32="",(S32*(1-$AI$1)),(IF(B32=1,(S32*(1-$AI$1)),(IF(B32=2,(S32*(1-0.15)),(IF(B32=3,(S32*(1-0.1)),(IF(B32=4,(S32*(1)))))))))))) -> 16316.8 | AJ32: =AI32*0.16 -> 2610.688 | AK32: =AI32+AJ32 -> 18927.488 | AL32: =IFERROR(__xludf.DUMMYFUNCTION("""COMPUTED_VALUE"""),1.0) -> 1 | AN32: =IFERROR(__xludf.DUMMYFUNCTION("""COMPUTED_VALUE""")," C") -> C | AO32: =IFERROR(__xludf.DUMMYFUNCTION("""COMPUTED_VALUE""")," AR02") -> AR02 | AP32: =IFERROR(__xludf.DUMMYFUNCTION("""COMPUTED_VALUE""")," PZA") -> PZA | AQ32: =IFERROR(__xludf.DUMMYFUNCTION("""COMPUTED_VALUE""")," REF") -> REF | AR32: =IFERROR(__xludf.DUMMYFUNCTION("""COMPUTED_VALUE""")," ARRANCADOR PARA MOTOR DE 3 HP TRIFÁSICO 220V CODIGO 10046369 7~10 AMP") -> ARRANCADOR PARA MOTOR DE 3 HP TRIFÁSICO 220V CODIGO 10046369 7~10 AMP | AS32: =IFERROR(__xludf.DUMMYFUNCTION("""COMPUTED_VALUE""")," ARRANCADOR 3HP TRI 220V 10046369 7-10A") -> ARRANCADOR 3HP TRI 220V 10046369 7-10A | AT32: =IFERROR(__xludf.DUMMYFUNCTION("""COMPUTED_VALUE"""),38.0) -> 38 | AY32: =IFERROR(__xludf.DUMMYFUNCTION("""COMPUTED_VALUE"""),3143.0) -> 3143 | AZ32: =IFERROR(__xludf.DUMMYFUNCTION("""COMPUTED_VALUE"""),1628.0) -> 1628 | BA32: =IFERROR(__xludf.DUMMYFUNCTION("""COMPUTED_VALUE"""),1758.24) -> 1758.24 | BB32: =IFERROR(__xludf.DUMMYFUNCTION("""COMPUTED_VALUE"""),1758.24) -> 1758.24 | BC32: =IFERROR(__xludf.DUMMYFUNCTION("""COMPUTED_VALUE"""),1958.0) -> 1958 | BD32: =IFERROR(__xludf.DUMMYFUNCTION("""COMPUTED_VALUE"""),2056.0) -> 2056 | BE32: =IFERROR(__xludf.DUMMYFUNCTION("""COMPUTED_VALUE"""),328.96) -> 328.96 | BF32: =IFERROR(__xludf.DUMMYFUNCTION("""COMPUTED_VALUE"""),2384.96) -> 2384.96 | BG32: =IFERROR(__xludf.DUMMYFUNCTION("""COMPUTED_VALUE"""),0.05005107252298264) -> 0.050051073 | BH32: =IFERROR(__xludf.DUMMYFUNCTION("""COMPUTED_VALUE"""),1953.1999999999998) -> 1953.2 | BI32: =IFERROR(__xludf.DUMMYFUNCTION("""COMPUTED_VALUE"""),312.512) -> 312.512 | BJ32: =IFERROR(__xludf.DUMMYFUNCTION("""COMPUTED_VALUE"""),2265.712) -> 2265.712 | BK32: =IFERROR(__xludf.DUMMYFUNCTION("""COMPUTED_VALUE"""),1850.4) -> 1850.4 | BL32: =IFERROR(__xludf.DUMMYFUNCTION("""COMPUTED_VALUE"""),296.064) -> 296.064 | BM32: =IFERROR(__xludf.DUMMYFUNCTION("""COMPUTED_VALUE"""),2146.464) -> 2146.464 | BN32: =IFERROR(__xludf.DUMMYFUNCTION("""COMPUTED_VALUE"""),1747.6) -> 1747.6 | BO32: =IFERROR(__xludf.DUMMYFUNCTION("""COMPUTED_VALUE"""),279.616) -> 279.616 | BP32: =IFERROR(__xludf.DUMMYFUNCTION("""COMPUTED_VALUE"""),2027.216) -> 2027.216 | BQ32: =IFERROR(__xludf.DUMMYFUNCTION("""COMPUTED_VALUE"""),1706.48) -> 1706.48 | BR32: =IFERROR(__xludf.DUMMYFUNCTION("""COMPUTED_VALUE"""),273.0368) -> 273.0368 | BS32: =IFERROR(__xludf.DUMMYFUNCTION("""COMPUTED_VALUE"""),1979.5168) -> 1979.5168 | BT32: =IFERROR(__xludf.DUMMYFUNCTION("""COMPUTED_VALUE"""),1644.8000000000002) -> 1644.8 | BU32: =IFERROR(__xludf.DUMMYFUNCTION("""COMPUTED_VALUE"""),263.168) -> 263.168 | BV32: =IFERROR(__xludf.DUMMYFUNCTION("""COMPUTED_VALUE"""),1907.9680000000003) -> 1907.968
B33: 3 | C33: E | D33: MG123 | E33: PZA | F33: TGA | G33: AMASADORA DE 10 KG. CON PALETAS FUNDIDAS Y FLECHA EN ACERO INOX. T-304 G.A. | I33: =IF(D33="","",LEN(H33)) -> 0 | O33: 18823 | P33: 20328.84 | Q33: 20328.84 | R33: 22413 | S33: 23534 | T33: =S33*0.16 -> 3765.44 | U33: =S33+T33 -> 27299.44 | V33: =(S33-R33)/R33 -> 0.050015616 | W33: =(IF(B33="",(S33*(1-$W$1)),(IF(B33=1,(S33*(1-$W$1)),(IF(B33=2,(S33*(1-$W$1)),(IF(B33=3,(S33*(1-$W$1)),(IF(B33=4,(S33*(1)))))))))))) -> 22357.3 | X33: =W33*0.16 -> 3577.168 | Y33: =W33+X33 -> 25934.468 | Z33: =(IF(B33="",(S33*(1-$Z$1)),(IF(B33=1,(S33*(1-$Z$1)),(IF(B33=2,(S33*(1-$Z$1)),(IF(B33=3,(S33*(1-$Z$1)),(IF(B33=4,(S33*(1)))))))))))) -> 21180.6 | AA33: =Z33*0.16 -> 3388.896 | AB33: =Z33+AA33 -> 24569.496 | AC33: =(IF(B33="",(S33*(1-$AC$1)),(IF(B33=1,(S33*(1-$AC$1)),(IF(B33=2,(S33*(1-0.15)),(IF(B33=3,(S33*(1-0.1)),(IF(B33=4,(S33*(1)))))))))))) -> 21180.6 | AD33: =AC33*0.16 -> 3388.896 | AE33: =AC33+AD33 -> 24569.496 | AF33: =(IF(B33="",(S33*(1-$AF$1)),(IF(B33=1,(S33*(1-$AF$1)),(IF(B33=2,(S33*(1-0.15)),(IF(B33=3,(S33*(1-0.1)),(IF(B33=4,(S33*(1)))))))))))) -> 21180.6 | AG33: =AF33*0.16 -> 3388.896 | AH33: =AF33+AG33 -> 24569.496 | AI33: =(IF(B33="",(S33*(1-$AI$1)),(IF(B33=1,(S33*(1-$AI$1)),(IF(B33=2,(S33*(1-0.15)),(IF(B33=3,(S33*(1-0.1)),(IF(B33=4,(S33*(1)))))))))))) -> 21180.6 | AJ33: =AI33*0.16 -> 3388.896 | AK33: =AI33+AJ33 -> 24569.496 | AL33: =IFERROR(__xludf.DUMMYFUNCTION("""COMPUTED_VALUE"""),1.0) -> 1 | AN33: =IFERROR(__xludf.DUMMYFUNCTION("""COMPUTED_VALUE""")," C") -> C | AO33: =IFERROR(__xludf.DUMMYFUNCTION("""COMPUTED_VALUE""")," AR11") -> AR11 | AP33: =IFERROR(__xludf.DUMMYFUNCTION("""COMPUTED_VALUE""")," PZA") -> PZA | AQ33: =IFERROR(__xludf.DUMMYFUNCTION("""COMPUTED_VALUE""")," REF") -> REF | AR33: =IFERROR(__xludf.DUMMYFUNCTION("""COMPUTED_VALUE""")," ARRANCADOR PARA MOTOR DE 5 HP MONOFÁSICO 220V CODIGO 10072610 22~32 AMP") -> ARRANCADOR PARA MOTOR DE 5 HP MONOFÁSICO 220V CODIGO 10072610 22~32 AMP | AS33: =IFERROR(__xludf.DUMMYFUNCTION("""COMPUTED_VALUE""")," ARRANCADOR 5HP MON 220V 10072610 22-32A") -> ARRANCADOR 5HP MON 220V 10072610 22-32A | AT33: =IFERROR(__xludf.DUMMYFUNCTION("""COMPUTED_VALUE"""),39.0) -> 39 | AY33: =IFERROR(__xludf.DUMMYFUNCTION("""COMPUTED_VALUE"""),5184.0) -> 5184 | AZ33: =IFERROR(__xludf.DUMMYFUNCTION("""COMPUTED_VALUE"""),5598.0) -> 5598 | BA33: =IFERROR(__xludf.DUMMYFUNCTION("""COMPUTED_VALUE"""),6045.84) -> 6045.84 | BB33: =IFERROR(__xludf.DUMMYFUNCTION("""COMPUTED_VALUE"""),6045.84) -> 6045.84 | BC33: =IFERROR(__xludf.DUMMYFUNCTION("""COMPUTED_VALUE"""),6730.0) -> 6730 | BD33: =IFERROR(__xludf.DUMMYFUNCTION("""COMPUTED_VALUE"""),3390.0) -> 3390 | BE33: =IFERROR(__xludf.DUMMYFUNCTION("""COMPUTED_VALUE"""),542.4) -> 542.4 | BF33: =IFERROR(__xludf.DUMMYFUNCTION("""COMPUTED_VALUE"""),3932.4) -> 3932.4 | BG33: =IFERROR(__xludf.DUMMYFUNCTION("""COMPUTED_VALUE"""),-0.4962852897473997) -> -0.49628529 | BH33: =IFERROR(__xludf.DUMMYFUNCTION("""COMPUTED_VALUE"""),3220.5) -> 3220.5 | BI33: =IFERROR(__xludf.DUMMYFUNCTION("""COMPUTED_VALUE"""),515.28) -> 515.28 | BJ33: =IFERROR(__xludf.DUMMYFUNCTION("""COMPUTED_VALUE"""),3735.7799999999997) -> 3735.78 | BK33: =IFERROR(__xludf.DUMMYFUNCTION("""COMPUTED_VALUE"""),3051.0) -> 3051 | BL33: =IFERROR(__xludf.DUMMYFUNCTION("""COMPUTED_VALUE"""),488.16) -> 488.16 | BM33: =IFERROR(__xludf.DUMMYFUNCTION("""COMPUTED_VALUE"""),3539.16) -> 3539.16 | BN33: =IFERROR(__xludf.DUMMYFUNCTION("""COMPUTED_VALUE"""),2881.5) -> 2881.5 | BO33: =IFERROR(__xludf.DUMMYFUNCTION("""COMPUTED_VALUE"""),461.04) -> 461.04 | BP33: =IFERROR(__xludf.DUMMYFUNCTION("""COMPUTED_VALUE"""),3342.54) -> 3342.54 | BQ33: =IFERROR(__xludf.DUMMYFUNCTION("""COMPUTED_VALUE"""),2813.7) -> 2813.7 | BR33: =IFERROR(__xludf.DUMMYFUNCTION("""COMPUTED_VALUE"""),450.192) -> 450.192 | BS33: =IFERROR(__xludf.DUMMYFUNCTION("""COMPUTED_VALUE"""),3263.892) -> 3263.892 | BT33: =IFERROR(__xludf.DUMMYFUNCTION("""COMPUTED_VALUE"""),2712.0) -> 2712 | BU33: =IFERROR(__xludf.DUMMYFUNCTION("""COMPUTED_VALUE"""),433.92) -> 433.92 | BV33: =IFERROR(__xludf.DUMMYFUNCTION("""COMPUTED_VALUE"""),3145.92) -> 3145.92
B34: 3 | C34: E | D34: MM60 | E34: PZA | F34: TNO | G34: AMASADORA DE 10 KG. EN ACERO INOX. T-430 | I34: =IF(D34="","",LEN(H34)) -> 0 | O34: 12775 | P34: 13797 | Q34: 13797 | R34: 15212 | S34: 15973 | T34: =S34*0.16 -> 2555.68 | U34: =S34+T34 -> 18528.68 | V34: =(S34-R34)/R34 -> 0.050026295 | W34: =(IF(B34="",(S34*(1-$W$1)),(IF(B34=1,(S34*(1-$W$1)),(IF(B34=2,(S34*(1-$W$1)),(IF(B34=3,(S34*(1-$W$1)),(IF(B34=4,(S34*(1)))))))))))) -> 15174.35 | X34: =W34*0.16 -> 2427.896 | Y34: =W34+X34 -> 17602.246 | Z34: =(IF(B34="",(S34*(1-$Z$1)),(IF(B34=1,(S34*(1-$Z$1)),(IF(B34=2,(S34*(1-$Z$1)),(IF(B34=3,(S34*(1-$Z$1)),(IF(B34=4,(S34*(1)))))))))))) -> 14375.7 | AA34: =Z34*0.16 -> 2300.112 | AB34: =Z34+AA34 -> 16675.812 | AC34: =(IF(B34="",(S34*(1-$AC$1)),(IF(B34=1,(S34*(1-$AC$1)),(IF(B34=2,(S34*(1-0.15)),(IF(B34=3,(S34*(1-0.1)),(IF(B34=4,(S34*(1)))))))))))) -> 14375.7 | AD34: =AC34*0.16 -> 2300.112 | AE34: =AC34+AD34 -> 16675.812 | AF34: =(IF(B34="",(S34*(1-$AF$1)),(IF(B34=1,(S34*(1-$AF$1)),(IF(B34=2,(S34*(1-0.15)),(IF(B34=3,(S34*(1-0.1)),(IF(B34=4,(S34*(1)))))))))))) -> 14375.7 | AG34: =AF34*0.16 -> 2300.112 | AH34: =AF34+AG34 -> 16675.812 | AI34: =(IF(B34="",(S34*(1-$AI$1)),(IF(B34=1,(S34*(1-$AI$1)),(IF(B34=2,(S34*(1-0.15)),(IF(B34=3,(S34*(1-0.1)),(IF(B34=4,(S34*(1)))))))))))) -> 14375.7 | AJ34: =AI34*0.16 -> 2300.112 | AK34: =AI34+AJ34 -> 16675.812 | AL34: =IFERROR(__xludf.DUMMYFUNCTION("""COMPUTED_VALUE"""),1.0) -> 1 | AN34: =IFERROR(__xludf.DUMMYFUNCTION("""COMPUTED_VALUE""")," C") -> C | AO34: =IFERROR(__xludf.DUMMYFUNCTION("""COMPUTED_VALUE""")," AR03") -> AR03 | AP34: =IFERROR(__xludf.DUMMYFUNCTION("""COMPUTED_VALUE""")," PZA") -> PZA | AQ34: =IFERROR(__xludf.DUMMYFUNCTION("""COMPUTED_VALUE""")," REF") -> REF | AR34: =IFERROR(__xludf.DUMMYFUNCTION("""COMPUTED_VALUE""")," ARRANCADOR PARA MOTOR DE 5 HP TRIFÁSICO 220V CODIGO 10046370 11~17 AMP") -> ARRANCADOR PARA MOTOR DE 5 HP TRIFÁSICO 220V CODIGO 10046370 11~17 AMP | AS34: =IFERROR(__xludf.DUMMYFUNCTION("""COMPUTED_VALUE""")," ARRANCADOR 5HP TRI 220V 10046370 11-17A") -> ARRANCADOR 5HP TRI 220V 10046370 11-17A | AT34: =IFERROR(__xludf.DUMMYFUNCTION("""COMPUTED_VALUE"""),39.0) -> 39 | AY34: =IFERROR(__xludf.DUMMYFUNCTION("""COMPUTED_VALUE"""),3512.0) -> 3512 | AZ34: =IFERROR(__xludf.DUMMYFUNCTION("""COMPUTED_VALUE"""),1935.0) -> 1935 | BA34: =IFERROR(__xludf.DUMMYFUNCTION("""COMPUTED_VALUE"""),2089.8) -> 2089.8 | BB34: =IFERROR(__xludf.DUMMYFUNCTION("""COMPUTED_VALUE"""),2089.8) -> 2089.8 | BC34: =IFERROR(__xludf.DUMMYFUNCTION("""COMPUTED_VALUE"""),2327.0) -> 2327 | BD34: =IFERROR(__xludf.DUMMYFUNCTION("""COMPUTED_VALUE"""),2443.0) -> 2443 | BE34: =IFERROR(__xludf.DUMMYFUNCTION("""COMPUTED_VALUE"""),390.88) -> 390.88 | BF34: =IFERROR(__xludf.DUMMYFUNCTION("""COMPUTED_VALUE"""),2833.88) -> 2833.88 | BG34: =IFERROR(__xludf.DUMMYFUNCTION("""COMPUTED_VALUE"""),0.04984959174903309) -> 0.049849592 | BH34: =IFERROR(__xludf.DUMMYFUNCTION("""COMPUTED_VALUE"""),2320.85) -> 2320.85 | BI34: =IFERROR(__xludf.DUMMYFUNCTION("""COMPUTED_VALUE"""),371.336) -> 371.336 | BJ34: =IFERROR(__xludf.DUMMYFUNCTION("""COMPUTED_VALUE"""),2692.1859999999997) -> 2692.186 | BK34: =IFERROR(__xludf.DUMMYFUNCTION("""COMPUTED_VALUE"""),2198.7000000000003) -> 2198.7 | BL34: =IFERROR(__xludf.DUMMYFUNCTION("""COMPUTED_VALUE"""),351.79200000000003) -> 351.792 | BM34: =IFERROR(__xludf.DUMMYFUNCTION("""COMPUTED_VALUE"""),2550.492) -> 2550.492 | BN34: =IFERROR(__xludf.DUMMYFUNCTION("""COMPUTED_VALUE"""),2076.5499999999997) -> 2076.55 | BO34: =IFERROR(__xludf.DUMMYFUNCTION("""COMPUTED_VALUE"""),332.248) -> 332.248 | BP34: =IFERROR(__xludf.DUMMYFUNCTION("""COMPUTED_VALUE"""),2408.798) -> 2408.798 | BQ34: =IFERROR(__xludf.DUMMYFUNCTION("""COMPUTED_VALUE"""),2027.6899999999998) -> 2027.69 | BR34: =IFERROR(__xludf.DUMMYFUNCTION("""COMPUTED_VALUE"""),324.43039999999996) -> 324.4304 | BS34: =IFERROR(__xludf.DUMMYFUNCTION("""COMPUTED_VALUE"""),2352.1204) -> 2352.1204 | BT34: =IFERROR(__xludf.DUMMYFUNCTION("""COMPUTED_VALUE"""),1954.4) -> 1954.4 | BU34: =IFERROR(__xludf.DUMMYFUNCTION("""COMPUTED_VALUE"""),312.704) -> 312.704 | BV34: =IFERROR(__xludf.DUMMYFUNCTION("""COMPUTED_VALUE"""),2267.1040000000003) -> 2267.104
B35: 3 | C35: E | D35: MG03 | E35: PZA | F35: TGA | G35: AMASADORA DE 100 KG. CON PALETAS FUNDIDAS Y FLECHA EN ACERO INOX. T-304 G.A. | H35: AMASADORA 100KG PAL FUND FLE INOX | I35: =IF(D35="","",LEN(H35)) -> 33 | O35: 32132 | P35: 34702.56 | Q35: 34702.56 | R35: 38260 | S35: 37550 | T35: =S35*0.16 -> 6008 | U35: =S35+T35 -> 43558 | V35: =(S35-R35)/R35 -> -0.01855724 | W35: =(IF(B35="",(S35*(1-$W$1)),(IF(B35=1,(S35*(1-$W$1)),(IF(B35=2,(S35*(1-$W$1)),(IF(B35=3,(S35*(1-$W$1)),(IF(B35=4,(S35*(1)))))))))))) -> 35672.5 | X35: =W35*0.16 -> 5707.6 | Y35: =W35+X35 -> 41380.1 | Z35: =(IF(B35="",(S35*(1-$Z$1)),(IF(B35=1,(S35*(1-$Z$1)),(IF(B35=2,(S35*(1-$Z$1)),(IF(B35=3,(S35*(1-$Z$1)),(IF(B35=4,(S35*(1)))))))))))) -> 33795 | AA35: =Z35*0.16 -> 5407.2 | AB35: =Z35+AA35 -> 39202.2 | AC35: =(IF(B35="",(S35*(1-$AC$1)),(IF(B35=1,(S35*(1-$AC$1)),(IF(B35=2,(S35*(1-0.15)),(IF(B35=3,(S35*(1-0.1)),(IF(B35=4,(S35*(1)))))))))))) -> 33795 | AD35: =AC35*0.16 -> 5407.2 | AE35: =AC35+AD35 -> 39202.2 | AF35: =(IF(B35="",(S35*(1-$AF$1)),(IF(B35=1,(S35*(1-$AF$1)),(IF(B35=2,(S35*(1-0.15)),(IF(B35=3,(S35*(1-0.1)),(IF(B35=4,(S35*(1)))))))))))) -> 33795 | AG35: =AF35*0.16 -> 5407.2 | AH35: =AF35+AG35 -> 39202.2 | AI35: =(IF(B35="",(S35*(1-$AI$1)),(IF(B35=1,(S35*(1-$AI$1)),(IF(B35=2,(S35*(1-0.15)),(IF(B35=3,(S35*(1-0.1)),(IF(B35=4,(S35*(1)))))))))))) -> 33795 | AJ35: =AI35*0.16 -> 5407.2 | AK35: =AI35+AJ35 -> 39202.2 | AL35: =IFERROR(__xludf.DUMMYFUNCTION("""COMPUTED_VALUE"""),1.0) -> 1 | AN35: =IFERROR(__xludf.DUMMYFUNCTION("""COMPUTED_VALUE""")," C") -> C | AO35: =IFERROR(__xludf.DUMMYFUNCTION("""COMPUTED_VALUE""")," AR12") -> AR12 | AP35: =IFERROR(__xludf.DUMMYFUNCTION("""COMPUTED_VALUE""")," PZA") -> PZA | AQ35: =IFERROR(__xludf.DUMMYFUNCTION("""COMPUTED_VALUE""")," REF") -> REF | AR35: =IFERROR(__xludf.DUMMYFUNCTION("""COMPUTED_VALUE""")," ARRANCADOR PARA MOTOR DE 7.5 HP MONOFÁSICO 220V CODIGO 10046372 32~50 AMP") -> ARRANCADOR PARA MOTOR DE 7.5 HP MONOFÁSICO 220V CODIGO 10046372 32~50 AMP | AS35: =IFERROR(__xludf.DUMMYFUNCTION("""COMPUTED_VALUE""")," ARRANCADOR7.5HP MON 220V 10046372 32-50A") -> ARRANCADOR7.5HP MON 220V 10046372 32-50A | AT35: =IFERROR(__xludf.DUMMYFUNCTION("""COMPUTED_VALUE"""),40.0) -> 40 | AY35: =IFERROR(__xludf.DUMMYFUNCTION("""COMPUTED_VALUE"""),6858.0) -> 6858 | AZ35: =IFERROR(__xludf.DUMMYFUNCTION("""COMPUTED_VALUE"""),7406.0) -> 7406 | BA35: =IFERROR(__xludf.DUMMYFUNCTION("""COMPUTED_VALUE"""),7998.4800000000005) -> 7998.48 | BB35: =IFERROR(__xludf.DUMMYFUNCTION("""COMPUTED_VALUE"""),7998.4800000000005) -> 7998.48 | BC35: =IFERROR(__xludf.DUMMYFUNCTION("""COMPUTED_VALUE"""),8903.0) -> 8903 | BD35: =IFERROR(__xludf.DUMMYFUNCTION("""COMPUTED_VALUE"""),4486.0) -> 4486 | BE35: =IFERROR(__xludf.DUMMYFUNCTION("""COMPUTED_VALUE"""),717.76) -> 717.76 | BF35: =IFERROR(__xludf.DUMMYFUNCTION("""COMPUTED_VALUE"""),5203.76) -> 5203.76 | BG35: =IFERROR(__xludf.DUMMYFUNCTION("""COMPUTED_VALUE"""),-0.49612490171852186) -> -0.4961249 | BH35: =IFERROR(__xludf.DUMMYFUNCTION("""COMPUTED_VALUE"""),4261.7) -> 4261.7 | BI35: =IFERROR(__xludf.DUMMYFUNCTION("""COMPUTED_VALUE"""),681.872) -> 681.872 | BJ35: =IFERROR(__xludf.DUMMYFUNCTION("""COMPUTED_VALUE"""),4943.572) -> 4943.572 | BK35: =IFERROR(__xludf.DUMMYFUNCTION("""COMPUTED_VALUE"""),4037.4) -> 4037.4 | BL35: =IFERROR(__xludf.DUMMYFUNCTION("""COMPUTED_VALUE"""),645.984) -> 645.984 | BM35: =IFERROR(__xludf.DUMMYFUNCTION("""COMPUTED_VALUE"""),4683.384) -> 4683.384 | BN35: =IFERROR(__xludf.DUMMYFUNCTION("""COMPUTED_VALUE"""),3813.1) -> 3813.1 | BO35: =IFERROR(__xludf.DUMMYFUNCTION("""COMPUTED_VALUE"""),610.096) -> 610.096 | BP35: =IFERROR(__xludf.DUMMYFUNCTION("""COMPUTED_VALUE"""),4423.196) -> 4423.196 | BQ35: =IFERROR(__xludf.DUMMYFUNCTION("""COMPUTED_VALUE"""),3723.3799999999997) -> 3723.38 | BR35: =IFERROR(__xludf.DUMMYFUNCTION("""COMPUTED_VALUE"""),595.7407999999999) -> 595.7408 | BS35: =IFERROR(__xludf.DUMMYFUNCTION("""COMPUTED_VALUE"""),4319.1208) -> 4319.1208 | BT35: =IFERROR(__xludf.DUMMYFUNCTION("""COMPUTED_VALUE"""),3588.8) -> 3588.8 | BU35: =IFERROR(__xludf.DUMMYFUNCTION("""COMPUTED_VALUE"""),574.2080000000001) -> 574.208 | BV35: =IFERROR(__xludf.DUMMYFUNCTION("""COMPUTED_VALUE"""),4163.008) -> 4163.008
B36: 3 | C36: E | D36: MG129 | E36: PZA | F36: TGA | G36: AMASADORA DE 100 KG. CON PALETAS FUNDIDAS Y FLECHA EN ACERO INOX. T-304 G.A. SIN ESQUINAS | H36: AMASADORA 100K PAL FUND FLE INOX SIN ESQ | I36: =IF(D36="","",LEN(H36)) -> 40 | O36: 36747 | P36: 39686.76 | Q36: 39686.76 | R36: 43755 | S36: 41350 | T36: =S36*0.16 -> 6616 | U36: =S36+T36 -> 47966 | V36: =(S36-R36)/R36 -> -0.054965147 | W36: =(IF(B36="",(S36*(1-$W$1)),(IF(B36=1,(S36*(1-$W$1)),(IF(B36=2,(S36*(1-$W$1)),(IF(B36=3,(S36*(1-$W$1)),(IF(B36=4,(S36*(1)))))))))))) -> 39282.5 | X36: =W36*0.16 -> 6285.2 | Y36: =W36+X36 -> 45567.7 | Z36: =(IF(B36="",(S36*(1-$Z$1)),(IF(B36=1,(S36*(1-$Z$1)),(IF(B36=2,(S36*(1-$Z$1)),(IF(B36=3,(S36*(1-$Z$1)),(IF(B36=4,(S36*(1)))))))))))) -> 37215 | AA36: =Z36*0.16 -> 5954.4 | AB36: =Z36+AA36 -> 43169.4 | AC36: =(IF(B36="",(S36*(1-$AC$1)),(IF(B36=1,(S36*(1-$AC$1)),(IF(B36=2,(S36*(1-0.15)),(IF(B36=3,(S36*(1-0.1)),(IF(B36=4,(S36*(1)))))))))))) -> 37215 | AD36: =AC36*0.16 -> 5954.4 | AE36: =AC36+AD36 -> 43169.4 | AF36: =(IF(B36="",(S36*(1-$AF$1)),(IF(B36=1,(S36*(1-$AF$1)),(IF(B36=2,(S36*(1-0.15)),(IF(B36=3,(S36*(1-0.1)),(IF(B36=4,(S36*(1)))))))))))) -> 37215 | AG36: =AF36*0.16 -> 5954.4 | AH36: =AF36+AG36 -> 43169.4 | AI36: =(IF(B36="",(S36*(1-$AI$1)),(IF(B36=1,(S36*(1-$AI$1)),(IF(B36=2,(S36*(1-0.15)),(IF(B36=3,(S36*(1-0.1)),(IF(B36=4,(S36*(1)))))))))))) -> 37215 | AJ36: =AI36*0.16 -> 5954.4 | AK36: =AI36+AJ36 -> 43169.4 | AL36: =IFERROR(__xludf.DUMMYFUNCTION("""COMPUTED_VALUE"""),1.0) -> 1 | AN36: =IFERROR(__xludf.DUMMYFUNCTION("""COMPUTED_VALUE""")," C") -> C | AO36: =IFERROR(__xludf.DUMMYFUNCTION("""COMPUTED_VALUE""")," AR04") -> AR04 | AP36: =IFERROR(__xludf.DUMMYFUNCTION("""COMPUTED_VALUE""")," PZA") -> PZA | AQ36: =IFERROR(__xludf.DUMMYFUNCTION("""COMPUTED_VALUE""")," REF") -> REF | AR36: =IFERROR(__xludf.DUMMYFUNCTION("""COMPUTED_VALUE""")," ARRANCADOR PARA MOTOR DE 7.5 HP TRIFÁSICO 220V CODIGO 10045781 15~23 AMP") -> ARRANCADOR PARA MOTOR DE 7.5 HP TRIFÁSICO 220V CODIGO 10045781 15~23 AMP | AS36: =IFERROR(__xludf.DUMMYFUNCTION("""COMPUTED_VALUE""")," ARRANCADOR7.5HP TRI 220V 10045781 15-23A") -> ARRANCADOR7.5HP TRI 220V 10045781 15-23A | AT36: =IFERROR(__xludf.DUMMYFUNCTION("""COMPUTED_VALUE"""),40.0) -> 40 | AY36: =IFERROR(__xludf.DUMMYFUNCTION("""COMPUTED_VALUE"""),3512.0) -> 3512 | AZ36: =IFERROR(__xludf.DUMMYFUNCTION("""COMPUTED_VALUE"""),1935.0) -> 1935 | BA36: =IFERROR(__xludf.DUMMYFUNCTION("""COMPUTED_VALUE"""),2089.8) -> 2089.8 | BB36: =IFERROR(__xludf.DUMMYFUNCTION("""COMPUTED_VALUE"""),2089.8) -> 2089.8 | BC36: =IFERROR(__xludf.DUMMYFUNCTION("""COMPUTED_VALUE"""),2327.0) -> 2327 | BD36: =IFERROR(__xludf.DUMMYFUNCTION("""COMPUTED_VALUE"""),2443.0) -> 2443 | BE36: =IFERROR(__xludf.DUMMYFUNCTION("""COMPUTED_VALUE"""),390.88) -> 390.88 | BF36: =IFERROR(__xludf.DUMMYFUNCTION("""COMPUTED_VALUE"""),2833.88) -> 2833.88 | BG36: =IFERROR(__xludf.DUMMYFUNCTION("""COMPUTED_VALUE"""),0.04984959174903309) -> 0.049849592 | BH36: =IFERROR(__xludf.DUMMYFUNCTION("""COMPUTED_VALUE"""),2320.85) -> 2320.85 | BI36: =IFERROR(__xludf.DUMMYFUNCTION("""COMPUTED_VALUE"""),371.336) -> 371.336 | BJ36: =IFERROR(__xludf.DUMMYFUNCTION("""COMPUTED_VALUE"""),2692.1859999999997) -> 2692.186 | BK36: =IFERROR(__xludf.DUMMYFUNCTION("""COMPUTED_VALUE"""),2198.7000000000003) -> 2198.7 | BL36: =IFERROR(__xludf.DUMMYFUNCTION("""COMPUTED_VALUE"""),351.79200000000003) -> 351.792 | BM36: =IFERROR(__xludf.DUMMYFUNCTION("""COMPUTED_VALUE"""),2550.492) -> 2550.492 | BN36: =IFERROR(__xludf.DUMMYFUNCTION("""COMPUTED_VALUE"""),2076.5499999999997) -> 2076.55 | BO36: =IFERROR(__xludf.DUMMYFUNCTION("""COMPUTED_VALUE"""),332.248) -> 332.248 | BP36: =IFERROR(__xludf.DUMMYFUNCTION("""COMPUTED_VALUE"""),2408.798) -> 2408.798 | BQ36: =IFERROR(__xludf.DUMMYFUNCTION("""COMPUTED_VALUE"""),2027.6899999999998) -> 2027.69 | BR36: =IFERROR(__xludf.DUMMYFUNCTION("""COMPUTED_VALUE"""),324.43039999999996) -> 324.4304 | BS36: =IFERROR(__xludf.DUMMYFUNCTION("""COMPUTED_VALUE"""),2352.1204) -> 2352.1204 | BT36: =IFERROR(__xludf.DUMMYFUNCTION("""COMPUTED_VALUE"""),1954.4) -> 1954.4 | BU36: =IFERROR(__xludf.DUMMYFUNCTION("""COMPUTED_VALUE"""),312.704) -> 312.704 | BV36: =IFERROR(__xludf.DUMMYFUNCTION("""COMPUTED_VALUE"""),2267.1040000000003) -> 2267.104
B37: 3 | C37: E | D37: MG82 | E37: PZA | F37: TGA | G37: AMASADORA DE 100 KG. CON PALETAS FUNDIDAS Y FLECHA EN ACERO INOX. T-304 G.A. SIN ESQUINAS MOT MONO | H37: AMASADORA 100K PAL FUND FLE INX S/ES MON | I37: =IF(D37="","",LEN(H37)) -> 40 | O37: 38389 | P37: 41460.12 | Q37: 41460.12 | R37: 45710 | S37: 43550 | T37: =S37*0.16 -> 6968 | U37: =S37+T37 -> 50518 | V37: =(S37-R37)/R37 -> -0.04725443 | W37: =(IF(B37="",(S37*(1-$W$1)),(IF(B37=1,(S37*(1-$W$1)),(IF(B37=2,(S37*(1-$W$1)),(IF(B37=3,(S37*(1-$W$1)),(IF(B37=4,(S37*(1)))))))))))) -> 41372.5 | X37: =W37*0.16 -> 6619.6 | Y37: =W37+X37 -> 47992.1 | Z37: =(IF(B37="",(S37*(1-$Z$1)),(IF(B37=1,(S37*(1-$Z$1)),(IF(B37=2,(S37*(1-$Z$1)),(IF(B37=3,(S37*(1-$Z$1)),(IF(B37=4,(S37*(1)))))))))))) -> 39195 | AA37: =Z37*0.16 -> 6271.2 | AB37: =Z37+AA37 -> 45466.2 | AC37: =(IF(B37="",(S37*(1-$AC$1)),(IF(B37=1,(S37*(1-$AC$1)),(IF(B37=2,(S37*(1-0.15)),(IF(B37=3,(S37*(1-0.1)),(IF(B37=4,(S37*(1)))))))))))) -> 39195 | AD37: =AC37*0.16 -> 6271.2 | AE37: =AC37+AD37 -> 45466.2 | AF37: =(IF(B37="",(S37*(1-$AF$1)),(IF(B37=1,(S37*(1-$AF$1)),(IF(B37=2,(S37*(1-0.15)),(IF(B37=3,(S37*(1-0.1)),(IF(B37=4,(S37*(1)))))))))))) -> 39195 | AG37: =AF37*0.16 -> 6271.2 | AH37: =AF37+AG37 -> 45466.2 | AI37: =(IF(B37="",(S37*(1-$AI$1)),(IF(B37=1,(S37*(1-$AI$1)),(IF(B37=2,(S37*(1-0.15)),(IF(B37=3,(S37*(1-0.1)),(IF(B37=4,(S37*(1)))))))))))) -> 39195 | AJ37: =AI37*0.16 -> 6271.2 | AK37: =AI37+AJ37 -> 45466.2 | AL37: =IFERROR(__xludf.DUMMYFUNCTION("""COMPUTED_VALUE"""),1.0) -> 1 | AN37: =IFERROR(__xludf.DUMMYFUNCTION("""COMPUTED_VALUE""")," P") -> P | AO37: =IFERROR(__xludf.DUMMYFUNCTION("""COMPUTED_VALUE""")," AS01") -> AS01 | AP37: =IFERROR(__xludf.DUMMYFUNCTION("""COMPUTED_VALUE""")," PZA") -> PZA | AQ37: =IFERROR(__xludf.DUMMYFUNCTION("""COMPUTED_VALUE""")," REF") -> REF | AR37: =IFERROR(__xludf.DUMMYFUNCTION("""COMPUTED_VALUE""")," ASPA DE 4 ALETAS PARA VENTILADOR") -> ASPA DE 4 ALETAS PARA VENTILADOR | AS37: =IFERROR(__xludf.DUMMYFUNCTION("""COMPUTED_VALUE""")," ASPA DE 4 ALETAS PARA VENTILADOR") -> ASPA DE 4 ALETAS PARA VENTILADOR | AT37: =IFERROR(__xludf.DUMMYFUNCTION("""COMPUTED_VALUE"""),32.0) -> 32 | AY37: =IFERROR(__xludf.DUMMYFUNCTION("""COMPUTED_VALUE"""),100.0) -> 100 | AZ37: =IFERROR(__xludf.DUMMYFUNCTION("""COMPUTED_VALUE"""),108.0) -> 108 | BA37: =IFERROR(__xludf.DUMMYFUNCTION("""COMPUTED_VALUE"""),116.64000000000001) -> 116.64 | BB37: =IFERROR(__xludf.DUMMYFUNCTION("""COMPUTED_VALUE"""),116.64000000000001) -> 116.64 | BC37: =IFERROR(__xludf.DUMMYFUNCTION("""COMPUTED_VALUE"""),131.0) -> 131 | BD37: =IFERROR(__xludf.DUMMYFUNCTION("""COMPUTED_VALUE"""),138.0) -> 138 | BE37: =IFERROR(__xludf.DUMMYFUNCTION("""COMPUTED_VALUE"""),22.080000000000002) -> 22.08 | BF37: =IFERROR(__xludf.DUMMYFUNCTION("""COMPUTED_VALUE"""),160.08) -> 160.08 | BG37: =IFERROR(__xludf.DUMMYFUNCTION("""COMPUTED_VALUE"""),0.05343511450381679) -> 0.053435114 | BH37: =IFERROR(__xludf.DUMMYFUNCTION("""COMPUTED_VALUE"""),131.1) -> 131.1 | BI37: =IFERROR(__xludf.DUMMYFUNCTION("""COMPUTED_VALUE"""),20.976) -> 20.976 | BJ37: =IFERROR(__xludf.DUMMYFUNCTION("""COMPUTED_VALUE"""),152.076) -> 152.076 | BK37: =IFERROR(__xludf.DUMMYFUNCTION("""COMPUTED_VALUE"""),124.2) -> 124.2 | BL37: =IFERROR(__xludf.DUMMYFUNCTION("""COMPUTED_VALUE"""),19.872) -> 19.872 | BM37: =IFERROR(__xludf.DUMMYFUNCTION("""COMPUTED_VALUE"""),144.072) -> 144.072 | BN37: =IFERROR(__xludf.DUMMYFUNCTION("""COMPUTED_VALUE"""),117.3) -> 117.3 | BO37: =IFERROR(__xludf.DUMMYFUNCTION("""COMPUTED_VALUE"""),18.768) -> 18.768 | BP37: =IFERROR(__xludf.DUMMYFUNCTION("""COMPUTED_VALUE"""),136.06799999999998) -> 136.068 | BQ37: =IFERROR(__xludf.DUMMYFUNCTION("""COMPUTED_VALUE"""),114.53999999999999) -> 114.54 | BR37: =IFERROR(__xludf.DUMMYFUNCTION("""COMPUTED_VALUE"""),18.3264) -> 18.3264 | BS37: =IFERROR(__xludf.DUMMYFUNCTION("""COMPUTED_VALUE"""),132.8664) -> 132.8664 | BT37: =IFERROR(__xludf.DUMMYFUNCTION("""COMPUTED_VALUE"""),110.4) -> 110.4 | BU37: =IFERROR(__xludf.DUMMYFUNCTION("""COMPUTED_VALUE"""),17.664) -> 17.664 | BV37: =IFERROR(__xludf.DUMMYFUNCTION("""COMPUTED_VALUE"""),128.06400000000002) -> 128.064
B38: 3 | C38: E | D38: MG302 | E38: PZA | F38: TGA | G38: AMASADORA DE 25 KG. CON ASPA FLECHA EN ACERO INOX. T-304 PARA TAMAL G.A. | H38: AMASADORA 25KG C/ASPA FLE INOX P/TAMAL | I38: =IF(D38="","",LEN(H38)) -> 38 | O38: 23718 | P38: 25615.44 | Q38: 25615.44 | R38: 28241 | S38: 29653 | T38: =S38*0.16 -> 4744.48 | U38: =S38+T38 -> 34397.48 | V38: =(S38-R38)/R38 -> 0.04999823 | W38: =(IF(B38="",(S38*(1-$W$1)),(IF(B38=1,(S38*(1-$W$1)),(IF(B38=2,(S38*(1-$W$1)),(IF(B38=3,(S38*(1-$W$1)),(IF(B38=4,(S38*(1)))))))))))) -> 28170.35 | X38: =W38*0.16 -> 4507.256 | Y38: =W38+X38 -> 32677.606 | Z38: =(IF(B38="",(S38*(1-$Z$1)),(IF(B38=1,(S38*(1-$Z$1)),(IF(B38=2,(S38*(1-$Z$1)),(IF(B38=3,(S38*(1-$Z$1)),(IF(B38=4,(S38*(1)))))))))))) -> 26687.7 | AA38: =Z38*0.16 -> 4270.032 | AB38: =Z38+AA38 -> 30957.732 | AC38: =(IF(B38="",(S38*(1-$AC$1)),(IF(B38=1,(S38*(1-$AC$1)),(IF(B38=2,(S38*(1-0.15)),(IF(B38=3,(S38*(1-0.1)),(IF(B38=4,(S38*(1)))))))))))) -> 26687.7 | AD38: =AC38*0.16 -> 4270.032 | AE38: =AC38+AD38 -> 30957.732 | AF38: =(IF(B38="",(S38*(1-$AF$1)),(IF(B38=1,(S38*(1-$AF$1)),(IF(B38=2,(S38*(1-0.15)),(IF(B38=3,(S38*(1-0.1)),(IF(B38=4,(S38*(1)))))))))))) -> 26687.7 | AG38: =AF38*0.16 -> 4270.032 | AH38: =AF38+AG38 -> 30957.732 | AI38: =(IF(B38="",(S38*(1-$AI$1)),(IF(B38=1,(S38*(1-$AI$1)),(IF(B38=2,(S38*(1-0.15)),(IF(B38=3,(S38*(1-0.1)),(IF(B38=4,(S38*(1)))))))))))) -> 26687.7 | AJ38: =AI38*0.16 -> 4270.032 | AK38: =AI38+AJ38 -> 30957.732 | AL38: =IFERROR(__xludf.DUMMYFUNCTION("""COMPUTED_VALUE"""),1.0) -> 1 | AN38: =IFERROR(__xludf.DUMMYFUNCTION("""COMPUTED_VALUE""")," P") -> P | AO38: =IFERROR(__xludf.DUMMYFUNCTION("""COMPUTED_VALUE""")," AS02") -> AS02 | AP38: =IFERROR(__xludf.DUMMYFUNCTION("""COMPUTED_VALUE""")," PZA") -> PZA | AQ38: =IFERROR(__xludf.DUMMYFUNCTION("""COMPUTED_VALUE""")," REF") -> REF | AR38: =IFERROR(__xludf.DUMMYFUNCTION("""COMPUTED_VALUE""")," ASPA DE 8 ALETAS PARA VENTILADOR") -> ASPA DE 8 ALETAS PARA VENTILADOR | AS38: =IFERROR(__xludf.DUMMYFUNCTION("""COMPUTED_VALUE""")," ASPA DE 8 ALETAS PARA VENTILADOR") -> ASPA DE 8 ALETAS PARA VENTILADOR | AT38: =IFERROR(__xludf.DUMMYFUNCTION("""COMPUTED_VALUE"""),32.0) -> 32 | AY38: =IFERROR(__xludf.DUMMYFUNCTION("""COMPUTED_VALUE"""),151.0) -> 151 | AZ38: =IFERROR(__xludf.DUMMYFUNCTION("""COMPUTED_VALUE"""),163.0) -> 163 | BA38: =IFERROR(__xludf.DUMMYFUNCTION("""COMPUTED_VALUE"""),176.04000000000002) -> 176.04 | BB38: =IFERROR(__xludf.DUMMYFUNCTION("""COMPUTED_VALUE"""),176.04000000000002) -> 176.04 | BC38: =IFERROR(__xludf.DUMMYFUNCTION("""COMPUTED_VALUE"""),197.0) -> 197 | BD38: =IFERROR(__xludf.DUMMYFUNCTION("""COMPUTED_VALUE"""),207.0) -> 207 | BE38: =IFERROR(__xludf.DUMMYFUNCTION("""COMPUTED_VALUE"""),33.12) -> 33.12 | BF38: =IFERROR(__xludf.DUMMYFUNCTION("""COMPUTED_VALUE"""),240.12) -> 240.12 | BG38: =IFERROR(__xludf.DUMMYFUNCTION("""COMPUTED_VALUE"""),0.050761421319796954) -> 0.050761421 | BH38: =IFERROR(__xludf.DUMMYFUNCTION("""COMPUTED_VALUE"""),196.64999999999998) -> 196.65 | BI38: =IFERROR(__xludf.DUMMYFUNCTION("""COMPUTED_VALUE"""),31.464) -> 31.464 | BJ38: =IFERROR(__xludf.DUMMYFUNCTION("""COMPUTED_VALUE"""),228.11399999999998) -> 228.114 | BK38: =IFERROR(__xludf.DUMMYFUNCTION("""COMPUTED_VALUE"""),186.3) -> 186.3 | BL38: =IFERROR(__xludf.DUMMYFUNCTION("""COMPUTED_VALUE"""),29.808000000000003) -> 29.808 | BM38: =IFERROR(__xludf.DUMMYFUNCTION("""COMPUTED_VALUE"""),216.108) -> 216.108 | BN38: =IFERROR(__xludf.DUMMYFUNCTION("""COMPUTED_VALUE"""),175.95) -> 175.95 | BO38: =IFERROR(__xludf.DUMMYFUNCTION("""COMPUTED_VALUE"""),28.151999999999997) -> 28.152 | BP38: =IFERROR(__xludf.DUMMYFUNCTION("""COMPUTED_VALUE"""),204.10199999999998) -> 204.102 | BQ38: =IFERROR(__xludf.DUMMYFUNCTION("""COMPUTED_VALUE"""),171.81) -> 171.81 | BR38: =IFERROR(__xludf.DUMMYFUNCTION("""COMPUTED_VALUE"""),27.4896) -> 27.4896 | BS38: =IFERROR(__xludf.DUMMYFUNCTION("""COMPUTED_VALUE"""),199.2996) -> 199.2996 | BT38: =IFERROR(__xludf.DUMMYFUNCTION("""COMPUTED_VALUE"""),165.60000000000002) -> 165.6 | BU38: =IFERROR(__xludf.DUMMYFUNCTION("""COMPUTED_VALUE"""),26.496000000000006) -> 26.496 | BV38: =IFERROR(__xludf.DUMMYFUNCTION("""COMPUTED_VALUE"""),192.09600000000003) -> 192.096
B39: 3 | C39: E | D39: MG01 | E39: PZA | F39: TGA | G39: AMASADORA DE 25 KG. CON PALETAS FUNDIDAS Y FLECHA EN ACERO INOX. T-304 G.A. | I39: =IF(D39="","",LEN(H39)) -> 0 | O39: 18823 | P39: 20328.84 | Q39: 20328.84 | R39: 22413 | S39: 19320 | T39: =S39*0.16 -> 3091.2 | U39: =S39+T39 -> 22411.2 | V39: =(S39-R39)/R39 -> -0.13800027 | W39: =(IF(B39="",(S39*(1-$W$1)),(IF(B39=1,(S39*(1-$W$1)),(IF(B39=2,(S39*(1-$W$1)),(IF(B39=3,(S39*(1-$W$1)),(IF(B39=4,(S39*(1)))))))))))) -> 18354 | X39: =W39*0.16 -> 2936.64 | Y39: =W39+X39 -> 21290.64 | Z39: =(IF(B39="",(S39*(1-$Z$1)),(IF(B39=1,(S39*(1-$Z$1)),(IF(B39=2,(S39*(1-$Z$1)),(IF(B39=3,(S39*(1-$Z$1)),(IF(B39=4,(S39*(1)))))))))))) -> 17388 | AA39: =Z39*0.16 -> 2782.08 | AB39: =Z39+AA39 -> 20170.08 | AC39: =(IF(B39="",(S39*(1-$AC$1)),(IF(B39=1,(S39*(1-$AC$1)),(IF(B39=2,(S39*(1-0.15)),(IF(B39=3,(S39*(1-0.1)),(IF(B39=4,(S39*(1)))))))))))) -> 17388 | AD39: =AC39*0.16 -> 2782.08 | AE39: =AC39+AD39 -> 20170.08 | AF39: =(IF(B39="",(S39*(1-$AF$1)),(IF(B39=1,(S39*(1-$AF$1)),(IF(B39=2,(S39*(1-0.15)),(IF(B39=3,(S39*(1-0.1)),(IF(B39=4,(S39*(1)))))))))))) -> 17388 | AG39: =AF39*0.16 -> 2782.08 | AH39: =AF39+AG39 -> 20170.08 | AI39: =(IF(B39="",(S39*(1-$AI$1)),(IF(B39=1,(S39*(1-$AI$1)),(IF(B39=2,(S39*(1-0.15)),(IF(B39=3,(S39*(1-0.1)),(IF(B39=4,(S39*(1)))))))))))) -> 17388 | AJ39: =AI39*0.16 -> 2782.08 | AK39: =AI39+AJ39 -> 20170.08 | AL39: =IFERROR(__xludf.DUMMYFUNCTION("""COMPUTED_VALUE"""),1.0) -> 1 | AN39: =IFERROR(__xludf.DUMMYFUNCTION("""COMPUTED_VALUE""")," P") -> P | AO39: =IFERROR(__xludf.DUMMYFUNCTION("""COMPUTED_VALUE""")," AS03") -> AS03 | AP39: =IFERROR(__xludf.DUMMYFUNCTION("""COMPUTED_VALUE""")," PZA") -> PZA | AQ39: =IFERROR(__xludf.DUMMYFUNCTION("""COMPUTED_VALUE""")," REF") -> REF | AR39: =IFERROR(__xludf.DUMMYFUNCTION("""COMPUTED_VALUE""")," ASPA DE ALUMINIO DÚPLEX") -> ASPA DE ALUMINIO DÚPLEX | AS39: =IFERROR(__xludf.DUMMYFUNCTION("""COMPUTED_VALUE""")," ASPA DE ALUMINIO DUPLEX") -> ASPA DE ALUMINIO DUPLEX | AT39: =IFERROR(__xludf.DUMMYFUNCTION("""COMPUTED_VALUE"""),23.0) -> 23 | AY39: =IFERROR(__xludf.DUMMYFUNCTION("""COMPUTED_VALUE"""),772.0) -> 772 | AZ39: =IFERROR(__xludf.DUMMYFUNCTION("""COMPUTED_VALUE"""),833.0) -> 833 | BA39: =IFERROR(__xludf.DUMMYFUNCTION("""COMPUTED_VALUE"""),899.6400000000001) -> 899.64 | BB39: =IFERROR(__xludf.DUMMYFUNCTION("""COMPUTED_VALUE"""),899.6400000000001) -> 899.64 | BC39: =IFERROR(__xludf.DUMMYFUNCTION("""COMPUTED_VALUE"""),1002.0) -> 1002 | BD39: =IFERROR(__xludf.DUMMYFUNCTION("""COMPUTED_VALUE"""),1052.0) -> 1052 | BE39: =IFERROR(__xludf.DUMMYFUNCTION("""COMPUTED_VALUE"""),168.32) -> 168.32 | BF39: =IFERROR(__xludf.DUMMYFUNCTION("""COMPUTED_VALUE"""),1220.32) -> 1220.32 | BG39: =IFERROR(__xludf.DUMMYFUNCTION("""COMPUTED_VALUE"""),0.0499001996007984) -> 0.0499002 | BH39: =IFERROR(__xludf.DUMMYFUNCTION("""COMPUTED_VALUE"""),999.4) -> 999.4 | BI39: =IFERROR(__xludf.DUMMYFUNCTION("""COMPUTED_VALUE"""),159.904) -> 159.904 | BJ39: =IFERROR(__xludf.DUMMYFUNCTION("""COMPUTED_VALUE"""),1159.304) -> 1159.304 | BK39: =IFERROR(__xludf.DUMMYFUNCTION("""COMPUTED_VALUE"""),946.8000000000001) -> 946.8 | BL39: =IFERROR(__xludf.DUMMYFUNCTION("""COMPUTED_VALUE"""),151.48800000000003) -> 151.488 | BM39: =IFERROR(__xludf.DUMMYFUNCTION("""COMPUTED_VALUE"""),1098.288) -> 1098.288 | BN39: =IFERROR(__xludf.DUMMYFUNCTION("""COMPUTED_VALUE"""),894.1999999999999) -> 894.2 | BO39: =IFERROR(__xludf.DUMMYFUNCTION("""COMPUTED_VALUE"""),143.072) -> 143.072 | BP39: =IFERROR(__xludf.DUMMYFUNCTION("""COMPUTED_VALUE"""),1037.272) -> 1037.272 | BQ39: =IFERROR(__xludf.DUMMYFUNCTION("""COMPUTED_VALUE"""),873.16) -> 873.16 | BR39: =IFERROR(__xludf.DUMMYFUNCTION("""COMPUTED_VALUE"""),139.7056) -> 139.7056 | BS39: =IFERROR(__xludf.DUMMYFUNCTION("""COMPUTED_VALUE"""),1012.8656) -> 1012.8656 | BT39: =IFERROR(__xludf.DUMMYFUNCTION("""COMPUTED_VALUE"""),841.6) -> 841.6 | BU39: =IFERROR(__xludf.DUMMYFUNCTION("""COMPUTED_VALUE"""),134.656) -> 134.656 | BV39: =IFERROR(__xludf.DUMMYFUNCTION("""COMPUTED_VALUE"""),976.2560000000001) -> 976.256
B40: 3 | C40: E | D40: MG131 | E40: PZA | F40: TGA | G40: AMASADORA DE 25 KG. CON PALETAS FUNDIDAS Y FLECHA EN ACERO INOX. T-304 G.A. SIN ESQUINAS | H40: AMASADORA 25KG PAL FUND FLE INOX SIN ESQ | I40: =IF(D40="","",LEN(H40)) -> 40 | O40: 21517 | P40: 23238.36 | Q40: 23238.36 | R40: 25620 | S40: 22120 | T40: =S40*0.16 -> 3539.2 | U40: =S40+T40 -> 25659.2 | V40: =(S40-R40)/R40 -> -0.13661202 | W40: =(IF(B40="",(S40*(1-$W$1)),(IF(B40=1,(S40*(1-$W$1)),(IF(B40=2,(S40*(1-$W$1)),(IF(B40=3,(S40*(1-$W$1)),(IF(B40=4,(S40*(1)))))))))))) -> 21014 | X40: =W40*0.16 -> 3362.24 | Y40: =W40+X40 -> 24376.24 | Z40: =(IF(B40="",(S40*(1-$Z$1)),(IF(B40=1,(S40*(1-$Z$1)),(IF(B40=2,(S40*(1-$Z$1)),(IF(B40=3,(S40*(1-$Z$1)),(IF(B40=4,(S40*(1)))))))))))) -> 19908 | AA40: =Z40*0.16 -> 3185.28 | AB40: =Z40+AA40 -> 23093.28 | AC40: =(IF(B40="",(S40*(1-$AC$1)),(IF(B40=1,(S40*(1-$AC$1)),(IF(B40=2,(S40*(1-0.15)),(IF(B40=3,(S40*(1-0.1)),(IF(B40=4,(S40*(1)))))))))))) -> 19908 | AD40: =AC40*0.16 -> 3185.28 | AE40: =AC40+AD40 -> 23093.28 | AF40: =(IF(B40="",(S40*(1-$AF$1)),(IF(B40=1,(S40*(1-$AF$1)),(IF(B40=2,(S40*(1-0.15)),(IF(B40=3,(S40*(1-0.1)),(IF(B40=4,(S40*(1)))))))))))) -> 19908 | AG40: =AF40*0.16 -> 3185.28 | AH40: =AF40+AG40 -> 23093.28 | AI40: =(IF(B40="",(S40*(1-$AI$1)),(IF(B40=1,(S40*(1-$AI$1)),(IF(B40=2,(S40*(1-0.15)),(IF(B40=3,(S40*(1-0.1)),(IF(B40=4,(S40*(1)))))))))))) -> 19908 | AJ40: =AI40*0.16 -> 3185.28 | AK40: =AI40+AJ40 -> 23093.28 | AL40: =IFERROR(__xludf.DUMMYFUNCTION("""COMPUTED_VALUE"""),1.0) -> 1 | AN40: =IFERROR(__xludf.DUMMYFUNCTION("""COMPUTED_VALUE""")," P") -> P | AO40: =IFERROR(__xludf.DUMMYFUNCTION("""COMPUTED_VALUE""")," AS04") -> AS04 | AP40: =IFERROR(__xludf.DUMMYFUNCTION("""COMPUTED_VALUE""")," PZA") -> PZA | AQ40: =IFERROR(__xludf.DUMMYFUNCTION("""COMPUTED_VALUE""")," REF") -> REF | AR40: =IFERROR(__xludf.DUMMYFUNCTION("""COMPUTED_VALUE""")," ASPA DE ALUMINIO PARA ARMAR SINFÍN CHICO") -> ASPA DE ALUMINIO PARA ARMAR SINFÍN CHICO | AS40: =IFERROR(__xludf.DUMMYFUNCTION("""COMPUTED_VALUE""")," ASPA DE ALUMINIO PARA ARMAR SINFIN CHICO") -> ASPA DE ALUMINIO PARA ARMAR SINFIN CHICO | AT40: =IFERROR(__xludf.DUMMYFUNCTION("""COMPUTED_VALUE"""),40.0) -> 40 | AY40: =IFERROR(__xludf.DUMMYFUNCTION("""COMPUTED_VALUE"""),821.0) -> 821 | AZ40: =IFERROR(__xludf.DUMMYFUNCTION("""COMPUTED_VALUE"""),886.0) -> 886 | BA40: =IFERROR(__xludf.DUMMYFUNCTION("""COMPUTED_VALUE"""),956.8800000000001) -> 956.88 | BB40: =IFERROR(__xludf.DUMMYFUNCTION("""COMPUTED_VALUE"""),956.8800000000001) -> 956.88 | BC40: =IFERROR(__xludf.DUMMYFUNCTION("""COMPUTED_VALUE"""),1066.0) -> 1066 | BD40: =IFERROR(__xludf.DUMMYFUNCTION("""COMPUTED_VALUE"""),1119.0) -> 1119 | BE40: =IFERROR(__xludf.DUMMYFUNCTION("""COMPUTED_VALUE"""),179.04) -> 179.04 | BF40: =IFERROR(__xludf.DUMMYFUNCTION("""COMPUTED_VALUE"""),1298.04) -> 1298.04 | BG40: =IFERROR(__xludf.DUMMYFUNCTION("""COMPUTED_VALUE"""),0.04971857410881801) -> 0.049718574 | BH40: =IFERROR(__xludf.DUMMYFUNCTION("""COMPUTED_VALUE"""),1063.05) -> 1063.05 | BI40: =IFERROR(__xludf.DUMMYFUNCTION("""COMPUTED_VALUE"""),170.088) -> 170.088 | BJ40: =IFERROR(__xludf.DUMMYFUNCTION("""COMPUTED_VALUE"""),1233.138) -> 1233.138 | BK40: =IFERROR(__xludf.DUMMYFUNCTION("""COMPUTED_VALUE"""),1007.1) -> 1007.1 | BL40: =IFERROR(__xludf.DUMMYFUNCTION("""COMPUTED_VALUE"""),161.136) -> 161.136 | BM40: =IFERROR(__xludf.DUMMYFUNCTION("""COMPUTED_VALUE"""),1168.236) -> 1168.236 | BN40: =IFERROR(__xludf.DUMMYFUNCTION("""COMPUTED_VALUE"""),951.15) -> 951.15 | BO40: =IFERROR(__xludf.DUMMYFUNCTION("""COMPUTED_VALUE"""),152.184) -> 152.184 | BP40: =IFERROR(__xludf.DUMMYFUNCTION("""COMPUTED_VALUE"""),1103.334) -> 1103.334 | BQ40: =IFERROR(__xludf.DUMMYFUNCTION("""COMPUTED_VALUE"""),928.77) -> 928.77 | BR40: =IFERROR(__xludf.DUMMYFUNCTION("""COMPUTED_VALUE"""),148.6032) -> 148.6032 | BS40: =IFERROR(__xludf.DUMMYFUNCTION("""COMPUTED_VALUE"""),1077.3732) -> 1077.3732 | BT40: =IFERROR(__xludf.DUMMYFUNCTION("""COMPUTED_VALUE"""),895.2) -> 895.2 | BU40: =IFERROR(__xludf.DUMMYFUNCTION("""COMPUTED_VALUE"""),143.232) -> 143.232 | BV40: =IFERROR(__xludf.DUMMYFUNCTION("""COMPUTED_VALUE"""),1038.432) -> 1038.432
B41: 3 | C41: E | D41: MM01 | E41: PZA | F41: TNO | G41: AMASADORA DE 25 KG. EN ACERO INOX. T-430 | I41: =IF(D41="","",LEN(H41)) -> 0 | O41: 12775 | P41: 13797 | Q41: 13797 | R41: 15212 | S41: 15973 | T41: =S41*0.16 -> 2555.68 | U41: =S41+T41 -> 18528.68 | V41: =(S41-R41)/R41 -> 0.050026295 | W41: =(IF(B41="",(S41*(1-$W$1)),(IF(B41=1,(S41*(1-$W$1)),(IF(B41=2,(S41*(1-$W$1)),(IF(B41=3,(S41*(1-$W$1)),(IF(B41=4,(S41*(1)))))))))))) -> 15174.35 | X41: =W41*0.16 -> 2427.896 | Y41: =W41+X41 -> 17602.246 | Z41: =(IF(B41="",(S41*(1-$Z$1)),(IF(B41=1,(S41*(1-$Z$1)),(IF(B41=2,(S41*(1-$Z$1)),(IF(B41=3,(S41*(1-$Z$1)),(IF(B41=4,(S41*(1)))))))))))) -> 14375.7 | AA41: =Z41*0.16 -> 2300.112 | AB41: =Z41+AA41 -> 16675.812 | AC41: =(IF(B41="",(S41*(1-$AC$1)),(IF(B41=1,(S41*(1-$AC$1)),(IF(B41=2,(S41*(1-0.15)),(IF(B41=3,(S41*(1-0.1)),(IF(B41=4,(S41*(1)))))))))))) -> 14375.7 | AD41: =AC41*0.16 -> 2300.112 | AE41: =AC41+AD41 -> 16675.812 | AF41: =(IF(B41="",(S41*(1-$AF$1)),(IF(B41=1,(S41*(1-$AF$1)),(IF(B41=2,(S41*(1-0.15)),(IF(B41=3,(S41*(1-0.1)),(IF(B41=4,(S41*(1)))))))))))) -> 14375.7 | AG41: =AF41*0.16 -> 2300.112 | AH41: =AF41+AG41 -> 16675.812 | AI41: =(IF(B41="",(S41*(1-$AI$1)),(IF(B41=1,(S41*(1-$AI$1)),(IF(B41=2,(S41*(1-0.15)),(IF(B41=3,(S41*(1-0.1)),(IF(B41=4,(S41*(1)))))))))))) -> 14375.7 | AJ41: =AI41*0.16 -> 2300.112 | AK41: =AI41+AJ41 -> 16675.812 | AL41: =IFERROR(__xludf.DUMMYFUNCTION("""COMPUTED_VALUE"""),1.0) -> 1 | AN41: =IFERROR(__xludf.DUMMYFUNCTION("""COMPUTED_VALUE""")," P") -> P | AO41: =IFERROR(__xludf.DUMMYFUNCTION("""COMPUTED_VALUE""")," AS05") -> AS05 | AP41: =IFERROR(__xludf.DUMMYFUNCTION("""COMPUTED_VALUE""")," PZA") -> PZA | AQ41: =IFERROR(__xludf.DUMMYFUNCTION("""COMPUTED_VALUE""")," REF") -> REF | AR41: =IFERROR(__xludf.DUMMYFUNCTION("""COMPUTED_VALUE""")," ASPA DE ALUMINIO SENCILLA") -> ASPA DE ALUMINIO SENCILLA | AS41: =IFERROR(__xludf.DUMMYFUNCTION("""COMPUTED_VALUE""")," ASPA DE ALUMINIO SENCILLA") -> ASPA DE ALUMINIO SENCILLA | AT41: =IFERROR(__xludf.DUMMYFUNCTION("""COMPUTED_VALUE"""),25.0) -> 25 | AY41: =IFERROR(__xludf.DUMMYFUNCTION("""COMPUTED_VALUE"""),590.0) -> 590 | AZ41: =IFERROR(__xludf.DUMMYFUNCTION("""COMPUTED_VALUE"""),637.0) -> 637 | BA41: =IFERROR(__xludf.DUMMYFUNCTION("""COMPUTED_VALUE"""),687.96) -> 687.96 | BB41: =IFERROR(__xludf.DUMMYFUNCTION("""COMPUTED_VALUE"""),687.96) -> 687.96 | BC41: =IFERROR(__xludf.DUMMYFUNCTION("""COMPUTED_VALUE"""),767.0) -> 767 | BD41: =IFERROR(__xludf.DUMMYFUNCTION("""COMPUTED_VALUE"""),805.0) -> 805 | BE41: =IFERROR(__xludf.DUMMYFUNCTION("""COMPUTED_VALUE"""),128.8) -> 128.8 | BF41: =IFERROR(__xludf.DUMMYFUNCTION("""COMPUTED_VALUE"""),933.8) -> 933.8 | BG41: =IFERROR(__xludf.DUMMYFUNCTION("""COMPUTED_VALUE"""),0.04954367666232073) -> 0.049543677 | BH41: =IFERROR(__xludf.DUMMYFUNCTION("""COMPUTED_VALUE"""),764.75) -> 764.75 | BI41: =IFERROR(__xludf.DUMMYFUNCTION("""COMPUTED_VALUE"""),122.36) -> 122.36 | BJ41: =IFERROR(__xludf.DUMMYFUNCTION("""COMPUTED_VALUE"""),887.11) -> 887.11 | BK41: =IFERROR(__xludf.DUMMYFUNCTION("""COMPUTED_VALUE"""),724.5) -> 724.5 | BL41: =IFERROR(__xludf.DUMMYFUNCTION("""COMPUTED_VALUE"""),115.92) -> 115.92 | BM41: =IFERROR(__xludf.DUMMYFUNCTION("""COMPUTED_VALUE"""),840.42) -> 840.42 | BN41: =IFERROR(__xludf.DUMMYFUNCTION("""COMPUTED_VALUE"""),684.25) -> 684.25 | BO41: =IFERROR(__xludf.DUMMYFUNCTION("""COMPUTED_VALUE"""),109.48) -> 109.48 | BP41: =IFERROR(__xludf.DUMMYFUNCTION("""COMPUTED_VALUE"""),793.73) -> 793.73 | BQ41: =IFERROR(__xludf.DUMMYFUNCTION("""COMPUTED_VALUE"""),668.15) -> 668.15 | BR41: =IFERROR(__xludf.DUMMYFUNCTION("""COMPUTED_VALUE"""),106.904) -> 106.904 | BS41: =IFERROR(__xludf.DUMMYFUNCTION("""COMPUTED_VALUE"""),775.054) -> 775.054 | BT41: =IFERROR(__xludf.DUMMYFUNCTION("""COMPUTED_VALUE"""),644.0) -> 644 | BU41: =IFERROR(__xludf.DUMMYFUNCTION("""COMPUTED_VALUE"""),103.04) -> 103.04 | BV41: =IFERROR(__xludf.DUMMYFUNCTION("""COMPUTED_VALUE"""),747.04) -> 747.04
B42: 3 | C42: E | D42: MG130 | E42: PZA | F42: TGA | G42: AMASADORA DE 50 KG. CON ASPA FLECHA EN ACERO INOX. T-304 PARA TAMAL G.A. | H42: AMASADORA 50KG C/ASPA FLE INOX P/TAMAL | I42: =IF(D42="","",LEN(H42)) -> 38 | O42: 30116 | P42: 32525.28 | Q42: 32525.28 | R42: 35859 | S42: 37652 | T42: =S42*0.16 -> 6024.32 | U42: =S42+T42 -> 43676.32 | V42: =(S42-R42)/R42 -> 0.050001394 | W42: =(IF(B42="",(S42*(1-$W$1)),(IF(B42=1,(S42*(1-$W$1)),(IF(B42=2,(S42*(1-$W$1)),(IF(B42=3,(S42*(1-$W$1)),(IF(B42=4,(S42*(1)))))))))))) -> 35769.4 | X42: =W42*0.16 -> 5723.104 | Y42: =W42+X42 -> 41492.504 | Z42: =(IF(B42="",(S42*(1-$Z$1)),(IF(B42=1,(S42*(1-$Z$1)),(IF(B42=2,(S42*(1-$Z$1)),(IF(B42=3,(S42*(1-$Z$1)),(IF(B42=4,(S42*(1)))))))))))) -> 33886.8 | AA42: =Z42*0.16 -> 5421.888 | AB42: =Z42+AA42 -> 39308.688 | AC42: =(IF(B42="",(S42*(1-$AC$1)),(IF(B42=1,(S42*(1-$AC$1)),(IF(B42=2,(S42*(1-0.15)),(IF(B42=3,(S42*(1-0.1)),(IF(B42=4,(S42*(1)))))))))))) -> 33886.8 | AD42: =AC42*0.16 -> 5421.888 | AE42: =AC42+AD42 -> 39308.688 | AF42: =(IF(B42="",(S42*(1-$AF$1)),(IF(B42=1,(S42*(1-$AF$1)),(IF(B42=2,(S42*(1-0.15)),(IF(B42=3,(S42*(1-0.1)),(IF(B42=4,(S42*(1)))))))))))) -> 33886.8 | AG42: =AF42*0.16 -> 5421.888 | AH42: =AF42+AG42 -> 39308.688 | AI42: =(IF(B42="",(S42*(1-$AI$1)),(IF(B42=1,(S42*(1-$AI$1)),(IF(B42=2,(S42*(1-0.15)),(IF(B42=3,(S42*(1-0.1)),(IF(B42=4,(S42*(1)))))))))))) -> 33886.8 | AJ42: =AI42*0.16 -> 5421.888 | AK42: =AI42+AJ42 -> 39308.688 | AL42: =IFERROR(__xludf.DUMMYFUNCTION("""COMPUTED_VALUE"""),1.0) -> 1 | AN42: =IFERROR(__xludf.DUMMYFUNCTION("""COMPUTED_VALUE""")," C") -> C | AO42: =IFERROR(__xludf.DUMMYFUNCTION("""COMPUTED_VALUE""")," BA62") -> BA62 | AP42: =IFERROR(__xludf.DUMMYFUNCTION("""COMPUTED_VALUE""")," PZA") -> PZA | AQ42: =IFERROR(__xludf.DUMMYFUNCTION("""COMPUTED_VALUE""")," REF") -> REF | AR42: =IFERROR(__xludf.DUMMYFUNCTION("""COMPUTED_VALUE""")," BALERO 15520 MULTIMARCA") -> BALERO 15520 MULTIMARCA | AS42: =IFERROR(__xludf.DUMMYFUNCTION("""COMPUTED_VALUE""")," BALERO 15520 MULTIMARCA") -> BALERO 15520 MULTIMARCA | AT42: =IFERROR(__xludf.DUMMYFUNCTION("""COMPUTED_VALUE"""),23.0) -> 23 | AY42: =IFERROR(__xludf.DUMMYFUNCTION("""COMPUTED_VALUE"""),74.0) -> 74 | AZ42: =IFERROR(__xludf.DUMMYFUNCTION("""COMPUTED_VALUE"""),79.0) -> 79 | BA42: =IFERROR(__xludf.DUMMYFUNCTION("""COMPUTED_VALUE"""),85.32000000000001) -> 85.32 | BB42: =IFERROR(__xludf.DUMMYFUNCTION("""COMPUTED_VALUE"""),85.32000000000001) -> 85.32 | BC42: =IFERROR(__xludf.DUMMYFUNCTION("""COMPUTED_VALUE"""),90.0) -> 90 | BD42: =IFERROR(__xludf.DUMMYFUNCTION("""COMPUTED_VALUE"""),95.0) -> 95 | BE42: =IFERROR(__xludf.DUMMYFUNCTION("""COMPUTED_VALUE"""),15.200000000000001) -> 15.2 | BF42: =IFERROR(__xludf.DUMMYFUNCTION("""COMPUTED_VALUE"""),110.2) -> 110.2 | BG42: =IFERROR(__xludf.DUMMYFUNCTION("""COMPUTED_VALUE"""),0.05555555555555555) -> 0.055555556 | BH42: =IFERROR(__xludf.DUMMYFUNCTION("""COMPUTED_VALUE"""),90.25) -> 90.25 | BI42: =IFERROR(__xludf.DUMMYFUNCTION("""COMPUTED_VALUE"""),14.44) -> 14.44 | BJ42: =IFERROR(__xludf.DUMMYFUNCTION("""COMPUTED_VALUE"""),104.69) -> 104.69 | BK42: =IFERROR(__xludf.DUMMYFUNCTION("""COMPUTED_VALUE"""),85.5) -> 85.5 | BL42: =IFERROR(__xludf.DUMMYFUNCTION("""COMPUTED_VALUE"""),13.68) -> 13.68 | BM42: =IFERROR(__xludf.DUMMYFUNCTION("""COMPUTED_VALUE"""),99.18) -> 99.18 | BN42: =IFERROR(__xludf.DUMMYFUNCTION("""COMPUTED_VALUE"""),80.75) -> 80.75 | BO42: =IFERROR(__xludf.DUMMYFUNCTION("""COMPUTED_VALUE"""),12.92) -> 12.92 | BP42: =IFERROR(__xludf.DUMMYFUNCTION("""COMPUTED_VALUE"""),93.67) -> 93.67 | BQ42: =IFERROR(__xludf.DUMMYFUNCTION("""COMPUTED_VALUE"""),78.85) -> 78.85 | BR42: =IFERROR(__xludf.DUMMYFUNCTION("""COMPUTED_VALUE"""),12.616) -> 12.616 | BS42: =IFERROR(__xludf.DUMMYFUNCTION("""COMPUTED_VALUE"""),91.466) -> 91.466 | BT42: =IFERROR(__xludf.DUMMYFUNCTION("""COMPUTED_VALUE"""),76.0) -> 76 | BU42: =IFERROR(__xludf.DUMMYFUNCTION("""COMPUTED_VALUE"""),12.16) -> 12.16 | BV42: =IFERROR(__xludf.DUMMYFUNCTION("""COMPUTED_VALUE"""),88.16) -> 88.16
B43: 3 | C43: E | D43: MG124 | E43: PZA | F43: TGA | G43: AMASADORA DE 50 KG. CON ASPA, EN ACERO INOX. T-304 PARA TAMAL G.A., ACABADO HIGIÉNICO | H43: AMASADORA 50KG C/ASPA INOX TAMAL S/ESQ | I43: =IF(D43="","",LEN(H43)) -> 38 | O43: 36839 | P43: 39786.12 | Q43: 39786.12 | R43: 43864 | S43: 46057 | T43: =S43*0.16 -> 7369.12 | U43: =S43+T43 -> 53426.12 | V43: =(S43-R43)/R43 -> 0.04999544 | W43: =(IF(B43="",(S43*(1-$W$1)),(IF(B43=1,(S43*(1-$W$1)),(IF(B43=2,(S43*(1-$W$1)),(IF(B43=3,(S43*(1-$W$1)),(IF(B43=4,(S43*(1)))))))))))) -> 43754.15 | X43: =W43*0.16 -> 7000.664 | Y43: =W43+X43 -> 50754.814 | Z43: =(IF(B43="",(S43*(1-$Z$1)),(IF(B43=1,(S43*(1-$Z$1)),(IF(B43=2,(S43*(1-$Z$1)),(IF(B43=3,(S43*(1-$Z$1)),(IF(B43=4,(S43*(1)))))))))))) -> 41451.3 | AA43: =Z43*0.16 -> 6632.208 | AB43: =Z43+AA43 -> 48083.508 | AC43: =(IF(B43="",(S43*(1-$AC$1)),(IF(B43=1,(S43*(1-$AC$1)),(IF(B43=2,(S43*(1-0.15)),(IF(B43=3,(S43*(1-0.1)),(IF(B43=4,(S43*(1)))))))))))) -> 41451.3 | AD43: =AC43*0.16 -> 6632.208 | AE43: =AC43+AD43 -> 48083.508 | AF43: =(IF(B43="",(S43*(1-$AF$1)),(IF(B43=1,(S43*(1-$AF$1)),(IF(B43=2,(S43*(1-0.15)),(IF(B43=3,(S43*(1-0.1)),(IF(B43=4,(S43*(1)))))))))))) -> 41451.3 | AG43: =AF43*0.16 -> 6632.208 | AH43: =AF43+AG43 -> 48083.508 | AI43: =(IF(B43="",(S43*(1-$AI$1)),(IF(B43=1,(S43*(1-$AI$1)),(IF(B43=2,(S43*(1-0.15)),(IF(B43=3,(S43*(1-0.1)),(IF(B43=4,(S43*(1)))))))))))) -> 41451.3 | AJ43: =AI43*0.16 -> 6632.208 | AK43: =AI43+AJ43 -> 48083.508 | AL43: =IFERROR(__xludf.DUMMYFUNCTION("""COMPUTED_VALUE"""),1.0) -> 1 | AN43: =IFERROR(__xludf.DUMMYFUNCTION("""COMPUTED_VALUE""")," C") -> C | AO43: =IFERROR(__xludf.DUMMYFUNCTION("""COMPUTED_VALUE""")," BA20") -> BA20 | AP43: =IFERROR(__xludf.DUMMYFUNCTION("""COMPUTED_VALUE""")," PZA") -> PZA | AQ43: =IFERROR(__xludf.DUMMYFUNCTION("""COMPUTED_VALUE""")," REF") -> REF | AR43: =IFERROR(__xludf.DUMMYFUNCTION("""COMPUTED_VALUE""")," BALERO 15580 MULTIMARCA") -> BALERO 15580 MULTIMARCA | AS43: =IFERROR(__xludf.DUMMYFUNCTION("""COMPUTED_VALUE""")," BALERO 15580 MULTIMARCA") -> BALERO 15580 MULTIMARCA | AT43: =IFERROR(__xludf.DUMMYFUNCTION("""COMPUTED_VALUE"""),23.0) -> 23 | AY43: =IFERROR(__xludf.DUMMYFUNCTION("""COMPUTED_VALUE"""),130.0) -> 130 | AZ43: =IFERROR(__xludf.DUMMYFUNCTION("""COMPUTED_VALUE"""),140.0) -> 140 | BA43: =IFERROR(__xludf.DUMMYFUNCTION("""COMPUTED_VALUE"""),151.20000000000002) -> 151.2 | BB43: =IFERROR(__xludf.DUMMYFUNCTION("""COMPUTED_VALUE"""),151.20000000000002) -> 151.2 | BC43: =IFERROR(__xludf.DUMMYFUNCTION("""COMPUTED_VALUE"""),174.0) -> 174 | BD43: =IFERROR(__xludf.DUMMYFUNCTION("""COMPUTED_VALUE"""),183.0) -> 183 | BE43: =IFERROR(__xludf.DUMMYFUNCTION("""COMPUTED_VALUE"""),29.28) -> 29.28 | BF43: =IFERROR(__xludf.DUMMYFUNCTION("""COMPUTED_VALUE"""),212.28) -> 212.28 | BG43: =IFERROR(__xludf.DUMMYFUNCTION("""COMPUTED_VALUE"""),0.05172413793103448) -> 0.051724138 | BH43: =IFERROR(__xludf.DUMMYFUNCTION("""COMPUTED_VALUE"""),173.85) -> 173.85 | BI43: =IFERROR(__xludf.DUMMYFUNCTION("""COMPUTED_VALUE"""),27.816) -> 27.816 | BJ43: =IFERROR(__xludf.DUMMYFUNCTION("""COMPUTED_VALUE"""),201.666) -> 201.666 | BK43: =IFERROR(__xludf.DUMMYFUNCTION("""COMPUTED_VALUE"""),164.70000000000002) -> 164.7 | BL43: =IFERROR(__xludf.DUMMYFUNCTION("""COMPUTED_VALUE"""),26.352000000000004) -> 26.352 | BM43: =IFERROR(__xludf.DUMMYFUNCTION("""COMPUTED_VALUE"""),191.05200000000002) -> 191.052 | BN43: =IFERROR(__xludf.DUMMYFUNCTION("""COMPUTED_VALUE"""),155.54999999999998) -> 155.55 | BO43: =IFERROR(__xludf.DUMMYFUNCTION("""COMPUTED_VALUE"""),24.887999999999998) -> 24.888 | BP43: =IFERROR(__xludf.DUMMYFUNCTION("""COMPUTED_VALUE"""),180.438) -> 180.438 | BQ43: =IFERROR(__xludf.DUMMYFUNCTION("""COMPUTED_VALUE"""),151.89) -> 151.89 | BR43: =IFERROR(__xludf.DUMMYFUNCTION("""COMPUTED_VALUE"""),24.3024) -> 24.3024 | BS43: =IFERROR(__xludf.DUMMYFUNCTION("""COMPUTED_VALUE"""),176.1924) -> 176.1924 | BT43: =IFERROR(__xludf.DUMMYFUNCTION("""COMPUTED_VALUE"""),146.4) -> 146.4 | BU43: =IFERROR(__xludf.DUMMYFUNCTION("""COMPUTED_VALUE"""),23.424000000000003) -> 23.424 | BV43: =IFERROR(__xludf.DUMMYFUNCTION("""COMPUTED_VALUE"""),169.824) -> 169.824
B44: 3 | C44: E | D44: MG101 | E44: PZA | F44: TGA | G44: AMASADORA DE 50 KG. CON PALETAS FUNDIDAS Y FLECHA EN ACERO INOX. T-304 ACABADO HIGIÉNICO G.A., MOTOR TRIFASICO | H44: AMASADORA 50KG PAL FUND FLE INX S/ES TRI | I44: =IF(D44="","",LEN(H44)) -> 40 | O44: 32604 | P44: 35212.32 | Q44: 35212.32 | R44: 38822 | S44: 40763 | T44: =S44*0.16 -> 6522.08 | U44: =S44+T44 -> 47285.08 | V44: =(S44-R44)/R44 -> 0.049997424 | W44: =(IF(B44="",(S44*(1-$W$1)),(IF(B44=1,(S44*(1-$W$1)),(IF(B44=2,(S44*(1-$W$1)),(IF(B44=3,(S44*(1-$W$1)),(IF(B44=4,(S44*(1)))))))))))) -> 38724.85 | X44: =W44*0.16 -> 6195.976 | Y44: =W44+X44 -> 44920.826 | Z44: =(IF(B44="",(S44*(1-$Z$1)),(IF(B44=1,(S44*(1-$Z$1)),(IF(B44=2,(S44*(1-$Z$1)),(IF(B44=3,(S44*(1-$Z$1)),(IF(B44=4,(S44*(1)))))))))))) -> 36686.7 | AA44: =Z44*0.16 -> 5869.872 | AB44: =Z44+AA44 -> 42556.572 | AC44: =(IF(B44="",(S44*(1-$AC$1)),(IF(B44=1,(S44*(1-$AC$1)),(IF(B44=2,(S44*(1-0.15)),(IF(B44=3,(S44*(1-0.1)),(IF(B44=4,(S44*(1)))))))))))) -> 36686.7 | AD44: =AC44*0.16 -> 5869.872 | AE44: =AC44+AD44 -> 42556.572 | AF44: =(IF(B44="",(S44*(1-$AF$1)),(IF(B44=1,(S44*(1-$AF$1)),(IF(B44=2,(S44*(1-0.15)),(IF(B44=3,(S44*(1-0.1)),(IF(B44=4,(S44*(1)))))))))))) -> 36686.7 | AG44: =AF44*0.16 -> 5869.872 | AH44: =AF44+AG44 -> 42556.572 | AI44: =(IF(B44="",(S44*(1-$AI$1)),(IF(B44=1,(S44*(1-$AI$1)),(IF(B44=2,(S44*(1-0.15)),(IF(B44=3,(S44*(1-0.1)),(IF(B44=4,(S44*(1)))))))))))) -> 36686.7 | AJ44: =AI44*0.16 -> 5869.872 | AK44: =AI44+AJ44 -> 42556.572 | AL44: =IFERROR(__xludf.DUMMYFUNCTION("""COMPUTED_VALUE"""),1.0) -> 1 | AN44: =IFERROR(__xludf.DUMMYFUNCTION("""COMPUTED_VALUE""")," C") -> C | AO44: =IFERROR(__xludf.DUMMYFUNCTION("""COMPUTED_VALUE""")," BA61") -> BA61 | AP44: =IFERROR(__xludf.DUMMYFUNCTION("""COMPUTED_VALUE""")," PZA") -> PZA | AQ44: =IFERROR(__xludf.DUMMYFUNCTION("""COMPUTED_VALUE""")," REF") -> REF | AR44: =IFERROR(__xludf.DUMMYFUNCTION("""COMPUTED_VALUE""")," BALERO 15580/20 MULTIMARCA") -> BALERO 15580/20 MULTIMARCA | AS44: =IFERROR(__xludf.DUMMYFUNCTION("""COMPUTED_VALUE""")," BALERO 15580/20 MULTIMARCA") -> BALERO 15580/20 MULTIMARCA | AT44: =IFERROR(__xludf.DUMMYFUNCTION("""COMPUTED_VALUE"""),26.0) -> 26 | AY44: =IFERROR(__xludf.DUMMYFUNCTION("""COMPUTED_VALUE"""),1131.0) -> 1131 | AZ44: =IFERROR(__xludf.DUMMYFUNCTION("""COMPUTED_VALUE"""),1221.0) -> 1221 | BA44: =IFERROR(__xludf.DUMMYFUNCTION("""COMPUTED_VALUE"""),1318.68) -> 1318.68 | BB44: =IFERROR(__xludf.DUMMYFUNCTION("""COMPUTED_VALUE"""),1318.68) -> 1318.68 | BC44: =IFERROR(__xludf.DUMMYFUNCTION("""COMPUTED_VALUE"""),1425.0) -> 1425 | BD44: =IFERROR(__xludf.DUMMYFUNCTION("""COMPUTED_VALUE"""),1496.0) -> 1496 | BE44: =IFERROR(__xludf.DUMMYFUNCTION("""COMPUTED_VALUE"""),239.36) -> 239.36 | BF44: =IFERROR(__xludf.DUMMYFUNCTION("""COMPUTED_VALUE"""),1735.3600000000001) -> 1735.36 | BG44: =IFERROR(__xludf.DUMMYFUNCTION("""COMPUTED_VALUE"""),0.04982456140350877) -> 0.049824561 | BH44: =IFERROR(__xludf.DUMMYFUNCTION("""COMPUTED_VALUE"""),1421.2) -> 1421.2 | BI44: =IFERROR(__xludf.DUMMYFUNCTION("""COMPUTED_VALUE"""),227.39200000000002) -> 227.392 | BJ44: =IFERROR(__xludf.DUMMYFUNCTION("""COMPUTED_VALUE"""),1648.592) -> 1648.592 | BK44: =IFERROR(__xludf.DUMMYFUNCTION("""COMPUTED_VALUE"""),1346.4) -> 1346.4 | BL44: =IFERROR(__xludf.DUMMYFUNCTION("""COMPUTED_VALUE"""),215.424) -> 215.424 | BM44: =IFERROR(__xludf.DUMMYFUNCTION("""COMPUTED_VALUE"""),1561.824) -> 1561.824 | BN44: =IFERROR(__xludf.DUMMYFUNCTION("""COMPUTED_VALUE"""),1271.6) -> 1271.6 | BO44: =IFERROR(__xludf.DUMMYFUNCTION("""COMPUTED_VALUE"""),203.456) -> 203.456 | BP44: =IFERROR(__xludf.DUMMYFUNCTION("""COMPUTED_VALUE"""),1475.0559999999998) -> 1475.056 | BQ44: =IFERROR(__xludf.DUMMYFUNCTION("""COMPUTED_VALUE"""),1241.6799999999998) -> 1241.68 | BR44: =IFERROR(__xludf.DUMMYFUNCTION("""COMPUTED_VALUE"""),198.66879999999998) -> 198.6688 | BS44: =IFERROR(__xludf.DUMMYFUNCTION("""COMPUTED_VALUE"""),1440.3487999999998) -> 1440.3488 | BT44: =IFERROR(__xludf.DUMMYFUNCTION("""COMPUTED_VALUE"""),1196.8) -> 1196.8 | BU44: =IFERROR(__xludf.DUMMYFUNCTION("""COMPUTED_VALUE"""),191.488) -> 191.488 | BV44: =IFERROR(__xludf.DUMMYFUNCTION("""COMPUTED_VALUE"""),1388.288) -> 1388.288
B45: 3 | C45: E | D45: MG02 | E45: PZA | F45: TGA | G45: AMASADORA DE 50 KG. CON PALETAS FUNDIDAS Y FLECHA EN ACERO INOX. T-304 G.A. | H45: AMASADORA 50KG PAL FUND FLE INOX | I45: =IF(D45="","",LEN(H45)) -> 32 | O45: 27379 | P45: 29569.32 | Q45: 29569.32 | R45: 32600 | S45: 28660 | T45: =S45*0.16 -> 4585.6 | U45: =S45+T45 -> 33245.6 | V45: =(S45-R45)/R45 -> -0.1208589 | W45: =(IF(B45="",(S45*(1-$W$1)),(IF(B45=1,(S45*(1-$W$1)),(IF(B45=2,(S45*(1-$W$1)),(IF(B45=3,(S45*(1-$W$1)),(IF(B45=4,(S45*(1)))))))))))) -> 27227 | X45: =W45*0.16 -> 4356.32 | Y45: =W45+X45 -> 31583.32 | Z45: =(IF(B45="",(S45*(1-$Z$1)),(IF(B45=1,(S45*(1-$Z$1)),(IF(B45=2,(S45*(1-$Z$1)),(IF(B45=3,(S45*(1-$Z$1)),(IF(B45=4,(S45*(1)))))))))))) -> 25794 | AA45: =Z45*0.16 -> 4127.04 | AB45: =Z45+AA45 -> 29921.04 | AC45: =(IF(B45="",(S45*(1-$AC$1)),(IF(B45=1,(S45*(1-$AC$1)),(IF(B45=2,(S45*(1-0.15)),(IF(B45=3,(S45*(1-0.1)),(IF(B45=4,(S45*(1)))))))))))) -> 25794 | AD45: =AC45*0.16 -> 4127.04 | AE45: =AC45+AD45 -> 29921.04 | AF45: =(IF(B45="",(S45*(1-$AF$1)),(IF(B45=1,(S45*(1-$AF$1)),(IF(B45=2,(S45*(1-0.15)),(IF(B45=3,(S45*(1-0.1)),(IF(B45=4,(S45*(1)))))))))))) -> 25794 | AG45: =AF45*0.16 -> 4127.04 | AH45: =AF45+AG45 -> 29921.04 | AI45: =(IF(B45="",(S45*(1-$AI$1)),(IF(B45=1,(S45*(1-$AI$1)),(IF(B45=2,(S45*(1-0.15)),(IF(B45=3,(S45*(1-0.1)),(IF(B45=4,(S45*(1)))))))))))) -> 25794 | AJ45: =AI45*0.16 -> 4127.04 | AK45: =AI45+AJ45 -> 29921.04 | AL45: =IFERROR(__xludf.DUMMYFUNCTION("""COMPUTED_VALUE"""),1.0) -> 1 | AN45: =IFERROR(__xludf.DUMMYFUNCTION("""COMPUTED_VALUE""")," C") -> C | AO45: =IFERROR(__xludf.DUMMYFUNCTION("""COMPUTED_VALUE""")," BA03") -> BA03 | AP45: =IFERROR(__xludf.DUMMYFUNCTION("""COMPUTED_VALUE""")," PZA") -> PZA | AQ45: =IFERROR(__xludf.DUMMYFUNCTION("""COMPUTED_VALUE""")," REF") -> REF | AR45: =IFERROR(__xludf.DUMMYFUNCTION("""COMPUTED_VALUE""")," BALERO 30204A ZKL/ZVL") -> BALERO 30204A ZKL/ZVL | AS45: =IFERROR(__xludf.DUMMYFUNCTION("""COMPUTED_VALUE""")," BALERO 30204A ZKL/ZVL") -> BALERO 30204A ZKL/ZVL | AT45: =IFERROR(__xludf.DUMMYFUNCTION("""COMPUTED_VALUE"""),21.0) -> 21 | AZ45: =IFERROR(__xludf.DUMMYFUNCTION("""COMPUTED_VALUE"""),125.0) -> 125 | BA45: =IFERROR(__xludf.DUMMYFUNCTION("""COMPUTED_VALUE"""),135.0) -> 135 | BB45: =IFERROR(__xludf.DUMMYFUNCTION("""COMPUTED_VALUE"""),135.0) -> 135 | BC45: =IFERROR(__xludf.DUMMYFUNCTION("""COMPUTED_VALUE"""),142.0) -> 142 | BD45: =IFERROR(__xludf.DUMMYFUNCTION("""COMPUTED_VALUE"""),149.0) -> 149 | BE45: =IFERROR(__xludf.DUMMYFUNCTION("""COMPUTED_VALUE"""),23.84) -> 23.84 | BF45: =IFERROR(__xludf.DUMMYFUNCTION("""COMPUTED_VALUE"""),172.84) -> 172.84 | BG45: =IFERROR(__xludf.DUMMYFUNCTION("""COMPUTED_VALUE"""),0.04929577464788732) -> 0.049295775 | BH45: =IFERROR(__xludf.DUMMYFUNCTION("""COMPUTED_VALUE"""),141.54999999999998) -> 141.55 | BI45: =IFERROR(__xludf.DUMMYFUNCTION("""COMPUTED_VALUE"""),22.647999999999996) -> 22.648 | BJ45: =IFERROR(__xludf.DUMMYFUNCTION("""COMPUTED_VALUE"""),164.19799999999998) -> 164.198 | BK45: =IFERROR(__xludf.DUMMYFUNCTION("""COMPUTED_VALUE"""),134.1) -> 134.1 | BL45: =IFERROR(__xludf.DUMMYFUNCTION("""COMPUTED_VALUE"""),21.456) -> 21.456 | BM45: =IFERROR(__xludf.DUMMYFUNCTION("""COMPUTED_VALUE"""),155.55599999999998) -> 155.556 | BN45: =IFERROR(__xludf.DUMMYFUNCTION("""COMPUTED_VALUE"""),126.64999999999999) -> 126.65 | BO45: =IFERROR(__xludf.DUMMYFUNCTION("""COMPUTED_VALUE"""),20.264) -> 20.264 | BP45: =IFERROR(__xludf.DUMMYFUNCTION("""COMPUTED_VALUE"""),146.914) -> 146.914 | BQ45: =IFERROR(__xludf.DUMMYFUNCTION("""COMPUTED_VALUE"""),123.66999999999999) -> 123.67 | BR45: =IFERROR(__xludf.DUMMYFUNCTION("""COMPUTED_VALUE"""),19.7872) -> 19.7872 | BS45: =IFERROR(__xludf.DUMMYFUNCTION("""COMPUTED_VALUE"""),143.4572) -> 143.4572 | BT45: =IFERROR(__xludf.DUMMYFUNCTION("""COMPUTED_VALUE"""),119.2) -> 119.2 | BU45: =IFERROR(__xludf.DUMMYFUNCTION("""COMPUTED_VALUE"""),19.072) -> 19.072 | BV45: =IFERROR(__xludf.DUMMYFUNCTION("""COMPUTED_VALUE"""),138.272) -> 138.272
B46: 3 | C46: E | D46: MG04 | E46: PZA | F46: TGA | G46: AMASADORA DE 50 KG. CON PALETAS FUNDIDAS Y FLECHA EN ACERO INOX. T-304 G.A. SIN ESQUINAS MOT MONO | H46: AMASADORA 50KG PAL FUND FLE INX S/ES MON | I46: =IF(D46="","",LEN(H46)) -> 40 | O46: 31197 | P46: 33692.76 | Q46: 33692.76 | R46: 37147 | S46: 32060 | T46: =S46*0.16 -> 5129.6 | U46: =S46+T46 -> 37189.6 | V46: =(S46-R46)/R46 -> -0.13694242 | W46: =(IF(B46="",(S46*(1-$W$1)),(IF(B46=1,(S46*(1-$W$1)),(IF(B46=2,(S46*(1-$W$1)),(IF(B46=3,(S46*(1-$W$1)),(IF(B46=4,(S46*(1)))))))))))) -> 30457 | X46: =W46*0.16 -> 4873.12 | Y46: =W46+X46 -> 35330.12 | Z46: =(IF(B46="",(S46*(1-$Z$1)),(IF(B46=1,(S46*(1-$Z$1)),(IF(B46=2,(S46*(1-$Z$1)),(IF(B46=3,(S46*(1-$Z$1)),(IF(B46=4,(S46*(1)))))))))))) -> 28854 | AA46: =Z46*0.16 -> 4616.64 | AB46: =Z46+AA46 -> 33470.64 | AC46: =(IF(B46="",(S46*(1-$AC$1)),(IF(B46=1,(S46*(1-$AC$1)),(IF(B46=2,(S46*(1-0.15)),(IF(B46=3,(S46*(1-0.1)),(IF(B46=4,(S46*(1)))))))))))) -> 28854 | AD46: =AC46*0.16 -> 4616.64 | AE46: =AC46+AD46 -> 33470.64 | AF46: =(IF(B46="",(S46*(1-$AF$1)),(IF(B46=1,(S46*(1-$AF$1)),(IF(B46=2,(S46*(1-0.15)),(IF(B46=3,(S46*(1-0.1)),(IF(B46=4,(S46*(1)))))))))))) -> 28854 | AG46: =AF46*0.16 -> 4616.64 | AH46: =AF46+AG46 -> 33470.64 | AI46: =(IF(B46="",(S46*(1-$AI$1)),(IF(B46=1,(S46*(1-$AI$1)),(IF(B46=2,(S46*(1-0.15)),(IF(B46=3,(S46*(1-0.1)),(IF(B46=4,(S46*(1)))))))))))) -> 28854 | AJ46: =AI46*0.16 -> 4616.64 | AK46: =AI46+AJ46 -> 33470.64 | AL46: =IFERROR(__xludf.DUMMYFUNCTION("""COMPUTED_VALUE"""),1.0) -> 1 | AN46: =IFERROR(__xludf.DUMMYFUNCTION("""COMPUTED_VALUE""")," C") -> C | AO46: =IFERROR(__xludf.DUMMYFUNCTION("""COMPUTED_VALUE""")," BA21") -> BA21 | AP46: =IFERROR(__xludf.DUMMYFUNCTION("""COMPUTED_VALUE""")," PZA") -> PZA | AQ46: =IFERROR(__xludf.DUMMYFUNCTION("""COMPUTED_VALUE""")," REF") -> REF | AR46: =IFERROR(__xludf.DUMMYFUNCTION("""COMPUTED_VALUE""")," BALERO 30205 ZKL/ZVL") -> BALERO 30205 ZKL/ZVL | AS46: =IFERROR(__xludf.DUMMYFUNCTION("""COMPUTED_VALUE""")," BALERO 30205 ZKL/ZVL") -> BALERO 30205 ZKL/ZVL | AT46: =IFERROR(__xludf.DUMMYFUNCTION("""COMPUTED_VALUE"""),20.0) -> 20 | AY46: =IFERROR(__xludf.DUMMYFUNCTION("""COMPUTED_VALUE"""),155.0) -> 155 | AZ46: =IFERROR(__xludf.DUMMYFUNCTION("""COMPUTED_VALUE"""),167.0) -> 167 | BA46: =IFERROR(__xludf.DUMMYFUNCTION("""COMPUTED_VALUE"""),180.36) -> 180.36 | BB46: =IFERROR(__xludf.DUMMYFUNCTION("""COMPUTED_VALUE"""),180.36) -> 180.36 | BC46: =IFERROR(__xludf.DUMMYFUNCTION("""COMPUTED_VALUE"""),202.0) -> 202 | BD46: =IFERROR(__xludf.DUMMYFUNCTION("""COMPUTED_VALUE"""),212.0) -> 212 | BE46: =IFERROR(__xludf.DUMMYFUNCTION("""COMPUTED_VALUE"""),33.92) -> 33.92 | BF46: =IFERROR(__xludf.DUMMYFUNCTION("""COMPUTED_VALUE"""),245.92000000000002) -> 245.92 | BG46: =IFERROR(__xludf.DUMMYFUNCTION("""COMPUTED_VALUE"""),0.04950495049504951) -> 0.04950495 | BH46: =IFERROR(__xludf.DUMMYFUNCTION("""COMPUTED_VALUE"""),201.39999999999998) -> 201.4 | BI46: =IFERROR(__xludf.DUMMYFUNCTION("""COMPUTED_VALUE"""),32.224) -> 32.224 | BJ46: =IFERROR(__xludf.DUMMYFUNCTION("""COMPUTED_VALUE"""),233.62399999999997) -> 233.624 | BK46: =IFERROR(__xludf.DUMMYFUNCTION("""COMPUTED_VALUE"""),190.8) -> 190.8 | BL46: =IFERROR(__xludf.DUMMYFUNCTION("""COMPUTED_VALUE"""),30.528000000000002) -> 30.528 | BM46: =IFERROR(__xludf.DUMMYFUNCTION("""COMPUTED_VALUE"""),221.328) -> 221.328 | BN46: =IFERROR(__xludf.DUMMYFUNCTION("""COMPUTED_VALUE"""),180.2) -> 180.2 | BO46: =IFERROR(__xludf.DUMMYFUNCTION("""COMPUTED_VALUE"""),28.831999999999997) -> 28.832 | BP46: =IFERROR(__xludf.DUMMYFUNCTION("""COMPUTED_VALUE"""),209.03199999999998) -> 209.032 | BQ46: =IFERROR(__xludf.DUMMYFUNCTION("""COMPUTED_VALUE"""),175.95999999999998) -> 175.96 | BR46: =IFERROR(__xludf.DUMMYFUNCTION("""COMPUTED_VALUE"""),28.153599999999997) -> 28.1536 | BS46: =IFERROR(__xludf.DUMMYFUNCTION("""COMPUTED_VALUE"""),204.11359999999996) -> 204.1136 | BT46: =IFERROR(__xludf.DUMMYFUNCTION("""COMPUTED_VALUE"""),169.60000000000002) -> 169.6 | BU46: =IFERROR(__xludf.DUMMYFUNCTION("""COMPUTED_VALUE"""),27.136000000000003) -> 27.136 | BV46: =IFERROR(__xludf.DUMMYFUNCTION("""COMPUTED_VALUE"""),196.73600000000002) -> 196.736
B47: 3 | C47: E | D47: MM02 | E47: PZA | F47: TNO | G47: AMASADORA DE 50 KG. EN ACERO INOX. T-430, MOTOR MONOFÁSICO | I47: =IF(D47="","",LEN(H47)) -> 0 | O47: 17036 | P47: 18398.88 | Q47: 18398.88 | R47: 20285 | S47: 21299 | T47: =S47*0.16 -> 3407.84 | U47: =S47+T47 -> 24706.84 | V47: =(S47-R47)/R47 -> 0.049987676 | W47: =(IF(B47="",(S47*(1-$W$1)),(IF(B47=1,(S47*(1-$W$1)),(IF(B47=2,(S47*(1-$W$1)),(IF(B47=3,(S47*(1-$W$1)),(IF(B47=4,(S47*(1)))))))))))) -> 20234.05 | X47: =W47*0.16 -> 3237.448 | Y47: =W47+X47 -> 23471.498 | Z47: =(IF(B47="",(S47*(1-$Z$1)),(IF(B47=1,(S47*(1-$Z$1)),(IF(B47=2,(S47*(1-$Z$1)),(IF(B47=3,(S47*(1-$Z$1)),(IF(B47=4,(S47*(1)))))))))))) -> 19169.1 | AA47: =Z47*0.16 -> 3067.056 | AB47: =Z47+AA47 -> 22236.156 | AC47: =(IF(B47="",(S47*(1-$AC$1)),(IF(B47=1,(S47*(1-$AC$1)),(IF(B47=2,(S47*(1-0.15)),(IF(B47=3,(S47*(1-0.1)),(IF(B47=4,(S47*(1)))))))))))) -> 19169.1 | AD47: =AC47*0.16 -> 3067.056 | AE47: =AC47+AD47 -> 22236.156 | AF47: =(IF(B47="",(S47*(1-$AF$1)),(IF(B47=1,(S47*(1-$AF$1)),(IF(B47=2,(S47*(1-0.15)),(IF(B47=3,(S47*(1-0.1)),(IF(B47=4,(S47*(1)))))))))))) -> 19169.1 | AG47: =AF47*0.16 -> 3067.056 | AH47: =AF47+AG47 -> 22236.156 | AI47: =(IF(B47="",(S47*(1-$AI$1)),(IF(B47=1,(S47*(1-$AI$1)),(IF(B47=2,(S47*(1-0.15)),(IF(B47=3,(S47*(1-0.1)),(IF(B47=4,(S47*(1)))))))))))) -> 19169.1 | AJ47: =AI47*0.16 -> 3067.056 | AK47: =AI47+AJ47 -> 22236.156 | AL47: =IFERROR(__xludf.DUMMYFUNCTION("""COMPUTED_VALUE"""),1.0) -> 1 | AN47: =IFERROR(__xludf.DUMMYFUNCTION("""COMPUTED_VALUE""")," C") -> C | AO47: =IFERROR(__xludf.DUMMYFUNCTION("""COMPUTED_VALUE""")," BA22") -> BA22 | AP47: =IFERROR(__xludf.DUMMYFUNCTION("""COMPUTED_VALUE""")," PZA") -> PZA | AQ47: =IFERROR(__xludf.DUMMYFUNCTION("""COMPUTED_VALUE""")," REF") -> REF | AR47: =IFERROR(__xludf.DUMMYFUNCTION("""COMPUTED_VALUE""")," BALERO 30206 ZKL/ZVL") -> BALERO 30206 ZKL/ZVL | AS47: =IFERROR(__xludf.DUMMYFUNCTION("""COMPUTED_VALUE""")," BALERO 30206 ZKL/ZVL") -> BALERO 30206 ZKL/ZVL | AT47: =IFERROR(__xludf.DUMMYFUNCTION("""COMPUTED_VALUE"""),20.0) -> 20 | AY47: =IFERROR(__xludf.DUMMYFUNCTION("""COMPUTED_VALUE"""),179.0) -> 179 | AZ47: =IFERROR(__xludf.DUMMYFUNCTION("""COMPUTED_VALUE"""),193.0) -> 193 | BA47: =IFERROR(__xludf.DUMMYFUNCTION("""COMPUTED_VALUE"""),208.44000000000003) -> 208.44 | BB47: =IFERROR(__xludf.DUMMYFUNCTION("""COMPUTED_VALUE"""),208.44000000000003) -> 208.44 | BC47: =IFERROR(__xludf.DUMMYFUNCTION("""COMPUTED_VALUE"""),233.0) -> 233 | BD47: =IFERROR(__xludf.DUMMYFUNCTION("""COMPUTED_VALUE"""),245.0) -> 245 | BE47: =IFERROR(__xludf.DUMMYFUNCTION("""COMPUTED_VALUE"""),39.2) -> 39.2 | BF47: =IFERROR(__xludf.DUMMYFUNCTION("""COMPUTED_VALUE"""),284.2) -> 284.2 | BG47: =IFERROR(__xludf.DUMMYFUNCTION("""COMPUTED_VALUE"""),0.05150214592274678) -> 0.051502146 | BH47: =IFERROR(__xludf.DUMMYFUNCTION("""COMPUTED_VALUE"""),232.75) -> 232.75 | BI47: =IFERROR(__xludf.DUMMYFUNCTION("""COMPUTED_VALUE"""),37.24) -> 37.24 | BJ47: =IFERROR(__xludf.DUMMYFUNCTION("""COMPUTED_VALUE"""),269.99) -> 269.99 | BK47: =IFERROR(__xludf.DUMMYFUNCTION("""COMPUTED_VALUE"""),220.5) -> 220.5 | BL47: =IFERROR(__xludf.DUMMYFUNCTION("""COMPUTED_VALUE"""),35.28) -> 35.28 | BM47: =IFERROR(__xludf.DUMMYFUNCTION("""COMPUTED_VALUE"""),255.78) -> 255.78 | BN47: =IFERROR(__xludf.DUMMYFUNCTION("""COMPUTED_VALUE"""),208.25) -> 208.25 | BO47: =IFERROR(__xludf.DUMMYFUNCTION("""COMPUTED_VALUE"""),33.32) -> 33.32 | BP47: =IFERROR(__xludf.DUMMYFUNCTION("""COMPUTED_VALUE"""),241.57) -> 241.57 | BQ47: =IFERROR(__xludf.DUMMYFUNCTION("""COMPUTED_VALUE"""),203.35) -> 203.35 | BR47: =IFERROR(__xludf.DUMMYFUNCTION("""COMPUTED_VALUE"""),32.536) -> 32.536 | BS47: =IFERROR(__xludf.DUMMYFUNCTION("""COMPUTED_VALUE"""),235.886) -> 235.886 | BT47: =IFERROR(__xludf.DUMMYFUNCTION("""COMPUTED_VALUE"""),196.0) -> 196 | BU47: =IFERROR(__xludf.DUMMYFUNCTION("""COMPUTED_VALUE"""),31.36) -> 31.36 | BV47: =IFERROR(__xludf.DUMMYFUNCTION("""COMPUTED_VALUE"""),227.36) -> 227.36
B48: 3 | C48: E | D48: MG50 | E48: PZA | F48: TGA | G48: AMASADORA DE 100 KG. CON ASPA, FLECHA EN ACERO INOX. T-304 PARA TAMAL G.A. | H48: AMASADORA 100KG C/ASPA FLE INOX P/TAMAL | I48: =IF(D48="","",LEN(H48)) -> 39 | O48: 37923 | P48: 40956.84 | Q48: 40956.84 | R48: 45156 | S48: 47414 | T48: =S48*0.16 -> 7586.24 | U48: =S48+T48 -> 55000.24 | V48: =(S48-R48)/R48 -> 0.050004429 | W48: =(IF(B48="",(S48*(1-$W$1)),(IF(B48=1,(S48*(1-$W$1)),(IF(B48=2,(S48*(1-$W$1)),(IF(B48=3,(S48*(1-$W$1)),(IF(B48=4,(S48*(1)))))))))))) -> 45043.3 | X48: =W48*0.16 -> 7206.928 | Y48: =W48+X48 -> 52250.228 | Z48: =(IF(B48="",(S48*(1-$Z$1)),(IF(B48=1,(S48*(1-$Z$1)),(IF(B48=2,(S48*(1-$Z$1)),(IF(B48=3,(S48*(1-$Z$1)),(IF(B48=4,(S48*(1)))))))))))) -> 42672.6 | AA48: =Z48*0.16 -> 6827.616 | AB48: =Z48+AA48 -> 49500.216 | AC48: =(IF(B48="",(S48*(1-$AC$1)),(IF(B48=1,(S48*(1-$AC$1)),(IF(B48=2,(S48*(1-0.15)),(IF(B48=3,(S48*(1-0.1)),(IF(B48=4,(S48*(1)))))))))))) -> 42672.6 | AD48: =AC48*0.16 -> 6827.616 | AE48: =AC48+AD48 -> 49500.216 | AF48: =(IF(B48="",(S48*(1-$AF$1)),(IF(B48=1,(S48*(1-$AF$1)),(IF(B48=2,(S48*(1-0.15)),(IF(B48=3,(S48*(1-0.1)),(IF(B48=4,(S48*(1)))))))))))) -> 42672.6 | AG48: =AF48*0.16 -> 6827.616 | AH48: =AF48+AG48 -> 49500.216 | AI48: =(IF(B48="",(S48*(1-$AI$1)),(IF(B48=1,(S48*(1-$AI$1)),(IF(B48=2,(S48*(1-0.15)),(IF(B48=3,(S48*(1-0.1)),(IF(B48=4,(S48*(1)))))))))))) -> 42672.6 | AJ48: =AI48*0.16 -> 6827.616 | AK48: =AI48+AJ48 -> 49500.216 | AL48: =IFERROR(__xludf.DUMMYFUNCTION("""COMPUTED_VALUE"""),1.0) -> 1 | AN48: =IFERROR(__xludf.DUMMYFUNCTION("""COMPUTED_VALUE""")," C") -> C | AO48: =IFERROR(__xludf.DUMMYFUNCTION("""COMPUTED_VALUE""")," BA01") -> BA01 | AP48: =IFERROR(__xludf.DUMMYFUNCTION("""COMPUTED_VALUE""")," PZA") -> PZA | AQ48: =IFERROR(__xludf.DUMMYFUNCTION("""COMPUTED_VALUE""")," REF") -> REF | AR48: =IFERROR(__xludf.DUMMYFUNCTION("""COMPUTED_VALUE""")," BALERO 3204 ZKL/ZVL") -> BALERO 3204 ZKL/ZVL | AS48: =IFERROR(__xludf.DUMMYFUNCTION("""COMPUTED_VALUE""")," BALERO 3204 ZKL/ZVL") -> BALERO 3204 ZKL/ZVL | AT48: =IFERROR(__xludf.DUMMYFUNCTION("""COMPUTED_VALUE"""),19.0) -> 19 | AY48: =IFERROR(__xludf.DUMMYFUNCTION("""COMPUTED_VALUE"""),288.0) -> 288 | AZ48: =IFERROR(__xludf.DUMMYFUNCTION("""COMPUTED_VALUE"""),311.0) -> 311 | BA48: =IFERROR(__xludf.DUMMYFUNCTION("""COMPUTED_VALUE"""),335.88) -> 335.88 | BB48: =IFERROR(__xludf.DUMMYFUNCTION("""COMPUTED_VALUE"""),335.88) -> 335.88 | BC48: =IFERROR(__xludf.DUMMYFUNCTION("""COMPUTED_VALUE"""),386.0) -> 386 | BD48: =IFERROR(__xludf.DUMMYFUNCTION("""COMPUTED_VALUE"""),405.0) -> 405 | BE48: =IFERROR(__xludf.DUMMYFUNCTION("""COMPUTED_VALUE"""),64.8) -> 64.8 | BF48: =IFERROR(__xludf.DUMMYFUNCTION("""COMPUTED_VALUE"""),469.8) -> 469.8 | BG48: =IFERROR(__xludf.DUMMYFUNCTION("""COMPUTED_VALUE"""),0.04922279792746114) -> 0.049222798 | BH48: =IFERROR(__xludf.DUMMYFUNCTION("""COMPUTED_VALUE"""),384.75) -> 384.75 | BI48: =IFERROR(__xludf.DUMMYFUNCTION("""COMPUTED_VALUE"""),61.56) -> 61.56 | BJ48: =IFERROR(__xludf.DUMMYFUNCTION("""COMPUTED_VALUE"""),446.31) -> 446.31 | BK48: =IFERROR(__xludf.DUMMYFUNCTION("""COMPUTED_VALUE"""),364.5) -> 364.5 | BL48: =IFERROR(__xludf.DUMMYFUNCTION("""COMPUTED_VALUE"""),58.32) -> 58.32 | BM48: =IFERROR(__xludf.DUMMYFUNCTION("""COMPUTED_VALUE"""),422.82) -> 422.82 | BN48: =IFERROR(__xludf.DUMMYFUNCTION("""COMPUTED_VALUE"""),344.25) -> 344.25 | BO48: =IFERROR(__xludf.DUMMYFUNCTION("""COMPUTED_VALUE"""),55.08) -> 55.08 | BP48: =IFERROR(__xludf.DUMMYFUNCTION("""COMPUTED_VALUE"""),399.33) -> 399.33 | BQ48: =IFERROR(__xludf.DUMMYFUNCTION("""COMPUTED_VALUE"""),336.15) -> 336.15 | BR48: =IFERROR(__xludf.DUMMYFUNCTION("""COMPUTED_VALUE"""),53.784) -> 53.784 | BS48: =IFERROR(__xludf.DUMMYFUNCTION("""COMPUTED_VALUE"""),389.93399999999997) -> 389.934 | BT48: =IFERROR(__xludf.DUMMYFUNCTION("""COMPUTED_VALUE"""),324.0) -> 324 | BU48: =IFERROR(__xludf.DUMMYFUNCTION("""COMPUTED_VALUE"""),51.84) -> 51.84 | BV48: =IFERROR(__xludf.DUMMYFUNCTION("""COMPUTED_VALUE"""),375.84000000000003) -> 375.84
B49: 3 | C49: E | D49: MG58 | E49: PZA | F49: TGA | G49: AMASADORA DE 100 KG. CON PALETAS FUNDIDAS Y FLECHA EN ACERO INOX. T-304 ACABADO HIGIÉNICO, CON BANCO EN ACERO INOX. 304 G.A. | H49: AMASADORA 100K PAL FND FLE CHAS INX S/ES | I49: =IF(D49="","",LEN(H49)) -> 40 | O49: 60002 | P49: 64802.16 | Q49: 64802.16 | R49: 71445 | S49: 75017 | T49: =S49*0.16 -> 12002.72 | U49: =S49+T49 -> 87019.72 | V49: =(S49-R49)/R49 -> 0.049996501 | W49: =(IF(B49="",(S49*(1-$W$1)),(IF(B49=1,(S49*(1-$W$1)),(IF(B49=2,(S49*(1-$W$1)),(IF(B49=3,(S49*(1-$W$1)),(IF(B49=4,(S49*(1)))))))))))) -> 71266.15 | X49: =W49*0.16 -> 11402.584 | Y49: =W49+X49 -> 82668.734 | Z49: =(IF(B49="",(S49*(1-$Z$1)),(IF(B49=1,(S49*(1-$Z$1)),(IF(B49=2,(S49*(1-$Z$1)),(IF(B49=3,(S49*(1-$Z$1)),(IF(B49=4,(S49*(1)))))))))))) -> 67515.3 | AA49: =Z49*0.16 -> 10802.448 | AB49: =Z49+AA49 -> 78317.748 | AC49: =(IF(B49="",(S49*(1-$AC$1)),(IF(B49=1,(S49*(1-$AC$1)),(IF(B49=2,(S49*(1-0.15)),(IF(B49=3,(S49*(1-0.1)),(IF(B49=4,(S49*(1)))))))))))) -> 67515.3 | AD49: =AC49*0.16 -> 10802.448 | AE49: =AC49+AD49 -> 78317.748 | AF49: =(IF(B49="",(S49*(1-$AF$1)),(IF(B49=1,(S49*(1-$AF$1)),(IF(B49=2,(S49*(1-0.15)),(IF(B49=3,(S49*(1-0.1)),(IF(B49=4,(S49*(1)))))))))))) -> 67515.3 | AG49: =AF49*0.16 -> 10802.448 | AH49: =AF49+AG49 -> 78317.748 | AI49: =(IF(B49="",(S49*(1-$AI$1)),(IF(B49=1,(S49*(1-$AI$1)),(IF(B49=2,(S49*(1-0.15)),(IF(B49=3,(S49*(1-0.1)),(IF(B49=4,(S49*(1)))))))))))) -> 67515.3 | AJ49: =AI49*0.16 -> 10802.448 | AK49: =AI49+AJ49 -> 78317.748 | AL49: =IFERROR(__xludf.DUMMYFUNCTION("""COMPUTED_VALUE"""),1.0) -> 1 | AN49: =IFERROR(__xludf.DUMMYFUNCTION("""COMPUTED_VALUE""")," C") -> C | AO49: =IFERROR(__xludf.DUMMYFUNCTION("""COMPUTED_VALUE""")," BA23") -> BA23 | AP49: =IFERROR(__xludf.DUMMYFUNCTION("""COMPUTED_VALUE""")," PZA") -> PZA | AQ49: =IFERROR(__xludf.DUMMYFUNCTION("""COMPUTED_VALUE""")," REF") -> REF | AR49: =IFERROR(__xludf.DUMMYFUNCTION("""COMPUTED_VALUE""")," BALERO 32207 MULTIMARCA") -> BALERO 32207 MULTIMARCA | AS49: =IFERROR(__xludf.DUMMYFUNCTION("""COMPUTED_VALUE""")," BALERO 32207 MULTIMARCA") -> BALERO 32207 MULTIMARCA | AT49: =IFERROR(__xludf.DUMMYFUNCTION("""COMPUTED_VALUE"""),23.0) -> 23 | AY49: =IFERROR(__xludf.DUMMYFUNCTION("""COMPUTED_VALUE"""),150.0) -> 150 | AZ49: =IFERROR(__xludf.DUMMYFUNCTION("""COMPUTED_VALUE"""),162.0) -> 162 | BA49: =IFERROR(__xludf.DUMMYFUNCTION("""COMPUTED_VALUE"""),174.96) -> 174.96 | BB49: =IFERROR(__xludf.DUMMYFUNCTION("""COMPUTED_VALUE"""),174.96) -> 174.96 | BC49: =IFERROR(__xludf.DUMMYFUNCTION("""COMPUTED_VALUE"""),201.0) -> 201 | BD49: =IFERROR(__xludf.DUMMYFUNCTION("""COMPUTED_VALUE"""),211.0) -> 211 | BE49: =IFERROR(__xludf.DUMMYFUNCTION("""COMPUTED_VALUE"""),33.76) -> 33.76 | BF49: =IFERROR(__xludf.DUMMYFUNCTION("""COMPUTED_VALUE"""),244.76) -> 244.76 | BG49: =IFERROR(__xludf.DUMMYFUNCTION("""COMPUTED_VALUE"""),0.04975124378109453) -> 0.049751244 | BH49: =IFERROR(__xludf.DUMMYFUNCTION("""COMPUTED_VALUE"""),200.45) -> 200.45 | BI49: =IFERROR(__xludf.DUMMYFUNCTION("""COMPUTED_VALUE"""),32.071999999999996) -> 32.072 | BJ49: =IFERROR(__xludf.DUMMYFUNCTION("""COMPUTED_VALUE"""),232.522) -> 232.522 | BK49: =IFERROR(__xludf.DUMMYFUNCTION("""COMPUTED_VALUE"""),189.9) -> 189.9 | BL49: =IFERROR(__xludf.DUMMYFUNCTION("""COMPUTED_VALUE"""),30.384) -> 30.384 | BM49: =IFERROR(__xludf.DUMMYFUNCTION("""COMPUTED_VALUE"""),220.284) -> 220.284 | BN49: =IFERROR(__xludf.DUMMYFUNCTION("""COMPUTED_VALUE"""),179.35) -> 179.35 | BO49: =IFERROR(__xludf.DUMMYFUNCTION("""COMPUTED_VALUE"""),28.695999999999998) -> 28.696 | BP49: =IFERROR(__xludf.DUMMYFUNCTION("""COMPUTED_VALUE"""),208.046) -> 208.046 | BQ49: =IFERROR(__xludf.DUMMYFUNCTION("""COMPUTED_VALUE"""),175.13) -> 175.13 | BR49: =IFERROR(__xludf.DUMMYFUNCTION("""COMPUTED_VALUE"""),28.0208) -> 28.0208 | BS49: =IFERROR(__xludf.DUMMYFUNCTION("""COMPUTED_VALUE"""),203.1508) -> 203.1508 | BT49: =IFERROR(__xludf.DUMMYFUNCTION("""COMPUTED_VALUE"""),168.8) -> 168.8 | BU49: =IFERROR(__xludf.DUMMYFUNCTION("""COMPUTED_VALUE"""),27.008000000000003) -> 27.008 | BV49: =IFERROR(__xludf.DUMMYFUNCTION("""COMPUTED_VALUE"""),195.80800000000002) -> 195.808
B50: 3 | C50: E | D50: MG62 | E50: PZA | F50: TGA | G50: AMASADORA DE 100 KG. EN ACERO INOX. 304, BANCO EN ACERO INOX. 304, CON ASPA 304, MOTOR 3 HP., REDUCTOR Y TAPA | I50: =IF(D50="","",LEN(H50)) -> 0 | O50: 73996 | P50: 79915.68 | Q50: 79915.68 | R50: 88108 | S50: 92513 | T50: =S50*0.16 -> 14802.08 | U50: =S50+T50 -> 107315.08 | V50: =(S50-R50)/R50 -> 0.04999546 | W50: =(IF(B50="",(S50*(1-$W$1)),(IF(B50=1,(S50*(1-$W$1)),(IF(B50=2,(S50*(1-$W$1)),(IF(B50=3,(S50*(1-$W$1)),(IF(B50=4,(S50*(1)))))))))))) -> 87887.35 | X50: =W50*0.16 -> 14061.976 | Y50: =W50+X50 -> 101949.33 | Z50: =(IF(B50="",(S50*(1-$Z$1)),(IF(B50=1,(S50*(1-$Z$1)),(IF(B50=2,(S50*(1-$Z$1)),(IF(B50=3,(S50*(1-$Z$1)),(IF(B50=4,(S50*(1)))))))))))) -> 83261.7 | AA50: =Z50*0.16 -> 13321.872 | AB50: =Z50+AA50 -> 96583.572 | AC50: =(IF(B50="",(S50*(1-$AC$1)),(IF(B50=1,(S50*(1-$AC$1)),(IF(B50=2,(S50*(1-0.15)),(IF(B50=3,(S50*(1-0.1)),(IF(B50=4,(S50*(1)))))))))))) -> 83261.7 | AD50: =AC50*0.16 -> 13321.872 | AE50: =AC50+AD50 -> 96583.572 | AF50: =(IF(B50="",(S50*(1-$AF$1)),(IF(B50=1,(S50*(1-$AF$1)),(IF(B50=2,(S50*(1-0.15)),(IF(B50=3,(S50*(1-0.1)),(IF(B50=4,(S50*(1)))))))))))) -> 83261.7 | AG50: =AF50*0.16 -> 13321.872 | AH50: =AF50+AG50 -> 96583.572 | AI50: =(IF(B50="",(S50*(1-$AI$1)),(IF(B50=1,(S50*(1-$AI$1)),(IF(B50=2,(S50*(1-0.15)),(IF(B50=3,(S50*(1-0.1)),(IF(B50=4,(S50*(1)))))))))))) -> 83261.7 | AJ50: =AI50*0.16 -> 13321.872 | AK50: =AI50+AJ50 -> 96583.572 | AL50: =IFERROR(__xludf.DUMMYFUNCTION("""COMPUTED_VALUE"""),1.0) -> 1 | AN50: =IFERROR(__xludf.DUMMYFUNCTION("""COMPUTED_VALUE""")," C") -> C | AO50: =IFERROR(__xludf.DUMMYFUNCTION("""COMPUTED_VALUE""")," BA24") -> BA24 | AP50: =IFERROR(__xludf.DUMMYFUNCTION("""COMPUTED_VALUE""")," PZA") -> PZA | AQ50: =IFERROR(__xludf.DUMMYFUNCTION("""COMPUTED_VALUE""")," REF") -> REF | AR50: =IFERROR(__xludf.DUMMYFUNCTION("""COMPUTED_VALUE""")," BALERO 32207 ZKL/ZVL") -> BALERO 32207 ZKL/ZVL | AS50: =IFERROR(__xludf.DUMMYFUNCTION("""COMPUTED_VALUE""")," BALERO 32207 ZKL/ZVL") -> BALERO 32207 ZKL/ZVL | AT50: =IFERROR(__xludf.DUMMYFUNCTION("""COMPUTED_VALUE"""),20.0) -> 20 | AY50: =IFERROR(__xludf.DUMMYFUNCTION("""COMPUTED_VALUE"""),268.0) -> 268 | AZ50: =IFERROR(__xludf.DUMMYFUNCTION("""COMPUTED_VALUE"""),289.0) -> 289 | BA50: =IFERROR(__xludf.DUMMYFUNCTION("""COMPUTED_VALUE"""),312.12) -> 312.12 | BB50: =IFERROR(__xludf.DUMMYFUNCTION("""COMPUTED_VALUE"""),312.12) -> 312.12 | BC50: =IFERROR(__xludf.DUMMYFUNCTION("""COMPUTED_VALUE"""),348.0) -> 348 | BD50: =IFERROR(__xludf.DUMMYFUNCTION("""COMPUTED_VALUE"""),365.0) -> 365 | BE50: =IFERROR(__xludf.DUMMYFUNCTION("""COMPUTED_VALUE"""),58.4) -> 58.4 | BF50: =IFERROR(__xludf.DUMMYFUNCTION("""COMPUTED_VALUE"""),423.4) -> 423.4 | BG50: =IFERROR(__xludf.DUMMYFUNCTION("""COMPUTED_VALUE"""),0.04885057471264368) -> 0.048850575 | BH50: =IFERROR(__xludf.DUMMYFUNCTION("""COMPUTED_VALUE"""),346.75) -> 346.75 | BI50: =IFERROR(__xludf.DUMMYFUNCTION("""COMPUTED_VALUE"""),55.480000000000004) -> 55.48 | BJ50: =IFERROR(__xludf.DUMMYFUNCTION("""COMPUTED_VALUE"""),402.23) -> 402.23 | BK50: =IFERROR(__xludf.DUMMYFUNCTION("""COMPUTED_VALUE"""),328.5) -> 328.5 | BL50: =IFERROR(__xludf.DUMMYFUNCTION("""COMPUTED_VALUE"""),52.56) -> 52.56 | BM50: =IFERROR(__xludf.DUMMYFUNCTION("""COMPUTED_VALUE"""),381.06) -> 381.06 | BN50: =IFERROR(__xludf.DUMMYFUNCTION("""COMPUTED_VALUE"""),310.25) -> 310.25 | BO50: =IFERROR(__xludf.DUMMYFUNCTION("""COMPUTED_VALUE"""),49.64) -> 49.64 | BP50: =IFERROR(__xludf.DUMMYFUNCTION("""COMPUTED_VALUE"""),359.89) -> 359.89 | BQ50: =IFERROR(__xludf.DUMMYFUNCTION("""COMPUTED_VALUE"""),302.95) -> 302.95 | BR50: =IFERROR(__xludf.DUMMYFUNCTION("""COMPUTED_VALUE"""),48.472) -> 48.472 | BS50: =IFERROR(__xludf.DUMMYFUNCTION("""COMPUTED_VALUE"""),351.42199999999997) -> 351.422 | BT50: =IFERROR(__xludf.DUMMYFUNCTION("""COMPUTED_VALUE"""),292.0) -> 292 | BU50: =IFERROR(__xludf.DUMMYFUNCTION("""COMPUTED_VALUE"""),46.72) -> 46.72 | BV50: =IFERROR(__xludf.DUMMYFUNCTION("""COMPUTED_VALUE"""),338.72) -> 338.72
B51: 3 | C51: E | D51: MM03 | E51: PZA | F51: TNO | G51: AMASADORA DE 100 KG. EN ACERO INOX. T-430 | I51: =IF(D51="","",LEN(H51)) -> 0 | O51: 20480 | P51: 22118.4 | Q51: 22118.4 | R51: 24386 | S51: 25605 | T51: =S51*0.16 -> 4096.8 | U51: =S51+T51 -> 29701.8 | V51: =(S51-R51)/R51 -> 0.049987698 | W51: =(IF(B51="",(S51*(1-$W$1)),(IF(B51=1,(S51*(1-$W$1)),(IF(B51=2,(S51*(1-$W$1)),(IF(B51=3,(S51*(1-$W$1)),(IF(B51=4,(S51*(1)))))))))))) -> 24324.75 | X51: =W51*0.16 -> 3891.96 | Y51: =W51+X51 -> 28216.71 | Z51: =(IF(B51="",(S51*(1-$Z$1)),(IF(B51=1,(S51*(1-$Z$1)),(IF(B51=2,(S51*(1-$Z$1)),(IF(B51=3,(S51*(1-$Z$1)),(IF(B51=4,(S51*(1)))))))))))) -> 23044.5 | AA51: =Z51*0.16 -> 3687.12 | AB51: =Z51+AA51 -> 26731.62 | AC51: =(IF(B51="",(S51*(1-$AC$1)),(IF(B51=1,(S51*(1-$AC$1)),(IF(B51=2,(S51*(1-0.15)),(IF(B51=3,(S51*(1-0.1)),(IF(B51=4,(S51*(1)))))))))))) -> 23044.5 | AD51: =AC51*0.16 -> 3687.12 | AE51: =AC51+AD51 -> 26731.62 | AF51: =(IF(B51="",(S51*(1-$AF$1)),(IF(B51=1,(S51*(1-$AF$1)),(IF(B51=2,(S51*(1-0.15)),(IF(B51=3,(S51*(1-0.1)),(IF(B51=4,(S51*(1)))))))))))) -> 23044.5 | AG51: =AF51*0.16 -> 3687.12 | AH51: =AF51+AG51 -> 26731.62 | AI51: =(IF(B51="",(S51*(1-$AI$1)),(IF(B51=1,(S51*(1-$AI$1)),(IF(B51=2,(S51*(1-0.15)),(IF(B51=3,(S51*(1-0.1)),(IF(B51=4,(S51*(1)))))))))))) -> 23044.5 | AJ51: =AI51*0.16 -> 3687.12 | AK51: =AI51+AJ51 -> 26731.62 | AL51: =IFERROR(__xludf.DUMMYFUNCTION("""COMPUTED_VALUE"""),1.0) -> 1 | AN51: =IFERROR(__xludf.DUMMYFUNCTION("""COMPUTED_VALUE""")," C") -> C | AO51: =IFERROR(__xludf.DUMMYFUNCTION("""COMPUTED_VALUE""")," BA75") -> BA75 | AP51: =IFERROR(__xludf.DUMMYFUNCTION("""COMPUTED_VALUE""")," PZA") -> PZA | AQ51: =IFERROR(__xludf.DUMMYFUNCTION("""COMPUTED_VALUE""")," REF") -> REF | AR51: =IFERROR(__xludf.DUMMYFUNCTION("""COMPUTED_VALUE""")," BALERO 32209 MULTIMARCA") -> BALERO 32209 MULTIMARCA | AS51: =IFERROR(__xludf.DUMMYFUNCTION("""COMPUTED_VALUE""")," BALERO 32209 MULTIMARCA") -> BALERO 32209 MULTIMARCA | AT51: =IFERROR(__xludf.DUMMYFUNCTION("""COMPUTED_VALUE"""),23.0) -> 23 | BA51: =IFERROR(__xludf.DUMMYFUNCTION("""COMPUTED_VALUE"""),225.0) -> 225 | BB51: =IFERROR(__xludf.DUMMYFUNCTION("""COMPUTED_VALUE"""),225.0) -> 225 | BC51: =IFERROR(__xludf.DUMMYFUNCTION("""COMPUTED_VALUE"""),237.0) -> 237 | BD51: =IFERROR(__xludf.DUMMYFUNCTION("""COMPUTED_VALUE"""),249.0) -> 249 | BE51: =IFERROR(__xludf.DUMMYFUNCTION("""COMPUTED_VALUE"""),39.84) -> 39.84 | BF51: =IFERROR(__xludf.DUMMYFUNCTION("""COMPUTED_VALUE"""),288.84000000000003) -> 288.84 | BG51: =IFERROR(__xludf.DUMMYFUNCTION("""COMPUTED_VALUE"""),0.05063291139240506) -> 0.050632911 | BH51: =IFERROR(__xludf.DUMMYFUNCTION("""COMPUTED_VALUE"""),236.54999999999998) -> 236.55 | BI51: =IFERROR(__xludf.DUMMYFUNCTION("""COMPUTED_VALUE"""),37.848) -> 37.848 | BJ51: =IFERROR(__xludf.DUMMYFUNCTION("""COMPUTED_VALUE"""),274.39799999999997) -> 274.398 | BK51: =IFERROR(__xludf.DUMMYFUNCTION("""COMPUTED_VALUE"""),224.1) -> 224.1 | BL51: =IFERROR(__xludf.DUMMYFUNCTION("""COMPUTED_VALUE"""),35.856) -> 35.856 | BM51: =IFERROR(__xludf.DUMMYFUNCTION("""COMPUTED_VALUE"""),259.956) -> 259.956 | BN51: =IFERROR(__xludf.DUMMYFUNCTION("""COMPUTED_VALUE"""),211.65) -> 211.65 | BO51: =IFERROR(__xludf.DUMMYFUNCTION("""COMPUTED_VALUE"""),33.864000000000004) -> 33.864 | BP51: =IFERROR(__xludf.DUMMYFUNCTION("""COMPUTED_VALUE"""),245.514) -> 245.514 | BQ51: =IFERROR(__xludf.DUMMYFUNCTION("""COMPUTED_VALUE"""),206.67) -> 206.67 | BR51: =IFERROR(__xludf.DUMMYFUNCTION("""COMPUTED_VALUE"""),33.0672) -> 33.0672 | BS51: =IFERROR(__xludf.DUMMYFUNCTION("""COMPUTED_VALUE"""),239.73719999999997) -> 239.7372 | BT51: =IFERROR(__xludf.DUMMYFUNCTION("""COMPUTED_VALUE"""),199.20000000000002) -> 199.2 | BU51: =IFERROR(__xludf.DUMMYFUNCTION("""COMPUTED_VALUE"""),31.872000000000003) -> 31.872 | BV51: =IFERROR(__xludf.DUMMYFUNCTION("""COMPUTED_VALUE"""),231.07200000000003) -> 231.072
